Workbook

Sheet Index & Read Me
B2: WORKBOOK GUIDE · INDEX & READ ME
B3: Data Center Template, Northern Virginia — 90 MW Tier III hyperscale data center. Owner-side cost estimate + capital-program controls toolkit. Independent, illustrative model — not affiliated with any actual named project.
B5: TOTAL CAMPUS INVESTMENT | C5: IT CAPACITY · COST / MW · GROSS AREA · TABS
B6: ='Construction Budget'!H842 -> 1.0883418e+09 | C6: ='Campus Rollup'!D16&" MW · $"&TEXT('Construction Budget'!H843/1000000,"0.0")&"M / MW · "&TEXT('Campus Rollup'!C16,"#,##0")&" SF · 39 sheets" -> 90 MW · $12.1M / MW · 800,000 SF · 39 sheets
B8: EXECUTIVE & QA
B9: =HYPERLINK("#'Dashboard'!A1","Dashboard") -> Dashboard | C9: Executive summary — headline KPIs, five cost charts, six QC tie checks, and live delivery metrics (EVM / risk / procurement).
B10: =HYPERLINK("#'Basis of Estimate'!A1","Basis of Estimate") -> Basis of Estimate | C10: Methodology, inclusions / exclusions, key assumptions, and the scenario-control & value-engineering notes.
B11: COST ESTIMATE
B12: =HYPERLINK("#'Construction Budget'!A1","Construction Budget") -> Construction Budget | C12: The estimate spine — 25 CSI divisions, ~400 line items building to the $1.09B grand total.
B13: =HYPERLINK("#'Unit Cost Database'!A1","Unit Cost Database") -> Unit Cost Database | C13: Standard reference unit pricing; the active pricing tier (set on Scenario & Presets) drives the estimate.
B14: =HYPERLINK("#'Location Factors'!A1","Location Factors") -> Location Factors | C14: Regional cost-adjustment factors for the Loudoun County, VA market.
B15: =HYPERLINK("#'Allowances & Alternates'!A1","Allowances & Alternates") -> Allowances & Alternates | C15: Carried allowances and priced add/deduct alternates.
B16: =HYPERLINK("#'CSA Summary'!A1","CSA Summary") -> CSA Summary | C16: Civil / structural / architectural scope breakout.
B17: =HYPERLINK("#'Variance Tracker'!A1","Variance Tracker") -> Variance Tracker | C17: Estimate vs. subcontractor pricing by division.
B18: =HYPERLINK("#'Client Proposal'!A1","Client Proposal") -> Client Proposal | C18: Client-facing cost summary (Turner & Townsend format).
B19: CAMPUS & PROGRAM
B20: =HYPERLINK("#'Campus Rollup'!A1","Campus Rollup") -> Campus Rollup | C20: Per-building + shared-infrastructure rollup to the campus total; the hub every other tab references.
B21: =HYPERLINK("#'Phased Capital Plan'!A1","Phased Capital Plan") -> Phased Capital Plan | C21: Six-building sequential deployment; Phase 1 reconciles exactly to this estimate, then escalates to build-out.
B22: =HYPERLINK("#'Milestone Tracker'!A1","Milestone Tracker") -> Milestone Tracker | C22: Estimate evolution across design milestones (Concept → SD → DD → CD → GMP).
B23: DELIVERY CONTROLS
B24: =HYPERLINK("#'Cash Flow & EVM'!A1","Cash Flow & EVM") -> Cash Flow & EVM | C24: Earned-value S-curve with SPI / CPI, EAC / ETC, and PV reconciliation to budget at completion.
B25: =HYPERLINK("#'Draw Schedule'!A1","Draw Schedule") -> Draw Schedule | C25: 30-month construction draw / cash-flow schedule.
B26: =HYPERLINK("#'Risk & Contingency'!A1","Risk & Contingency") -> Risk & Contingency | C26: Risk register, analytical P50 / P80 / P90, and a 10,000-iteration Monte Carlo vs. the carried contingency.
B27: =HYPERLINK("#'Change Order Log'!A1","Change Order Log") -> Change Order Log | C27: Change orders with type / status / funding and a running contingency drawdown.
B28: =HYPERLINK("#'Procurement & Long-Lead'!A1","Procurement & Long-Lead") -> Procurement & Long-Lead | C28: Equipment lead times, back-calculated order-by dates, and escalation exposure with late-order flags.
B29: Construction Schedule | C29: Cradle-to-grave CPM master schedule — WBS, dependency-linked dates, critical path & month-by-month Gantt; NTP tied to Construction Budget start.
B30: Schedule Acceleration | C30: Scenario model to recover schedule toward the Q3-2028 target — acceleration levers with day-savings, cost premium & risk.
B31: DECISION SUPPORT
B32: =HYPERLINK("#'Scenario & Presets'!A1","Scenario & Presets") -> Scenario & Presets | C32: Control panel — pricing tier, cooling technology, resiliency tier, redundancy, and density presets that drive the whole model.
B33: =HYPERLINK("#'Scenario Comparison'!A1","Scenario Comparison") -> Scenario Comparison | C33: The live scenario beside three saved snapshots with $/MW deltas.
B34: =HYPERLINK("#'Value Engineering'!A1","Value Engineering") -> Value Engineering | C34: VE log with accept / reject decisions and a live VE-adjusted total.
B35: =HYPERLINK("#'Bid Leveling'!A1","Bid Leveling") -> Bid Leveling | C35: Price normalization across bidders for a single package.
B36: =HYPERLINK("#'Bid Evaluation'!A1","Bid Evaluation") -> Bid Evaluation | C36: Weighted CMAR / GMP scoring across six criteria with an auto recommendation.
B37: GC Bid Form | C37: Print-ready general-contractor bid form — 24 CSI divisions, alternates, unit prices, schedule, quals & signature; prices feed Bid Leveling.
B38: Bid Cover Sheet | C38: Sealed-bid cover sheet / envelope label with required-documents checklist; auto-fills from the GC Bid Form.
B39: =HYPERLINK("#'Power & Space Capacity'!A1","Power & Space Capacity") -> Power & Space Capacity | C39: IT-load-driven electrical / cooling / space sizing, binding-constraint, and stranded-capacity analysis.
B40: =HYPERLINK("#'Carbon & Sustainability'!A1","Carbon & Sustainability") -> Carbon & Sustainability | C40: Embodied + operational carbon vs. capex, with decarbonization levers.
B41: =HYPERLINK("#'TCO 8-Year'!A1","TCO 8-Year") -> TCO 8-Year | C41: Eight-year total-cost-of-ownership model.
B42: OWNER ECONOMICS
B43: =HYPERLINK("#'Total Development Cost'!A1","Total Development Cost") -> Total Development Cost | C43: All-in owner budget — construction plus land, utility, owner PM/soft costs, financing (IDC) and contingency.
B44: =HYPERLINK("#'Investment Pro Forma'!A1","Investment Pro Forma") -> Investment Pro Forma | C44: NNN lease-up pro forma — unlevered IRR, NPV, yield-on-cost and a lease-rate x exit-cap sensitivity.
B45: =HYPERLINK("#'Variance-to-Return'!A1","Variance-to-Return") -> Variance-to-Return | C45: Translates cost variance (EVM forecast + bids) into IRR, yield-on-cost and NPV impact.
B46: =HYPERLINK("#'IC Summary'!A1","IC Summary") -> IC Summary | C46: One-page committee view — capitalization, levered + unlevered returns, key risks and recommendation.
B47: =HYPERLINK("#'Sources & Uses'!A1","Sources & Uses") -> Sources & Uses | C47: Reconciles capital required (Uses = TDC) against funding (Sources = senior debt + sponsor equity).
B48: =HYPERLINK("#'Capital Stack & Returns'!A1","Capital Stack & Returns") -> Capital Stack & Returns | C48: Sizes permanent debt to the binding covenant; levered equity IRR, multiple, cash-on-cash and DSCR.
B49: REFERENCE
B50: =HYPERLINK("#'Benchmark Library'!A1","Benchmark Library") -> Benchmark Library | C50: Three-source $/MW benchmark set (T&T DCCI, Mortenson, CBRE).
B51: =HYPERLINK("#'Reference Models'!A1","Reference Models") -> Reference Models | C51: Comparable reference projects.
B53: HOW TO USE
B54: • | C54: Yellow cells are inputs; everything else is a live formula. Blue underlined names above jump to that sheet.
B55: • | C55: Drive the model from Scenario & Presets — pricing tier and cooling technology flow through every dependent tab automatically.
B56: • | C56: Six QC ties on the Dashboard confirm the workbook stays internally reconciled; they should all read “✅ Tie.”
B57: • | C57: Analysis tabs (EVM actuals, risk, procurement, capacity, carbon, bids, change orders, phasing) carry illustrative inputs that recalculate when real project data is entered.

Sheet Dashboard
B3: DATA CENTER CAMPUS
B4: =IFERROR(IF(OR('Campus Rollup'!B3="",'Campus Rollup'!B3=0),"Program Cost Estimate",'Campus Rollup'!B3&" — Cost Estimate"),"Program Cost Estimate") -> Data Center Template, Northern Virginia — Cost Estimate
B5: ="Prepared for "&IFERROR(IF(OR('Campus Rollup'!E3="",'Campus Rollup'!E3=0),"[Client]",'Campus Rollup'!E3),"[Client]")&" | "&IFERROR(IF(OR('Campus Rollup'!B4="",'Campus Rollup'!B4=0),"[Location]",'Campus Rollup'!B4),"[Location]")&" | "&'Campus Rollup'!H3&" Estimate ("&'Campus Rollup'!H4&") | "&TEXT('Campus Rollup'!E4,"mmmm d, yyyy") -> Prepared for Confidential Hyperscaler | Loudoun County, VA | Class 3 (DD) Estimate (−20% / +30%) | May 1, 2026
B8: TIER 1 · INVESTMENT & RETURNS
B11: DEVELOPMENT COST (ALL-IN) | E11: SPONSOR EQUITY | G11: LEVERED EQUITY IRR | I11: EQUITY MULTIPLE (LEV.)
B12: ='Capital Stack & Returns'!B7 -> 1.5128738e+09 | E12: ='Capital Stack & Returns'!B27 -> 6.0514951e+08 | G12: ='Capital Stack & Returns'!B46 -> 0.26651127 | I12: ='Capital Stack & Returns'!B47 -> 5.1974061
B14: UNLEVERED IRR | E14: STABILIZED YIELD-ON-COST | G14: STABILIZED DSCR | I14: DEVELOPMENT MARGIN
B15: ='Investment Pro Forma'!B33 -> 0.1744147 | E15: ='Investment Pro Forma'!B38 -> 0.10901442 | G15: ='Capital Stack & Returns'!B30 -> 2.37264 | I15: ='Investment Pro Forma'!B42 -> 0.67714491
B17: Levered to sponsor equity — figures link live to Capital Stack & Returns, Investment Pro Forma and Sources & Uses.
B18: TIER 2 · COST & BENCHMARKING
B20: TOTAL CAMPUS INVESTMENT | E20: IT CAPACITY | G20: COST PER MW | I20: GROSS BUILT AREA
B21: =IF('Campus Rollup'!H16=0,"$ —",IF('Campus Rollup'!H16>=1000000000,TEXT('Campus Rollup'!H16/1000000000,"$0.00")&"B",TEXT('Campus Rollup'!H16/1000000,"$0.0")&"M")) -> $1.09B | E21: =IF('Campus Rollup'!D16=0,"— MW",TEXT('Campus Rollup'!D16,"0.0")&" MW") -> 90.0 MW | G21: =IF(OR('Campus Rollup'!D16=0,'Campus Rollup'!H16=0),"$ —",TEXT('Campus Rollup'!H16/'Campus Rollup'!D16/1000000,"$0.0")&"M") -> $12.1M | I21: =IF('Campus Rollup'!C16=0,"— SF",IF('Campus Rollup'!C16>=1000000,TEXT('Campus Rollup'!C16/1000000,"0.00")&"M SF",TEXT('Campus Rollup'!C16/1000,"#,##0")&"K SF")) -> 800K SF
B23: =IF(COUNTIF('Campus Rollup'!D8:D13,">0")=0,"Awaiting building program","Across "&COUNTIF('Campus Rollup'!D8:D13,">0")&IF(COUNTIF('Campus Rollup'!D8:D13,">0")=1," building"," buildings")&" + shared infrastructure") -> Across 3 buildings + shared infrastructure | E23: ="Total IT load delivered" -> Total IT load delivered | G23: =IF(OR('Campus Rollup'!D16=0,'Campus Rollup'!H16=0),"vs "&TEXT('Benchmark Library'!L20/1000000,"$0.0")&"M benchmark",IF('Campus Rollup'!H16/'Campus Rollup'!D16<'Benchmark Library'!L20,"▼ Below industry median","▲ Above industry median")) -> ▲ Above industry median | I23: =IF('Campus Rollup'!C16=0,"$/SF — ",TEXT('Campus Rollup'!H16/'Campus Rollup'!C16,"$#,##0")&" / SF blended") -> $1,360 / SF blended
B24: ="Note: Development Cost (All-In) of "&TEXT('Total Development Cost'!C50/1000000,"$#,##0")&"M is the full owner budget (TDC) = Total Campus Investment / construction "&TEXT('Total Development Cost'!C46/1000000,"$#,##0")&"M + owner soft costs "&TEXT('Total Development Cost'!C47/1000000,"$#,##0")&"M + financing/IDC "&TEXT('Total Development Cost'!C48/1000000,"$#,##0")&"M + owner's contingency "&TEXT('Total Development Cost'!C49/1000000,"$#,##0")&"M. See Total Development Cost tab." -> Note: Development Cost (All-In) of $1,513M is the full owner budget (TDC) = Total Campus Investment / construction $1,088M + owner soft costs $269M + financing/IDC $84M + owner's contingency $72M. See Total Development Cost tab.
B25: DESIGN SCENARIOS — CAMPUS COST BY CONFIGURATION (90 MW / 800K SF) | H25: COST EVOLUTION BY DESIGN MILESTONE
B28: Design Scenario | C28: CSA | D28: MEP | E28: Cx / GC / Soft | F28: Total | G28: $ / MW
B29: ='Scenario Comparison'!B5&" — Base" -> Current (live) — Base | C29: ='Scenario Comparison'!B15 -> 2.7573192e+08 | D29: ='Scenario Comparison'!B16 -> 6.09161e+08 | E29: ='Scenario Comparison'!B17 -> 2.0344891e+08 | F29: ='Scenario Comparison'!B13 -> 1.0883418e+09 | G29: ='Scenario Comparison'!B14 -> 12092687
B30: ='Scenario Comparison'!C5 -> Reference — Hyperscale (Hybrid) | C30: ='Scenario Comparison'!C15 -> 4.1684051e+08 | D30: ='Scenario Comparison'!C16 -> 1080845097 | E30: ='Scenario Comparison'!C17 -> 2.605499e+08 | F30: ='Scenario Comparison'!C13 -> 1.7582355e+09 | G30: ='Scenario Comparison'!C14 -> 19535950
B31: ='Scenario Comparison'!D5 -> Air-Cooled (Chilled Water) | C31: ='Scenario Comparison'!D15 -> 4.1684051e+08 | D31: ='Scenario Comparison'!D16 -> 1002231672 | E31: ='Scenario Comparison'!D17 -> 2.5768586e+08 | F31: ='Scenario Comparison'!D13 -> 1.676758e+09 | G31: ='Scenario Comparison'!D14 -> 18630645
B32: ='Scenario Comparison'!E5 -> AI / HPC — Liquid Cooled | C32: ='Scenario Comparison'!E15 -> 6.1853019e+08 | D32: ='Scenario Comparison'!E16 -> 2069717493 | E32: ='Scenario Comparison'!E17 -> 3.3103934e+08 | F32: ='Scenario Comparison'!E13 -> 3.019287e+09 | G32: ='Scenario Comparison'!E14 -> 33547634
B33: Enterprise | C33: ='Scenario Comparison'!F15 -> 4.1684051e+08 | D33: ='Scenario Comparison'!F16 -> 1180628910 | E33: ='Scenario Comparison'!F17 -> 2.5768586e+08 | F33: ='Scenario Comparison'!F13 -> 1.8551553e+09 | G33: ='Scenario Comparison'!F14 -> 20612836
B34: Colocation | C34: ='Scenario Comparison'!G15 -> 4.1684051e+08 | D34: ='Scenario Comparison'!G16 -> 952120088 | E34: ='Scenario Comparison'!G17 -> 2.5768586e+08 | F34: ='Scenario Comparison'!G13 -> 1.6266465e+09 | G34: ='Scenario Comparison'!G14 -> 18073849
B35: Edge | C35: ='Scenario Comparison'!H15 -> 2.7573192e+08 | D35: ='Scenario Comparison'!H16 -> 578065774 | E35: ='Scenario Comparison'!H17 -> 2.0465606e+08 | F35: ='Scenario Comparison'!H13 -> 1.0584538e+09 | G35: ='Scenario Comparison'!H14 -> 11760597
B36: Typical (industry median) | C36: — | D36: — | E36: — | F36: ='Benchmark Library'!L20*'Campus Rollup'!D16 -> 1026000000 | G36: ='Benchmark Library'!L20 -> 11400000
B37: All design scenarios are modeled (linked to Scenario Comparison). Enterprise & Colocation share Air-Cooled's Mid · Chilled-Water cost — they differ only in tier / redundancy / density, which don't drive cost in this estimate. Typical = industry median $/MW × 90 MW.
B38: BENCHMARK POSITIONING | H38: INVESTMENT BY DISCIPLINE
B41: CURRENT ESTIMATE — $/MW
B42: =IF(OR('Campus Rollup'!D16=0,'Campus Rollup'!H16=0),"$ —",TEXT('Campus Rollup'!H16/'Campus Rollup'!D16/1000000,"$0.00")&"M") -> $12.09M | E42: INDUSTRY MEDIAN
E43: =TEXT('Benchmark Library'!L20/1000000,"$0.0")&"M / MW" -> $11.4M / MW
B44: =IF(OR('Campus Rollup'!D16=0,'Campus Rollup'!H16=0),"Populate buildings to compare against benchmark",IF('Campus Rollup'!H16/'Campus Rollup'!D16/1000000<'Benchmark Library'!L20/1000000,"▼ "&TEXT('Benchmark Library'!L20/1000000-'Campus Rollup'!H16/'Campus Rollup'!D16/1000000,"$0.0")&"M / MW below median ("&TEXT(('Campus Rollup'!H16/'Campus Rollup'!D16-'Benchmark Library'!L20)/'Benchmark Library'!L20,"+0.0%;-0.0%")&")","▲ "&TEXT('Campus Rollup'!H16/'Campus Rollup'!D16/1000000-'Benchmark Library'!L20/1000000,"$0.0")&"M / MW above median ("&TEXT(('Campus Rollup'!H16/'Campus Rollup'!D16-'Benchmark Library'!L20)/'Benchmark Library'!L20,"+0.0%;-0.0%")&")")) -> ▲ $0.7M / MW above median (+6.1%)
B45: ="Range across "&COUNTA('Benchmark Library'!B6:B15)&" comparable Tier III projects: "&TEXT('Benchmark Library'!L19/1000000,"$0.0")&"M – "&TEXT('Benchmark Library'!L22/1000000,"$0.0")&"M / MW" -> Range across 10 comparable Tier III projects: $9.8M – $17.8M / MW
B47: LOWEST COMPARABLE | D47: MEDIAN COMPARABLE | F47: HIGHEST COMPARABLE
B48: =TEXT('Benchmark Library'!L19/1000000,"$0.0")&"M / MW" -> $9.8M / MW | D48: =TEXT('Benchmark Library'!L20/1000000,"$0.0")&"M / MW" -> $11.4M / MW | F48: =TEXT('Benchmark Library'!L22/1000000,"$0.0")&"M / MW" -> $17.8M / MW
B50: TIER 3 · DELIVERY & CONTROLS
B52: KEY HIGHLIGHTS
B55: ◆ ESTIMATE CONFIDENCE | E55: ◆ VALUE ENGINEERING | H55: ◆ TENDER READINESS
B56: ='Campus Rollup'!H3 -> Class 3 (DD) | E56: =IF('Value Engineering'!H27=0,"In progress",TEXT('Value Engineering'!H27,"$#,##0")&" identified") -> $68,805,864 identified | H56: =IF(COUNTIF('Bid Leveling'!E14:E19,">0")=0,"Ready to bid",COUNTIF('Bid Leveling'!E14:E19,">0")&" bids received") -> Ready to bid
B58: ="Accuracy band "&'Campus Rollup'!H4&". Estimate built up from CSI-level detail across all 19 divisions, anchored against benchmark library of 10 comparable Tier III projects." -> Accuracy band −20% / +30%. Estimate built up from CSI-level detail across all 19 divisions, anchored against benchmark library of 10 comparable Tier III projects. | E58: =IF('Value Engineering'!L43=0,"Active scenario: "&'Value Engineering'!L41&" — no savings adopted yet; VE log open for client review.","Active scenario: "&'Value Engineering'!L41&" — "&TEXT('Value Engineering'!L43,"$#,##0")&" adopted ("&TEXT('Value Engineering'!L46,"0.0%")&" of base) → "&TEXT('Value Engineering'!L45,"$#,##0")&"/MW.") -> Active scenario: Balanced — $35,305,864 adopted (3.2% of base) → $11,700,400/MW. | H58: =IF(COUNTIF('Bid Leveling'!E14:E19,">0")=0,"Bid packages and tender documents prepared. Subcontractor outreach underway across structural, MEP, and specialty trades.","Bid leveling complete; recommendation under client review.") -> Bid packages and tender documents prepared. Subcontractor outreach underway across structural, MEP, and specialty trades.
B60: QC CHECKS
B61: Construction Budget total = Campus Rollup total | G61: =IF(ROUND('Construction Budget'!H842,0)=ROUND('Campus Rollup'!H16,0),"✅ Tie","❌ Off by "&TEXT('Construction Budget'!H842-'Campus Rollup'!H16,"$#,##0")) -> ✅ Tie | H61: ◆ SCOPE ADDS — ALLOWANCES & ALTERNATES
B62: Client Proposal subtotal = sum of divisions | G62: =IF(ROUND('Client Proposal'!C128,0)=ROUND('Construction Budget'!H842,0),"✅ Tie","❌ Off by "&TEXT('Client Proposal'!C128-'Construction Budget'!H842,"$#,##0")) -> ✅ Tie | H62: ='Allowances & Alternates'!F46 -> 17550000
B63: CSA Summary total = Campus Rollup CSA | G63: =IF(ROUND('CSA Summary'!B21,0)=ROUND('Campus Rollup'!E16,0),"✅ Tie","❌ Off by "&TEXT('CSA Summary'!B21-'Campus Rollup'!E16,"$#,##0")) -> ✅ Tie
B64: Draw Schedule total = Construction Budget | G64: =IF(ROUND('Draw Schedule'!C32,0)=ROUND('Construction Budget'!H842,0),"✅ Tie","❌ Off by "&TEXT('Draw Schedule'!C32-'Construction Budget'!H842,"$#,##0")) -> ✅ Tie | H64: ="Allowances "&TEXT('Allowances & Alternates'!F44,"$#,##0")&" · Accepted alternates "&TEXT('Allowances & Alternates'!F45,"$#,##0") -> Allowances $17,550,000 · Accepted alternates $0
B65: TCO sensitivity center = 8-yr TCO | G65: =IF(ROUND('TCO 8-Year'!D53*1000000,-3)=ROUND('TCO 8-Year'!B39,-3),"✅ Tie","❌ Drift") -> ✅ Tie | H65: ="Flows to Client Proposal total: "&TEXT('Client Proposal'!C135,"$0.00,,,")&"B" -> Flows to Client Proposal total: $1.11B
B66: Cash Flow PV curve = Budget at Completion (BAC) | G66: ='Cash Flow & EVM'!B20 -> ✅ Tie
B67: Construction Budget ties to Unit Cost Database | G67: =IF('Construction Budget'!F850=0,"✅ Tie","❌ "&'Construction Budget'!F850&" missing") -> ✅ Tie
B68: PROJECT CONTROLS — DELIVERY METRICS
B71: ◆ SCHEDULE & COST (EVM) | E71: ◆ RISK-BASED CONTINGENCY | H71: ◆ LONG-LEAD PROCUREMENT
B72: ="SPI "&TEXT('Cash Flow & EVM'!B12,"0.00")&" · CPI "&TEXT('Cash Flow & EVM'!B13,"0.00") -> SPI — · CPI — | E72: =TEXT('Risk & Contingency'!C26,"$#,##0")&" P80" -> $120,754,987 P80 | H72: ='Procurement & Long-Lead'!B44&" pkgs overdue to order" -> 5 pkgs overdue to order
B74: ='Cash Flow & EVM'!B18&" · "&'Cash Flow & EVM'!B19&" (data date: month "&'Cash Flow & EVM'!B5&")" -> ○ Not started · ○ Not started (data date: month 0) | E74: ="P80 vs "&TEXT('Risk & Contingency'!C32,"$#,##0")&" carried at flat 10% — "&IF('Risk & Contingency'!C26<='Risk & Contingency'!C32,"within allowance.","exceeds allowance.") -> P80 vs $98,940,166 carried at flat 10% — exceeds allowance. | H74: ="$"&TEXT('Procurement & Long-Lead'!B43/1000000,"0")&"M tracked · $"&TEXT('Procurement & Long-Lead'!B46/1000000,"0.0")&"M escalation exposure if delayed." -> $1087M tracked · $30.3M escalation exposure if delayed.
B77: SCENARIO MODELING
B78: ="Active configuration drives the live estimate — set on Scenario & Presets, compared on Scenario Comparison. Current preset: "&'Scenario & Presets'!B5 -> Active configuration drives the live estimate — set on Scenario & Presets, compared on Scenario Comparison. Current preset: Hyperscale
B79: ◆ ACTIVE CONFIGURATION | E79: ◆ LIVE SCENARIO IMPACT | H79: ◆ MODELED RANGE
B80: ='Scenario & Presets'!B16 -> Liquid-Cooled (DLC) | E80: ='Scenario & Presets'!B23 -> 12092687 | H80: =TEXT(MIN('Scenario Comparison'!B14:E14)/1000000,"$0.0")&"M – "&TEXT(MAX('Scenario Comparison'!B14:E14)/1000000,"$0.0")&"M / MW" -> $12.1M – $33.5M / MW
B81: ="Pricing tier: "&'Scenario & Presets'!B15 -> Pricing tier: Low | E81: ="Estimate total: "&TEXT('Scenario & Presets'!B22,"$0.00,,,")&"B" -> Estimate total: $1.09B | H81: ="Total: "&TEXT(MIN('Scenario Comparison'!B13:E13)/1000000000,"$0.00")&"B – "&TEXT(MAX('Scenario Comparison'!B13:E13)/1000000000,"$0.00")&"B" -> Total: $1.09B – $3.02B
B82: ='Scenario & Presets'!B17&" · "&'Scenario & Presets'!B18&" · "&'Scenario & Presets'!B19 -> Tier III · N+1 · High (15–30 kW) | E82: ='Scenario & Presets'!B25 -> ● Within archetype band | H82: ="Current vs baseline: "&TEXT('Scenario Comparison'!B21,"+0.0%;-0.0%")&" ("&TEXT('Scenario Comparison'!B20,"$#,##0,,")&"M)" -> Current vs baseline: -38.1% (-$670M)
B84: TIER 4 · SCENARIO & COST BACK-UP
B86: SCENARIO COMPARISON — LIVE vs SAVED SNAPSHOTS
B87: Scenario | D87: Cooling Technology | F87: Total Estimate | H87: $ / MW | J87: Δ vs Baseline
B88: ='Scenario Comparison'!B5 -> Current (live) | D88: ='Scenario Comparison'!B7 -> Liquid-Cooled (DLC) | F88: ='Scenario Comparison'!B13 -> 1.0883418e+09 | H88: ='Scenario Comparison'!B14 -> 12092687 | J88: ='Scenario Comparison'!B21 -> -0.38100338
B89: ='Scenario Comparison'!C5 -> Reference — Hyperscale (Hybrid) | D89: ='Scenario Comparison'!C7 -> Hybrid (As-Designed) | F89: ='Scenario Comparison'!C13 -> 1.7582355e+09 | H89: ='Scenario Comparison'!C14 -> 19535950 | J89: ='Scenario Comparison'!C21 -> 0
B90: ='Scenario Comparison'!D5 -> Air-Cooled (Chilled Water) | D90: ='Scenario Comparison'!D7 -> Chilled Water (Air-Cooled) | F90: ='Scenario Comparison'!D13 -> 1.676758e+09 | H90: ='Scenario Comparison'!D14 -> 18630645 | J90: ='Scenario Comparison'!D21 -> -0.046340475
B91: ='Scenario Comparison'!E5 -> AI / HPC — Liquid Cooled | D91: ='Scenario Comparison'!E7 -> Liquid-Cooled (DLC) | F91: ='Scenario Comparison'!E13 -> 3.019287e+09 | H91: ='Scenario Comparison'!E14 -> 33547634 | J91: ='Scenario Comparison'!E21 -> 0.7172256
B92: ='Scenario Comparison'!F5 -> Enterprise | D92: ='Scenario Comparison'!F7 -> Chilled Water (Air-Cooled) | F92: ='Scenario Comparison'!F13 -> 1.8551553e+09 | H92: ='Scenario Comparison'!F14 -> 20612836 | J92: ='Scenario Comparison'!F21 -> 0.055123314
B93: ='Scenario Comparison'!G5 -> Colocation | D93: ='Scenario Comparison'!G7 -> Chilled Water (Air-Cooled) | F93: ='Scenario Comparison'!G13 -> 1.6266465e+09 | H93: ='Scenario Comparison'!G14 -> 18073849 | J93: ='Scenario Comparison'!G21 -> -0.07484154
B94: ='Scenario Comparison'!H5 -> Edge | D94: ='Scenario Comparison'!H7 -> Chilled Water (Air-Cooled) | F94: ='Scenario Comparison'!H13 -> 1.0584538e+09 | H94: ='Scenario Comparison'!H14 -> 11760597 | J94: ='Scenario Comparison'!H21 -> -0.39800229
B95: Snapshots C–E are saved on the Scenario Comparison tab; re-capture after model edits. Live row reflects the current Scenario & Presets configuration.
B97: COST ANALYSIS
B98: Cost breakdown by trade, capital by building, and unit cost vs. industry benchmark.
B178: CONSTRUCTION SCHEDULE
B179: Milestone completion dates across the build program — design through commissioning.
B213: TIER 5 · ENGINEERING, ESG & PROGRAM DELIVERY
B216: ◆ INVESTMENT COMMITTEE | E216: ◆ DELIVERABLE CAPACITY | H216: ◆ CHANGE ORDERS & CONTINGENCY
B217: ='IC Summary'!G4 -> ACCEPT | E217: =TEXT('Power & Space Capacity'!B23,"0.0")&" MW usable" -> 89.7 MW usable | H217: =TEXT('Change Order Log'!D23/1000000,"$0.0")&"M drawn" -> $19.5M drawn
B218: ="Levered IRR "&TEXT('IC Summary'!E12,"0.0%")&" · "&TEXT('IC Summary'!E14,"0.00x")&" multiple · Unlevered "&TEXT('IC Summary'!B12,"0.0%") -> Levered IRR 26.7% · 5.20x multiple · Unlevered 17.4% | E218: ="Binding: "&LOWER('Power & Space Capacity'!B24)&" · "&TEXT('Power & Space Capacity'!B54,"0.0%")&" of design" -> Binding: standby generation · 99.7% of design | H218: =TEXT('Change Order Log'!D24/1000000,"$0.0")&"M of "&TEXT('Change Order Log'!D4/1000000,"$0.0")&"M remaining ("&TEXT(1-'Change Order Log'!D25,"0%")&")" -> $79.4M of $98.9M remaining (80%)
B219: ="Stabilized value "&TEXT('IC Summary'!E19/1000000000,"$0.00")&"B · dev. profit "&TEXT('IC Summary'!E20/1000000,"$#,##0")&"M" -> Stabilized value $2.54B · dev. profit $1,024M | E219: =TEXT('Power & Space Capacity'!B55,"0.0")&" MW stranded · "&TEXT('Power & Space Capacity'!B29,"#,##0")&" SF white space" -> 10.3 MW stranded · 135,000 SF white space | H219: ='Change Order Log'!D27 -> ● Healthy — over half of contingency remains
B221: ◆ LIFECYCLE CARBON | E221: ◆ PHASED CAMPUS BUILD-OUT | H221: ◆ SCHEDULE RECOVERY
B222: =TEXT('Carbon & Sustainability'!B28/1000000,"0.00")&"M tCO₂e" -> 0.68M tCO₂e | E222: =TEXT('Phased Capital Plan'!D21/1000000000,"$0.00")&"B program" -> $1.98B program | H222: =TEXT('Schedule Acceleration'!D7,"0")&" days recovered" -> 147 days recovered
B223: =TEXT('Carbon & Sustainability'!B31,"0.00")&" tCO₂e/SF · "&TEXT('Carbon & Sustainability'!B29,"0%")&" embodied · "&'Carbon & Sustainability'!E5&" scenario" -> 0.85 tCO₂e/SF · 58% embodied · Efficient scenario | E223: =TEXT('Phased Capital Plan'!D22,"0")&" MW at build-out · "&TEXT('Phased Capital Plan'!D23/1000000,"$0.0")&"M/MW blended" -> 180 MW at build-out · $11.0M/MW blended | H223: =TEXT('Schedule Acceleration'!D10/1000000,"$0.0")&"M premium · "&TEXT('Schedule Acceleration'!D11,"$#,##0")&"/day" -> $17.8M premium · $120,748/day
B224: ="Water "&TEXT('Carbon & Sustainability'!B60,"#,##0")&" ML/yr · −"&TEXT('Carbon & Sustainability'!B48,"0%")&" achievable with levers" -> Water 126 ML/yr · −71% achievable with levers | E224: ="Phase 1 "&TEXT('Phased Capital Plan'!D24/1000000000,"$0.00")&"B (ties to estimate) · expansion "&TEXT('Phased Capital Plan'!D25/1000000,"$#,##0")&"M" -> Phase 1 $1.09B (ties to estimate) · expansion $894M | H224: ='Schedule Acceleration'!D12 -> ✓ YES — meets Q3 2028
B226: ◆ ESTIMATE vs SUBCONTRACTOR BIDS | E226: All Tier 5 figures link live to their source tabs; values refresh automatically when the model changes.
B227: ='Variance Tracker'!G28 -> Awaiting bids
B228: ="Budget "&TEXT('Variance Tracker'!C28/1000000000,"$0.00")&"B across 24 CSI divisions — sub bids plug into the tracker as received." -> Budget $1.09B across 24 CSI divisions — sub bids plug into the tracker as received.
B231: PROGRAM CONTROLS — CONTINGENCY & PHASED BUILD-OUT
B232: Contingency balance vs. monitor/critical thresholds (Change Order Log) · cumulative capex and blended $/MW across the 6-building campus (Phased Capital Plan)

Sheet Scenario & Presets
A1: SCENARIO & PRESETS — PROJECT CONFIGURATION
A2: Pick an archetype preset for guidance, then set the active configuration. Pricing Tier and Cooling Technology drive the live estimate.
A4: 1 · PROJECT ARCHETYPE PRESET
A5: Select Archetype: | B5: Hyperscale
A6: Recommended configuration
A7: Resiliency Tier: | B7: =VLOOKUP($B$5,$A$32:$H$36,2,FALSE()) -> Tier III
A8: Redundancy: | B8: =VLOOKUP($B$5,$A$32:$H$36,3,FALSE()) -> N+1
A9: Rack Density: | B9: =VLOOKUP($B$5,$A$32:$H$36,4,FALSE()) -> High (15–30 kW)
A10: Cooling Technology: | B10: =VLOOKUP($B$5,$A$32:$H$36,5,FALSE()) -> Hybrid (As-Designed)
A11: Pricing Tier: | B11: =VLOOKUP($B$5,$A$32:$H$36,6,FALSE()) -> Mid
A12: Expected $/MW band: | B12: =TEXT(VLOOKUP($B$5,$A$32:$H$36,7,FALSE()),"$0.0")&"M – "&TEXT(VLOOKUP($B$5,$A$32:$H$36,8,FALSE()),"$0.0")&"M / MW" -> $9.5M – $14.0M / MW
A14: 2 · ACTIVE CONFIGURATION (drives the live model)
A15: Pricing Tier: | B15: Low | C15: → sets every unit cost (Unit Cost Database)
A16: Cooling Technology: | B16: Liquid-Cooled (DLC) | C16: → toggles Division 23 cooling scope (air / chilled-water / liquid)
A17: Resiliency Tier: | B17: Tier III | C17: → documentation & benchmark context
A18: Redundancy: | B18: N+1 | C18: → drives MEP via redundancy factor (critical power)
A19: Rack Density: | B19: High (15–30 kW) | C19: → drives MEP via rack-density factor
A21: 3 · LIVE SCENARIO IMPACT
A22: Estimate Total: | B22: ='Campus Rollup'!H16 -> 1.0883418e+09
A23: Cost per MW: | B23: =IF('Campus Rollup'!D16=0,"—",'Campus Rollup'!H16/'Campus Rollup'!D16) -> 12092687
A24: Selected-archetype band: | B24: =B12 -> $9.5M – $14.0M / MW
A25: Position vs archetype band: | B25: =IF('Campus Rollup'!D16=0,"—",IF('Campus Rollup'!H16/'Campus Rollup'!D16<VLOOKUP($B$5,$A$32:$H$36,7,FALSE())*1000000,"▼ Below archetype band",IF('Campus Rollup'!H16/'Campus Rollup'!D16>VLOOKUP($B$5,$A$32:$H$36,8,FALSE())*1000000,"▲ Above archetype band — review scope / density","● Within archetype band"))) -> ● Within archetype band
A29: REFERENCE TABLES — used by the dropdowns above. Do not edit.
A31: Archetype | B31: Tier | C31: Redundancy | D31: Rack Density | E31: Cooling Technology | F31: Pricing | G31: $/MW Low | H31: $/MW High
A32: Hyperscale | B32: Tier III | C32: N+1 | D32: High (15–30 kW) | E32: Hybrid (As-Designed) | F32: Mid | G32: 9.5 | H32: 14
A33: Enterprise | B33: Tier III+ | C33: 2N | D33: Medium (8–15 kW) | E33: Chilled Water (Air-Cooled) | F33: Mid | G33: 11 | H33: 16
A34: Colocation | B34: Tier III | C34: N+1 | D34: Medium (8–15 kW) | E34: Chilled Water (Air-Cooled) | F34: Mid | G34: 10 | H34: 15
A35: Edge | B35: Tier II | C35: N+1 | D35: Low (≤8 kW) | E35: Chilled Water (Air-Cooled) | F35: Low | G35: 8 | H35: 13
A36: AI / HPC | B36: Tier III+ | C36: 2N | D36: Ultra (30+ kW) | E36: Liquid-Cooled (DLC) | F36: High | G36: 14 | H36: 22
A38: COOLING TECHNOLOGY FACTORS (× Division 23 scope)
A39: Technology | B39: Air-side | C39: Chilled-water | D39: Liquid
A40: Hybrid (As-Designed) | B40: 1 | C40: 1 | D40: 1
A41: Chilled Water (Air-Cooled) | B41: 1 | C41: 1 | D41: 0
A42: Liquid-Cooled (DLC) | B42: 0.4 | C42: 0.6 | D42: 1
A43: Full Immersion | B43: 0.2 | C43: 0.5 | D43: 1.1
A45: Active cooling factors → | B45: =INDEX($B$40:$B$43,MATCH($B$16,$A$40:$A$43,0)) -> 0.4 | C45: =INDEX($C$40:$C$43,MATCH($B$16,$A$40:$A$43,0)) -> 0.6 | D45: =INDEX($D$40:$D$43,MATCH($B$16,$A$40:$A$43,0)) -> 1
A47: REDUNDANCY FACTORS (× critical-power train scope)
A48: Redundancy | B48: Factor
A49: N | B49: 0.85
A50: N+1 | B50: 1
A51: 2N | B51: 1.8
A52: 2N+1 | B52: 2
A54: Active redundancy factor → | B54: =INDEX($B$49:$B$52,MATCH($B$18,$A$49:$A$52,0)) -> 1
A56: RACK DENSITY FACTORS (× rack cooling & power scope)
A57: Density | B57: Factor
A58: Low (≤8 kW) | B58: 0.9
A59: Medium (8–15 kW) | B59: 0.95
A60: High (15–30 kW) | B60: 1
A61: Ultra (30+ kW) | B61: 1.15
A63: Active density factor → | B63: =INDEX($B$58:$B$61,MATCH($B$19,$A$58:$A$61,0)) -> 1
A65: Critical-power share of MEP | B65: 0.3 | C65: share of MEP that scales with redundancy (UPS/gen/distribution)
A66: MEP redundancy multiplier | B66: =(1-$B$65)+$B$65*$B$54 -> 1 | C66: → applied to MEP
A67: Active MEP config factor (× MEP) | B67: =$B$66*$B$63 -> 1 | C67: redundancy × rack-density; N+1 & High = 1.00 (baseline)

Sheet Scenario Comparison
A1: SCENARIO COMPARISON
A2: Column B is the recommended/live case. Reference columns reflect each archetype incl. redundancy & rack-density drivers.
B4: ★ RECOMMENDED
A5: Configuration | B5: Current (live) | C5: Reference — Hyperscale (Hybrid) | D5: Air-Cooled (Chilled Water) | E5: AI / HPC — Liquid Cooled | F5: Enterprise | G5: Colocation | H5: Edge
A6: Pricing Tier | B6: ='Scenario & Presets'!B15 -> Low | C6: Mid | D6: Mid | E6: High | F6: Mid | G6: Mid | H6: Low
A7: Cooling Technology | B7: ='Scenario & Presets'!B16 -> Liquid-Cooled (DLC) | C7: Hybrid (As-Designed) | D7: Chilled Water (Air-Cooled) | E7: Liquid-Cooled (DLC) | F7: Chilled Water (Air-Cooled) | G7: Chilled Water (Air-Cooled) | H7: Chilled Water (Air-Cooled)
A8: Resiliency Tier | B8: ='Scenario & Presets'!B17 -> Tier III | C8: Tier III | D8: Tier III | E8: Tier III+ | F8: Tier III+ | G8: Tier III | H8: Tier II
A9: Redundancy | B9: ='Scenario & Presets'!B18 -> N+1 | C9: N+1 | D9: N+1 | E9: 2N | F9: 2N | G9: N+1 | H9: N+1
A10: Rack Density | B10: ='Scenario & Presets'!B19 -> High (15–30 kW) | C10: High (15–30 kW) | D10: High (15–30 kW) | E10: Ultra (30+ kW) | F10: Medium (8–15 kW) | G10: Medium (8–15 kW) | H10: Low (≤8 kW)
A12: COST OUTCOMES
A13: Total Estimate | B13: ='Campus Rollup'!H16 -> 1.0883418e+09 | C13: =C15+C16+C17 -> 1.7582355e+09 | D13: =D15+D16+D17 -> 1.676758e+09 | E13: =E15+E16+E17 -> 3.019287e+09 | F13: =F15+F16+F17 -> 1.8551553e+09 | G13: =G15+G16+G17 -> 1.6266465e+09 | H13: =H15+H16+H17 -> 1.0584538e+09
A14: Cost per MW | B14: ='Campus Rollup'!H16/'Campus Rollup'!D16 -> 12092687 | C14: =C13/'Campus Rollup'!$D$16 -> 19535950 | D14: =D13/'Campus Rollup'!$D$16 -> 18630645 | E14: =E13/'Campus Rollup'!$D$16 -> 33547634 | F14: =F13/'Campus Rollup'!$D$16 -> 20612836 | G14: =G13/'Campus Rollup'!$D$16 -> 18073849 | H14: =H13/'Campus Rollup'!$D$16 -> 11760597
A15: CSA (Shell & Structure) | B15: ='Campus Rollup'!E16 -> 2.7573192e+08 | C15: 4.1684051e+08 | D15: 4.1684051e+08 | E15: 6.1853019e+08 | F15: 4.1684051e+08 | G15: 4.1684051e+08 | H15: 2.7573192e+08
A16: MEP (Mechanical / Electrical) | B16: ='Campus Rollup'!F16 -> 6.09161e+08 | C16: 1080845097 | D16: 1002231672 | E16: 2069717493 | F16: 1180628910 | G16: 952120088 | H16: 578065774
A17: Other (Commissioning, GC, Soft) | B17: ='Campus Rollup'!G16 -> 2.0344891e+08 | C17: 2.605499e+08 | D17: 2.5768586e+08 | E17: 3.3103934e+08 | F17: 2.5768586e+08 | G17: 2.5768586e+08 | H17: 2.0465606e+08
A19: COST vs BASELINE (baseline = Reference — Hyperscale)
A20: Δ vs baseline ($) | B20: ='Campus Rollup'!H16-$C$13 -> -6.6989368e+08 | C20: =C13-$C$13 -> 0 | D20: =D13-$C$13 -> -81477469 | E20: =E13-$C$13 -> 1.2610515e+09 | F20: =F13-$C$13 -> 96919769 | G20: =G13-$C$13 -> -1.3158905e+08 | H20: =H13-$C$13 -> -6.9978175e+08
A21: Δ vs baseline (%) | B21: =('Campus Rollup'!H16-$C$13)/$C$13 -> -0.38100338 | C21: =(C13-$C$13)/$C$13 -> 0 | D21: =(D13-$C$13)/$C$13 -> -0.046340475 | E21: =(E13-$C$13)/$C$13 -> 0.7172256 | F21: =(F13-$C$13)/$C$13 -> 0.055123314 | G21: =(G13-$C$13)/$C$13 -> -0.07484154 | H21: =(H13-$C$13)/$C$13 -> -0.39800229
A22: $/MW vs median ($11.4M) | B22: ='Campus Rollup'!H16/'Campus Rollup'!D16-'Benchmark Library'!L20 -> 692686.97 | C22: =C14-'Benchmark Library'!L20 -> 8135950.1 | D22: =D14-'Benchmark Library'!L20 -> 7230644.8 | E22: =E14-'Benchmark Library'!L20 -> 22147634 | F22: =F14-'Benchmark Library'!L20 -> 9212836.4 | G22: =G14-'Benchmark Library'!L20 -> 6673849.5 | H22: =H14-'Benchmark Library'!L20 -> 360597.24
A24: VALUE-ENGINEERING OVERLAY (recommended case)
A25: Active VE Scenario | B25: ='Value Engineering'!L41 -> Balanced
A26: VE Savings (adopted) | B26: ='Value Engineering'!L43 -> 35305864
A27: VE-Adjusted Total | B27: ='Value Engineering'!L44 -> 1.053036e+09
A28: VE-Adjusted $/MW | B28: ='Value Engineering'!L45 -> 11700400
A29: Each archetype now reflects its redundancy (2N vs N+1) and rack-density premium on MEP.
A31: CARBON & SUSTAINABILITY
A32: Lifecycle Carbon (tCO₂e) | B32: ='Carbon & Sustainability'!B77 -> 683824 | C32: ='Carbon & Sustainability'!C77 -> 2552332
A33: Carbon Intensity (tCO₂e/SF) | B33: ='Carbon & Sustainability'!B78 -> 0.85478 | C33: ='Carbon & Sustainability'!C78 -> 3.190415
A34: Annual Operational (tCO₂e/yr) | B34: ='Carbon & Sustainability'!B76 -> 18921.6 | C34: ='Carbon & Sustainability'!C76 -> 143488.8
A35: Embodied Share (%) | B35: ='Carbon & Sustainability'!B79 -> 0.58494583 | C35: ='Carbon & Sustainability'!C79 -> 0.15671942
A36: Annual Water (ML/yr) | B36: ='Carbon & Sustainability'!B81 -> 126.144 | C36: ='Carbon & Sustainability'!C81 -> 1135.296
A37: WUE (L/kWh) | B37: ='Carbon & Sustainability'!B73 -> 0.2 | C37: ='Carbon & Sustainability'!C73 -> 1.8
A38: Carbon vs baseline (%) | B38: =(B32-C32)/C32 -> -0.73207874
A39: Carbon is driven by cooling strategy. Recommended Liquid-DLC design maps to the Efficient profile; Hyperscale-Hybrid baseline maps to Base. Air-cooled options (D–H) share modeled cost but differ in PUE/WUE — see the Carbon & Sustainability tab to compare Efficient / Base / Conservative scenarios in full.

Sheet Construction Budget
A1: DATA CENTER CONSTRUCTION BUDGET
A3: Project Name: | C3: Data Center Template, Northern Virginia | E3: Start Date: | F3: 46143
A4: Project Location: | C4: Loudoun County, VA | E4: Target Completion: | F4: Q1 2029
A5: Owner / Client: | C5: Confidential Hyperscaler | E5: Architect / Engineer: | F5: HKS / Page Southerland Page
A6: Total Facility Area (SF): | C6: ='Campus Rollup'!C16 -> 800000 | E6: Halls / Pods: | F6: 9 halls (3 per building × 3 bldgs)
A7: Tier Rating: | C7: Tier III | E7: Contingency %: | F7: 0.1 | G7: Escalation %: | H7: 0.035
A8: Design PUE: | C8: 1.4 | G8: Location Factor: | H8: ='Location Factors'!B6 -> 1
A9: Total IT Load (MW): | C9: ='Campus Rollup'!D16 -> 90 | G9: Estimate Date: | H9: =F3 -> 46143
A10: UPS Capacity (MW): | C10: =C9 -> 90
A11: Generator Capacity (MW): | C11: =C9*1.25 -> 112.5
A12: Cooling Capacity (tons): | C12: =C9*285 -> 25650
A13: Raised Floor Area (SF): | C13: =C6*0.55 -> 440000
A14: Redundancy: | C14: N+1
A16: # | B16: CSI Code | C16: Description | D16: Qty | E16: Unit | F16: Unit Cost ($) | G16: Contingency % | H16: Extended Cost ($) | I16: Building | J16: Scope
A18: SOFT COSTS / PRE-CONSTRUCTION | J18: Soft
A19: 1 | B19: SC 01 00 | C19: Architectural & Engineering Design Fees | D19: =$C$9 -> 90 | E19: MW | F19: 275000 | G19: =$F$7 -> 0.1 | H19: =IF(OR(D19="",F19="",D19=0,F19=0),0,D19*F19*$H$8*(1+G19)*(1+$H$7)) -> 28177875 | I19: Shared | J19: Soft
A20: 2 | B20: SC 02 00 | C20: MEP Engineering — Critical Systems Design | D20: =$C$9 -> 90 | E20: =IFERROR(VLOOKUP($B20,'Unit Cost Database'!$A:$H,3,FALSE()),"LS") -> MW | F20: =IFERROR(VLOOKUP($B20,'Unit Cost Database'!$A:$H,8,FALSE()),0) -> 225000 | G20: =$F$7 -> 0.1 | H20: =IF(OR(D20="",F20="",D20=0,F20=0),0,D20*F20*$H$8*(1+G20)*(1+$H$7)) -> 23054625 | I20: Shared | J20: Soft
A21: 3 | B21: SC 03 00 | C21: Structural Engineering | D21: =$C$9 -> 90 | E21: =IFERROR(VLOOKUP($B21,'Unit Cost Database'!$A:$H,3,FALSE()),"LS") -> MW | F21: =IFERROR(VLOOKUP($B21,'Unit Cost Database'!$A:$H,8,FALSE()),0) -> 65000 | G21: =$F$7 -> 0.1 | H21: =IF(OR(D21="",F21="",D21=0,F21=0),0,D21*F21*$H$8*(1+G21)*(1+$H$7)) -> 6660225 | I21: Shared | J21: Soft
A22: 4 | B22: SC 04 00 | C22: Civil Engineering & Survey | D22: =$C$9 -> 90 | E22: =IFERROR(VLOOKUP($B22,'Unit Cost Database'!$A:$H,3,FALSE()),"LS") -> MW | F22: =IFERROR(VLOOKUP($B22,'Unit Cost Database'!$A:$H,8,FALSE()),0) -> 35000 | G22: =$F$7 -> 0.1 | H22: =IF(OR(D22="",F22="",D22=0,F22=0),0,D22*F22*$H$8*(1+G22)*(1+$H$7)) -> 3586275 | I22: Shared | J22: Soft
A23: 5 | B23: SC 05 00 | C23: Geotechnical Investigation | D23: =3 -> 3 | E23: =IFERROR(VLOOKUP($B23,'Unit Cost Database'!$A:$H,3,FALSE()),"LS") -> EA | F23: =IFERROR(VLOOKUP($B23,'Unit Cost Database'!$A:$H,8,FALSE()),0) -> 125000 | G23: =$F$7 -> 0.1 | H23: =IF(OR(D23="",F23="",D23=0,F23=0),0,D23*F23*$H$8*(1+G23)*(1+$H$7)) -> 426937.5 | I23: Shared | J23: Soft
A24: 6 | B24: SC 06 00 | C24: Environmental Consulting / Phase I ESA | D24: =1 -> 1 | E24: =IFERROR(VLOOKUP($B24,'Unit Cost Database'!$A:$H,3,FALSE()),"LS") -> LS | F24: =IFERROR(VLOOKUP($B24,'Unit Cost Database'!$A:$H,8,FALSE()),0) -> 250000 | G24: =$F$7 -> 0.1 | H24: =IF(OR(D24="",F24="",D24=0,F24=0),0,D24*F24*$H$8*(1+G24)*(1+$H$7)) -> 284625 | I24: Shared | J24: Soft
A25: 7 | B25: SC 07 00 | C25: Permitting & Entitlement Fees | D25: =$C$9 -> 90 | E25: =IFERROR(VLOOKUP($B25,'Unit Cost Database'!$A:$H,3,FALSE()),"LS") -> MW | F25: =IFERROR(VLOOKUP($B25,'Unit Cost Database'!$A:$H,8,FALSE()),0) -> 85000 | G25: =$F$7 -> 0.1 | H25: =IF(OR(D25="",F25="",D25=0,F25=0),0,D25*F25*$H$8*(1+G25)*(1+$H$7)) -> 8709525 | I25: Shared | J25: Soft
A26: 8 | B26: SC 08 00 | C26: Utility Connection & Impact Fees | D26: =$C$9 -> 90 | E26: =IFERROR(VLOOKUP($B26,'Unit Cost Database'!$A:$H,3,FALSE()),"LS") -> MW | F26: =IFERROR(VLOOKUP($B26,'Unit Cost Database'!$A:$H,8,FALSE()),0) -> 175000 | G26: =$F$7 -> 0.1 | H26: =IF(OR(D26="",F26="",D26=0,F26=0),0,D26*F26*$H$8*(1+G26)*(1+$H$7)) -> 17931375 | I26: Shared | J26: Soft
A27: 9 | B27: SC 09 00 | C27: Third-Party Commissioning Agent (CxA) | D27: =$C$9 -> 90 | E27: =IFERROR(VLOOKUP($B27,'Unit Cost Database'!$A:$H,3,FALSE()),"LS") -> MW | F27: =IFERROR(VLOOKUP($B27,'Unit Cost Database'!$A:$H,8,FALSE()),0) -> 7500 | G27: =$F$7 -> 0.1 | H27: =IF(OR(D27="",F27="",D27=0,F27=0),0,D27*F27*$H$8*(1+G27)*(1+$H$7)) -> 768487.5 | I27: Shared | J27: Soft
A28: 10 | B28: SC 10 00 | C28: Uptime Institute Tier Certification | D28: =1 -> 1 | E28: LS | F28: 350000 | G28: =$F$7 -> 0.1 | H28: =IF(OR(D28="",F28="",D28=0,F28=0),0,D28*F28*$H$8*(1+G28)*(1+$H$7)) -> 398475 | I28: Shared | J28: Soft
A29: 11 | B29: SC 11 00 | C29: LEED / Sustainability Certification | D29: =1 -> 1 | E29: =IFERROR(VLOOKUP($B29,'Unit Cost Database'!$A:$H,3,FALSE()),"LS") -> LS | F29: =IFERROR(VLOOKUP($B29,'Unit Cost Database'!$A:$H,8,FALSE()),0) -> 250000 | G29: =$F$7 -> 0.1 | H29: =IF(OR(D29="",F29="",D29=0,F29=0),0,D29*F29*$H$8*(1+G29)*(1+$H$7)) -> 284625 | I29: Shared | J29: Soft
A30: 12 | B30: SC 12 00 | C30: Owner's Representative / PM Fees | D30: =24 -> 24 | E30: =IFERROR(VLOOKUP($B30,'Unit Cost Database'!$A:$H,3,FALSE()),"LS") -> MO | F30: =IFERROR(VLOOKUP($B30,'Unit Cost Database'!$A:$H,8,FALSE()),0) -> 95000 | G30: =$F$7 -> 0.1 | H30: =IF(OR(D30="",F30="",D30=0,F30=0),0,D30*F30*$H$8*(1+G30)*(1+$H$7)) -> 2595780 | I30: Shared | J30: Soft
A31: 13 | B31: SC 13 00 | C31: Legal & Contract Administration | D31: =24 -> 24 | E31: =IFERROR(VLOOKUP($B31,'Unit Cost Database'!$A:$H,3,FALSE()),"LS") -> MO | F31: =IFERROR(VLOOKUP($B31,'Unit Cost Database'!$A:$H,8,FALSE()),0) -> 25000 | G31: =$F$7 -> 0.1 | H31: =IF(OR(D31="",F31="",D31=0,F31=0),0,D31*F31*$H$8*(1+G31)*(1+$H$7)) -> 683100 | I31: Shared | J31: Soft
A32: 14 | B32: SC 14 00 | C32: Cost Estimating / QS Services | D32: =24 -> 24 | E32: =IFERROR(VLOOKUP($B32,'Unit Cost Database'!$A:$H,3,FALSE()),"LS") -> MO | F32: =IFERROR(VLOOKUP($B32,'Unit Cost Database'!$A:$H,8,FALSE()),0) -> 35000 | G32: =$F$7 -> 0.1 | H32: =IF(OR(D32="",F32="",D32=0,F32=0),0,D32*F32*$H$8*(1+G32)*(1+$H$7)) -> 956340 | I32: Shared | J32: Soft
A33: 15 | B33: SC 15 00 | C33: Building Information Modeling (BIM) | D33: =$C$9 -> 90 | E33: MW | F33: 85000 | G33: =$F$7 -> 0.1 | H33: =IF(OR(D33="",F33="",D33=0,F33=0),0,D33*F33*$H$8*(1+G33)*(1+$H$7)) -> 8709525 | I33: Shared | J33: Soft
A34: 16 | B34: SC 16 00 | C34: Third-Party Testing & Inspection (IOR) | D34: =24 -> 24 | E34: =IFERROR(VLOOKUP($B34,'Unit Cost Database'!$A:$H,3,FALSE()),"LS") -> MO | F34: =IFERROR(VLOOKUP($B34,'Unit Cost Database'!$A:$H,8,FALSE()),0) -> 55000 | G34: =$F$7 -> 0.1 | H34: =IF(OR(D34="",F34="",D34=0,F34=0),0,D34*F34*$H$8*(1+G34)*(1+$H$7)) -> 1502820 | I34: Shared | J34: Soft
A35: 17 | B35: SC 17 00 | C35: FF&E — NOC / SOC / Office Fit-Out | D35: =$C$6*0.05 -> 40000 | E35: =IFERROR(VLOOKUP($B35,'Unit Cost Database'!$A:$H,3,FALSE()),"LS") -> SF | F35: =IFERROR(VLOOKUP($B35,'Unit Cost Database'!$A:$H,8,FALSE()),0) -> 175 | G35: =$F$7 -> 0.1 | H35: =IF(OR(D35="",F35="",D35=0,F35=0),0,D35*F35*$H$8*(1+G35)*(1+$H$7)) -> 7969500 | I35: Shared | J35: Soft
A36: 18 | B36: SC 18 00 | C36: Move Management & Logistics | D36: =1 -> 1 | E36: =IFERROR(VLOOKUP($B36,'Unit Cost Database'!$A:$H,3,FALSE()),"LS") -> LS | F36: =IFERROR(VLOOKUP($B36,'Unit Cost Database'!$A:$H,8,FALSE()),0) -> 350000 | G36: =$F$7 -> 0.1 | H36: =IF(OR(D36="",F36="",D36=0,F36=0),0,D36*F36*$H$8*(1+G36)*(1+$H$7)) -> 398475 | I36: Shared | J36: Soft
C37: Subtotal — SOFT COSTS / PRE-CONSTRUCTION | H37: =SUM(H19:H36) -> 113098590
A39: GENERAL CONDITIONS & REQUIREMENTS | J39: GC
A40: 1 | B40: 01 10 00 | C40: Project Management & Supervision | D40: =24 -> 24 | E40: =IFERROR(VLOOKUP($B40,'Unit Cost Database'!$A:$H,3,FALSE()),"LS") -> MO | F40: =IFERROR(VLOOKUP($B40,'Unit Cost Database'!$A:$H,8,FALSE()),0) -> 80000 | G40: =$F$7 -> 0.1 | H40: =IF(OR(D40="",F40="",D40=0,F40=0),0,D40*F40*$H$8*(1+G40)*(1+$H$7)) -> 2185920 | I40: Shared | J40: GC
A41: 2 | B41: 01 20 00 | C41: Price & Payment Procedures | D41: =24 -> 24 | E41: =IFERROR(VLOOKUP($B41,'Unit Cost Database'!$A:$H,3,FALSE()),"LS") -> MO | F41: =IFERROR(VLOOKUP($B41,'Unit Cost Database'!$A:$H,8,FALSE()),0) -> 17500 | G41: =$F$7 -> 0.1 | H41: =IF(OR(D41="",F41="",D41=0,F41=0),0,D41*F41*$H$8*(1+G41)*(1+$H$7)) -> 478170 | I41: Shared | J41: GC
A42: 3 | B42: 01 30 00 | C42: Administrative Requirements | D42: =24 -> 24 | E42: =IFERROR(VLOOKUP($B42,'Unit Cost Database'!$A:$H,3,FALSE()),"LS") -> MO | F42: =IFERROR(VLOOKUP($B42,'Unit Cost Database'!$A:$H,8,FALSE()),0) -> 12600 | G42: =$F$7 -> 0.1 | H42: =IF(OR(D42="",F42="",D42=0,F42=0),0,D42*F42*$H$8*(1+G42)*(1+$H$7)) -> 344282.4 | I42: Shared | J42: GC
A43: 4 | B43: 01 31 00 | C43: Project Management Software (Procore/Primavera) | D43: =24 -> 24 | E43: =IFERROR(VLOOKUP($B43,'Unit Cost Database'!$A:$H,3,FALSE()),"LS") -> MO | F43: =IFERROR(VLOOKUP($B43,'Unit Cost Database'!$A:$H,8,FALSE()),0) -> 5950 | G43: =$F$7 -> 0.1 | H43: =IF(OR(D43="",F43="",D43=0,F43=0),0,D43*F43*$H$8*(1+G43)*(1+$H$7)) -> 162577.8 | I43: Shared | J43: GC
A44: 5 | B44: 01 40 00 | C44: Quality Requirements — QA/QC Program | D44: =24 -> 24 | E44: =IFERROR(VLOOKUP($B44,'Unit Cost Database'!$A:$H,3,FALSE()),"LS") -> MO | F44: =IFERROR(VLOOKUP($B44,'Unit Cost Database'!$A:$H,8,FALSE()),0) -> 45500 | G44: =$F$7 -> 0.1 | H44: =IF(OR(D44="",F44="",D44=0,F44=0),0,D44*F44*$H$8*(1+G44)*(1+$H$7)) -> 1243242 | I44: Shared | J44: GC
A45: 6 | B45: 01 50 00 | C45: Temporary Facilities — Site Office, Laydown | D45: =24 -> 24 | E45: =IFERROR(VLOOKUP($B45,'Unit Cost Database'!$A:$H,3,FALSE()),"LS") -> MO | F45: =IFERROR(VLOOKUP($B45,'Unit Cost Database'!$A:$H,8,FALSE()),0) -> 20000 | G45: =$F$7 -> 0.1 | H45: =IF(OR(D45="",F45="",D45=0,F45=0),0,D45*F45*$H$8*(1+G45)*(1+$H$7)) -> 546480 | I45: Shared | J45: GC
A46: 7 | B46: 01 50 10 | C46: Temporary Utilities — Power, Water, Sanitary | D46: =24 -> 24 | E46: =IFERROR(VLOOKUP($B46,'Unit Cost Database'!$A:$H,3,FALSE()),"LS") -> MO | F46: =IFERROR(VLOOKUP($B46,'Unit Cost Database'!$A:$H,8,FALSE()),0) -> 24500 | G46: =$F$7 -> 0.1 | H46: =IF(OR(D46="",F46="",D46=0,F46=0),0,D46*F46*$H$8*(1+G46)*(1+$H$7)) -> 669438 | I46: Shared | J46: GC
A47: 8 | B47: 01 51 00 | C47: Temporary Construction — Fencing, Barriers | D47: =24 -> 24 | E47: =IFERROR(VLOOKUP($B47,'Unit Cost Database'!$A:$H,3,FALSE()),"LS") -> MO | F47: =IFERROR(VLOOKUP($B47,'Unit Cost Database'!$A:$H,8,FALSE()),0) -> 17500 | G47: =$F$7 -> 0.1 | H47: =IF(OR(D47="",F47="",D47=0,F47=0),0,D47*F47*$H$8*(1+G47)*(1+$H$7)) -> 478170 | I47: Shared | J47: GC
A48: 9 | B48: 01 52 00 | C48: Construction Waste Management & Recycling | D48: =24 -> 24 | E48: =IFERROR(VLOOKUP($B48,'Unit Cost Database'!$A:$H,3,FALSE()),"LS") -> MO | F48: =IFERROR(VLOOKUP($B48,'Unit Cost Database'!$A:$H,8,FALSE()),0) -> 24500 | G48: =$F$7 -> 0.1 | H48: =IF(OR(D48="",F48="",D48=0,F48=0),0,D48*F48*$H$8*(1+G48)*(1+$H$7)) -> 669438 | I48: Shared | J48: GC
A49: 10 | B49: 01 54 00 | C49: Construction Cleaning — Progress & Final | D49: =24 -> 24 | E49: =IFERROR(VLOOKUP($B49,'Unit Cost Database'!$A:$H,3,FALSE()),"LS") -> MO | F49: =IFERROR(VLOOKUP($B49,'Unit Cost Database'!$A:$H,8,FALSE()),0) -> 45500 | G49: =$F$7 -> 0.1 | H49: =IF(OR(D49="",F49="",D49=0,F49=0),0,D49*F49*$H$8*(1+G49)*(1+$H$7)) -> 1243242 | I49: Shared | J49: GC
A50: 11 | B50: 01 55 00 | C50: Vehicular Access & Haul Roads | D50: =24 -> 24 | E50: =IFERROR(VLOOKUP($B50,'Unit Cost Database'!$A:$H,3,FALSE()),"LS") -> MO | F50: =IFERROR(VLOOKUP($B50,'Unit Cost Database'!$A:$H,8,FALSE()),0) -> 12600 | G50: =$F$7 -> 0.1 | H50: =IF(OR(D50="",F50="",D50=0,F50=0),0,D50*F50*$H$8*(1+G50)*(1+$H$7)) -> 344282.4 | I50: Shared | J50: GC
A51: 12 | B51: 01 56 00 | C51: Environmental Protection | D51: =24 -> 24 | E51: =IFERROR(VLOOKUP($B51,'Unit Cost Database'!$A:$H,3,FALSE()),"LS") -> MO | F51: =IFERROR(VLOOKUP($B51,'Unit Cost Database'!$A:$H,8,FALSE()),0) -> 17500 | G51: =$F$7 -> 0.1 | H51: =IF(OR(D51="",F51="",D51=0,F51=0),0,D51*F51*$H$8*(1+G51)*(1+$H$7)) -> 478170 | I51: Shared | J51: GC
... A53: 14 | B53: 01 70 00 | C53: Execution & Closeout Requirements | D53: =24 -> 24 | E53: =IFERROR(VLOOKUP($B53,'Unit Cost Database'!$A:$H,3,FALSE()),"LS") -> MO | F53: =IFERROR(VLOOKUP($B53,'Unit Cost Database'!$A:$H,8,FALSE()),0) -> 17500 | G53: =$F$7 -> 0.1 | H53: =IF(OR(D53="",F53="",D53=0,F53=0),0,D53*F53*$H$8*(1+G53)*(1+$H$7)) -> 478170 | I53: Shared | J53: GC
A54: 15 | B54: 01 73 00 | C54: Permits, Fees & Inspections | D54: =1 -> 1 | E54: =IFERROR(VLOOKUP($B54,'Unit Cost Database'!$A:$H,3,FALSE()),"LS") -> LS | F54: =(H$772+H$792+H$835+H$112+H$164+H$212+H$387+H$359+H$495+H$665+H$239+H$272+H$292+H$714+H$742+H$75)*0.005 -> 4525263.9 | G54: =$F$7 -> 0.1 | H54: =IF(OR(D54="",F54="",D54=0,F54=0),0,D54*F54*$H$8*(1+G54)*(1+$H$7)) -> 5152013 | I54: Shared | J54: GC
A55: 16 | B55: 01 74 00 | C55: Bonds — Performance & Payment | D55: =1 -> 1 | E55: =IFERROR(VLOOKUP($B55,'Unit Cost Database'!$A:$H,3,FALSE()),"LS") -> LS | F55: =(H$772+H$792+H$835+H$112+H$164+H$212+H$387+H$359+H$495+H$665+H$239+H$272+H$292+H$714+H$742+H$75)*0.012 -> 10860633 | G55: =$F$7 -> 0.1 | H55: =IF(OR(D55="",F55="",D55=0,F55=0),0,D55*F55*$H$8*(1+G55)*(1+$H$7)) -> 12364831 | I55: Shared | J55: GC
A56: 17 | B56: 01 76 00 | C56: Insurance — Builder's Risk, Wrap-Up | D56: =1 -> 1 | E56: =IFERROR(VLOOKUP($B56,'Unit Cost Database'!$A:$H,3,FALSE()),"LS") -> LS | F56: =(H$772+H$792+H$835+H$112+H$164+H$212+H$387+H$359+H$495+H$665+H$239+H$272+H$292+H$714+H$742+H$75)*0.015 -> 13575792 | G56: =$F$7 -> 0.1 | H56: =IF(OR(D56="",F56="",D56=0,F56=0),0,D56*F56*$H$8*(1+G56)*(1+$H$7)) -> 15456039 | I56: Shared | J56: GC
A57: 18 | B57: 01 78 00 | C57: Closeout Submittals — As-Builts, Warranties | D57: =24 -> 24 | E57: =IFERROR(VLOOKUP($B57,'Unit Cost Database'!$A:$H,3,FALSE()),"LS") -> MO | F57: =IFERROR(VLOOKUP($B57,'Unit Cost Database'!$A:$H,8,FALSE()),0) -> 12600 | G57: =$F$7 -> 0.1 | H57: =IF(OR(D57="",F57="",D57=0,F57=0),0,D57*F57*$H$8*(1+G57)*(1+$H$7)) -> 344282.4 | I57: Shared | J57: GC
C58: Subtotal — GENERAL CONDITIONS & REQUIREMENTS | H58: =SUM(H40:H57) -> 42983031
A60: COMMISSIONING & TESTING | J60: Cx
A61: 1 | B61: CX 01 00 | C61: Commissioning Management & Administration | D61: =$C$9 -> 90 | E61: =IFERROR(VLOOKUP($B61,'Unit Cost Database'!$A:$H,3,FALSE()),"LS") -> MW | F61: =IFERROR(VLOOKUP($B61,'Unit Cost Database'!$A:$H,8,FALSE()),0) -> 50000 | G61: =$F$7 -> 0.1 | H61: =IF(OR(D61="",F61="",D61=0,F61=0),0,D61*F61*$H$8*(1+G61)*(1+$H$7)) -> 5123250 | I61: All Buildings | J61: Cx
A62: 2 | B62: CX 02 00 | C62: Level 1 Cx — Factory Witness Testing | D62: =$C$9*0.3 -> 27 | E62: =IFERROR(VLOOKUP($B62,'Unit Cost Database'!$A:$H,3,FALSE()),"LS") -> MW | F62: =IFERROR(VLOOKUP($B62,'Unit Cost Database'!$A:$H,8,FALSE()),0) -> 35000 | G62: =$F$7 -> 0.1 | H62: =IF(OR(D62="",F62="",D62=0,F62=0),0,D62*F62*$H$8*(1+G62)*(1+$H$7)) -> 1075882.5 | I62: All Buildings | J62: Cx
A63: 3 | B63: CX 03 00 | C63: Level 2 Cx — Component Verification (Individual Equipment) | D63: =$C$9*0.5 -> 45 | E63: =IFERROR(VLOOKUP($B63,'Unit Cost Database'!$A:$H,3,FALSE()),"LS") -> MW | F63: =IFERROR(VLOOKUP($B63,'Unit Cost Database'!$A:$H,8,FALSE()),0) -> 45000 | G63: =$F$7 -> 0.1 | H63: =IF(OR(D63="",F63="",D63=0,F63=0),0,D63*F63*$H$8*(1+G63)*(1+$H$7)) -> 2305462.5 | I63: All Buildings | J63: Cx
A64: 4 | B64: CX 04 00 | C64: Level 3 Cx — Subsystem Verification | D64: =$C$9*0.5 -> 45 | E64: =IFERROR(VLOOKUP($B64,'Unit Cost Database'!$A:$H,3,FALSE()),"LS") -> MW | F64: =IFERROR(VLOOKUP($B64,'Unit Cost Database'!$A:$H,8,FALSE()),0) -> 55000 | G64: =$F$7 -> 0.1 | H64: =IF(OR(D64="",F64="",D64=0,F64=0),0,D64*F64*$H$8*(1+G64)*(1+$H$7)) -> 2817787.5 | I64: All Buildings | J64: Cx
A65: 5 | B65: CX 05 00 | C65: Level 4 Cx — System Verification (Integrated) | D65: =$C$9 -> 90 | E65: =IFERROR(VLOOKUP($B65,'Unit Cost Database'!$A:$H,3,FALSE()),"LS") -> MW | F65: =IFERROR(VLOOKUP($B65,'Unit Cost Database'!$A:$H,8,FALSE()),0) -> 75000 | G65: =$F$7 -> 0.1 | H65: =IF(OR(D65="",F65="",D65=0,F65=0),0,D65*F65*$H$8*(1+G65)*(1+$H$7)) -> 7684875 | I65: All Buildings | J65: Cx
A66: 6 | B66: CX 06 00 | C66: Level 5 Cx — Integrated Systems Testing (IST) | D66: =$C$9 -> 90 | E66: =IFERROR(VLOOKUP($B66,'Unit Cost Database'!$A:$H,3,FALSE()),"LS") -> MW | F66: =IFERROR(VLOOKUP($B66,'Unit Cost Database'!$A:$H,8,FALSE()),0) -> 75000 | G66: =$F$7 -> 0.1 | H66: =IF(OR(D66="",F66="",D66=0,F66=0),0,D66*F66*$H$8*(1+G66)*(1+$H$7)) -> 7684875 | I66: All Buildings | J66: Cx
A67: 7 | B67: CX 07 00 | C67: Performance Verification Testing | D67: =$C$9 -> 90 | E67: =IFERROR(VLOOKUP($B67,'Unit Cost Database'!$A:$H,3,FALSE()),"LS") -> MW | F67: =IFERROR(VLOOKUP($B67,'Unit Cost Database'!$A:$H,8,FALSE()),0) -> 65000 | G67: =$F$7 -> 0.1 | H67: =IF(OR(D67="",F67="",D67=0,F67=0),0,D67*F67*$H$8*(1+G67)*(1+$H$7)) -> 6660225 | I67: All Buildings | J67: Cx
A68: 8 | B68: CX 08 00 | C68: Seasonal Testing — Summer / Winter Peaks | D68: =$C$9*0.3 -> 27 | E68: =IFERROR(VLOOKUP($B68,'Unit Cost Database'!$A:$H,3,FALSE()),"LS") -> MW | F68: =IFERROR(VLOOKUP($B68,'Unit Cost Database'!$A:$H,8,FALSE()),0) -> 45000 | G68: =$F$7 -> 0.1 | H68: =IF(OR(D68="",F68="",D68=0,F68=0),0,D68*F68*$H$8*(1+G68)*(1+$H$7)) -> 1383277.5 | I68: All Buildings | J68: Cx
A69: 9 | B69: CX 09 00 | C69: Failure Mode & Effects Testing (FMEA) | D69: =$C$9 -> 90 | E69: =IFERROR(VLOOKUP($B69,'Unit Cost Database'!$A:$H,3,FALSE()),"LS") -> MW | F69: =IFERROR(VLOOKUP($B69,'Unit Cost Database'!$A:$H,8,FALSE()),0) -> 35000 | G69: =$F$7 -> 0.1 | H69: =IF(OR(D69="",F69="",D69=0,F69=0),0,D69*F69*$H$8*(1+G69)*(1+$H$7)) -> 3586275 | I69: All Buildings | J69: Cx
A70: 10 | B70: CX 10 00 | C70: Documentation — O&M Manuals, As-Builts | D70: =$C$9 -> 90 | E70: =IFERROR(VLOOKUP($B70,'Unit Cost Database'!$A:$H,3,FALSE()),"LS") -> MW | F70: =IFERROR(VLOOKUP($B70,'Unit Cost Database'!$A:$H,8,FALSE()),0) -> 25000 | G70: =$F$7 -> 0.1 | H70: =IF(OR(D70="",F70="",D70=0,F70=0),0,D70*F70*$H$8*(1+G70)*(1+$H$7)) -> 2561625 | I70: All Buildings | J70: Cx
A71: 11 | B71: CX 11 00 | C71: Staff Training — Critical Systems Operation | D71: =$C$9 -> 90 | E71: =IFERROR(VLOOKUP($B71,'Unit Cost Database'!$A:$H,3,FALSE()),"LS") -> MW | F71: =IFERROR(VLOOKUP($B71,'Unit Cost Database'!$A:$H,8,FALSE()),0) -> 18000 | G71: =$F$7 -> 0.1 | H71: =IF(OR(D71="",F71="",D71=0,F71=0),0,D71*F71*$H$8*(1+G71)*(1+$H$7)) -> 1844370 | I71: All Buildings | J71: Cx
A72: 12 | B72: CX 12 00 | C72: Uptime Institute Tier Certification Support | D72: =1 -> 1 | E72: =IFERROR(VLOOKUP($B72,'Unit Cost Database'!$A:$H,3,FALSE()),"LS") -> LS | F72: =IFERROR(VLOOKUP($B72,'Unit Cost Database'!$A:$H,8,FALSE()),0) -> 250000 | G72: =$F$7 -> 0.1 | H72: =IF(OR(D72="",F72="",D72=0,F72=0),0,D72*F72*$H$8*(1+G72)*(1+$H$7)) -> 284625 | I72: All Buildings | J72: Cx
A73: 13 | B73: CX 13 00 | C73: Temporary Provisions — Load Banks for IST | D73: =$C$9*0.5 -> 45 | E73: =IFERROR(VLOOKUP($B73,'Unit Cost Database'!$A:$H,3,FALSE()),"LS") -> MW | F73: =IFERROR(VLOOKUP($B73,'Unit Cost Database'!$A:$H,8,FALSE()),0) -> 35000 | G73: =$F$7 -> 0.1 | H73: =IF(OR(D73="",F73="",D73=0,F73=0),0,D73*F73*$H$8*(1+G73)*(1+$H$7)) -> 1793137.5 | I73: All Buildings | J73: Cx
A74: 14 | B74: CX 14 00 | C74: Deficiency Tracking & Remediation | D74: =$C$9 -> 90 | E74: =IFERROR(VLOOKUP($B74,'Unit Cost Database'!$A:$H,3,FALSE()),"LS") -> MW | F74: =IFERROR(VLOOKUP($B74,'Unit Cost Database'!$A:$H,8,FALSE()),0) -> 25000 | G74: =$F$7 -> 0.1 | H74: =IF(OR(D74="",F74="",D74=0,F74=0),0,D74*F74*$H$8*(1+G74)*(1+$H$7)) -> 2561625 | I74: All Buildings | J74: Cx
C75: Subtotal — COMMISSIONING & TESTING | H75: =SUM(H61:H74) -> 47367292
A77: DIVISION 03 — CONCRETE | J77: CSA
A78: 1 | B78: 03 10 00 | C78: Concrete Formwork — Foundations | D78: =$C$6*0.04/27 -> 1185.1852 | E78: =IFERROR(VLOOKUP($B78,'Unit Cost Database'!$A:$H,3,FALSE()),"LS") -> CY | F78: =IFERROR(VLOOKUP($B78,'Unit Cost Database'!$A:$H,8,FALSE()),0) -> 220 | G78: =$F$7 -> 0.1 | H78: =IF(OR(D78="",F78="",D78=0,F78=0),0,D78*F78*$H$8*(1+G78)*(1+$H$7)) -> 296853.33 | I78: All Buildings | J78: CSA
A79: 2 | B79: 03 20 00 | C79: Concrete Reinforcement — Rebar | D79: =$C$6*0.04/27 -> 1185.1852 | E79: =IFERROR(VLOOKUP($B79,'Unit Cost Database'!$A:$H,3,FALSE()),"LS") -> CY | F79: =IFERROR(VLOOKUP($B79,'Unit Cost Database'!$A:$H,8,FALSE()),0) -> 240 | G79: =$F$7 -> 0.1 | H79: =IF(OR(D79="",F79="",D79=0,F79=0),0,D79*F79*$H$8*(1+G79)*(1+$H$7)) -> 323840 | I79: All Buildings | J79: CSA
A80: 3 | B80: 03 30 00 | C80: Cast-in-Place — Foundation Walls | D80: =$C$6*0.03/27 -> 888.88889 | E80: =IFERROR(VLOOKUP($B80,'Unit Cost Database'!$A:$H,3,FALSE()),"LS") -> CY | F80: =IFERROR(VLOOKUP($B80,'Unit Cost Database'!$A:$H,8,FALSE()),0) -> 450 | G80: =$F$7 -> 0.1 | H80: =IF(OR(D80="",F80="",D80=0,F80=0),0,D80*F80*$H$8*(1+G80)*(1+$H$7)) -> 455400 | I80: All Buildings | J80: CSA
A81: 4 | B81: 03 30 10 | C81: Cast-in-Place — Equipment Pads (Generator, Chiller, Transformer) | D81: =$C$6*0.02/27 -> 592.59259 | E81: =IFERROR(VLOOKUP($B81,'Unit Cost Database'!$A:$H,3,FALSE()),"LS") -> CY | F81: =IFERROR(VLOOKUP($B81,'Unit Cost Database'!$A:$H,8,FALSE()),0) -> 650 | G81: =$F$7 -> 0.1 | H81: =IF(OR(D81="",F81="",D81=0,F81=0),0,D81*F81*$H$8*(1+G81)*(1+$H$7)) -> 438533.33 | I81: All Buildings | J81: CSA
A82: 5 | B82: 03 30 20 | C82: Cast-in-Place — Elevated Slabs — breakdown ↓ | D82: 240000 | E82: =IFERROR(VLOOKUP($B82,'Unit Cost Database'!$A:$H,3,FALSE()),"LS") -> SF | F82: =IFERROR(VLOOKUP($B82,'Unit Cost Database'!$A:$H,8,FALSE()),0) -> 14 | G82: =$F$7 -> 0.1 | H82: =IF(OR(D82="",F82="",D82=0,F82=0),0,D82*F82*$H$8*(1+G82)*(1+$H$7)) -> 3825360 | I82: All Buildings | J82: CSA
B83: 3 30 21 | C83: • Elevated Slabs — Concrete | D83: 0 | E83: =IFERROR(VLOOKUP($B83,'Unit Cost Database'!$A:$H,3,FALSE()),"LS") -> LS | F83: =IFERROR(VLOOKUP($B83,'Unit Cost Database'!$A:$H,8,FALSE()),0) -> 1848000 | G83: =$F$7 -> 0.1 | H83: =IF(OR(D83="",F83="",D83=0,F83=0),0,D83*F83*$H$8*(1+G83)*(1+$H$7)) -> 0 | I83: All Buildings | J83: CSA
B84: 3 30 22 | C84: • Elevated Slabs — Rebar | D84: 0 | E84: =IFERROR(VLOOKUP($B84,'Unit Cost Database'!$A:$H,3,FALSE()),"LS") -> LS | F84: =IFERROR(VLOOKUP($B84,'Unit Cost Database'!$A:$H,8,FALSE()),0) -> 672000 | G84: =$F$7 -> 0.1 | H84: =IF(OR(D84="",F84="",D84=0,F84=0),0,D84*F84*$H$8*(1+G84)*(1+$H$7)) -> 0 | I84: All Buildings | J84: CSA
B85: 3 30 23 | C85: • Elevated Slabs — Forming | D85: 0 | E85: =IFERROR(VLOOKUP($B85,'Unit Cost Database'!$A:$H,3,FALSE()),"LS") -> LS | F85: =IFERROR(VLOOKUP($B85,'Unit Cost Database'!$A:$H,8,FALSE()),0) -> 504000 | G85: =$F$7 -> 0.1 | H85: =IF(OR(D85="",F85="",D85=0,F85=0),0,D85*F85*$H$8*(1+G85)*(1+$H$7)) -> 0 | I85: All Buildings | J85: CSA
B86: 3 30 24 | C86: • Elevated Slabs — Finishing | D86: 0 | E86: =IFERROR(VLOOKUP($B86,'Unit Cost Database'!$A:$H,3,FALSE()),"LS") -> LS | F86: =IFERROR(VLOOKUP($B86,'Unit Cost Database'!$A:$H,8,FALSE()),0) -> 336000 | G86: =$F$7 -> 0.1 | H86: =IF(OR(D86="",F86="",D86=0,F86=0),0,D86*F86*$H$8*(1+G86)*(1+$H$7)) -> 0 | I86: All Buildings | J86: CSA
A87: 6 | B87: 03 30 30 | C87: Cast-in-Place — Slab on Grade (Data Halls) — breakdown ↓ | D87: 605548.28 | E87: =IFERROR(VLOOKUP($B87,'Unit Cost Database'!$A:$H,3,FALSE()),"LS") -> SF | F87: =IFERROR(VLOOKUP($B87,'Unit Cost Database'!$A:$H,8,FALSE()),0) -> 10 | G87: =$F$7 -> 0.1 | H87: =IF(OR(D87="",F87="",D87=0,F87=0),0,D87*F87*$H$8*(1+G87)*(1+$H$7)) -> 6894167.2 | I87: All Buildings | J87: CSA
B88: 3 30 31 | C88: • Slab on Grade — Concrete | D88: 0 | E88: =IFERROR(VLOOKUP($B88,'Unit Cost Database'!$A:$H,3,FALSE()),"LS") -> LS | F88: =IFERROR(VLOOKUP($B88,'Unit Cost Database'!$A:$H,8,FALSE()),0) -> 3330515.6 | G88: =$F$7 -> 0.1 | H88: =IF(OR(D88="",F88="",D88=0,F88=0),0,D88*F88*$H$8*(1+G88)*(1+$H$7)) -> 0 | I88: All Buildings | J88: CSA
B89: 3 30 32 | C89: • Slab on Grade — Reinforcement | D89: 0 | E89: =IFERROR(VLOOKUP($B89,'Unit Cost Database'!$A:$H,3,FALSE()),"LS") -> LS | F89: =IFERROR(VLOOKUP($B89,'Unit Cost Database'!$A:$H,8,FALSE()),0) -> 1211096.6 | G89: =$F$7 -> 0.1 | H89: =IF(OR(D89="",F89="",D89=0,F89=0),0,D89*F89*$H$8*(1+G89)*(1+$H$7)) -> 0 | I89: All Buildings | J89: CSA
B90: 3 30 33 | C90: • Slab on Grade — Finishing & Curing | D90: 0 | E90: =IFERROR(VLOOKUP($B90,'Unit Cost Database'!$A:$H,3,FALSE()),"LS") -> LS | F90: =IFERROR(VLOOKUP($B90,'Unit Cost Database'!$A:$H,8,FALSE()),0) -> 908322.43 | G90: =$F$7 -> 0.1 | H90: =IF(OR(D90="",F90="",D90=0,F90=0),0,D90*F90*$H$8*(1+G90)*(1+$H$7)) -> 0 | I90: All Buildings | J90: CSA
B91: 3 30 34 | C91: • Slab on Grade — Vapor Barrier Prep | D91: 0 | E91: =IFERROR(VLOOKUP($B91,'Unit Cost Database'!$A:$H,3,FALSE()),"LS") -> LS | F91: =IFERROR(VLOOKUP($B91,'Unit Cost Database'!$A:$H,8,FALSE()),0) -> 605548.28 | G91: =$F$7 -> 0.1 | H91: =IF(OR(D91="",F91="",D91=0,F91=0),0,D91*F91*$H$8*(1+G91)*(1+$H$7)) -> 0 | I91: All Buildings | J91: CSA
A92: 7 | B92: 03 30 40 | C92: Cast-in-Place — Loading Dock / Ramps | D92: =$C$6*0.02 -> 16000 | E92: =IFERROR(VLOOKUP($B92,'Unit Cost Database'!$A:$H,3,FALSE()),"LS") -> SF | F92: =IFERROR(VLOOKUP($B92,'Unit Cost Database'!$A:$H,8,FALSE()),0) -> 18 | G92: =$F$7 -> 0.1 | H92: =IF(OR(D92="",F92="",D92=0,F92=0),0,D92*F92*$H$8*(1+G92)*(1+$H$7)) -> 327888 | I92: All Buildings | J92: CSA
A93: 8 | B93: 03 35 00 | C93: Concrete Finishing — Data Hall Floor Flatness (FF/FL) | D93: =$C$13 -> 440000 | E93: =IFERROR(VLOOKUP($B93,'Unit Cost Database'!$A:$H,3,FALSE()),"LS") -> SF | F93: =IFERROR(VLOOKUP($B93,'Unit Cost Database'!$A:$H,8,FALSE()),0) -> 2.8 | G93: =$F$7 -> 0.1 | H93: =IF(OR(D93="",F93="",D93=0,F93=0),0,D93*F93*$H$8*(1+G93)*(1+$H$7)) -> 1402632 | I93: All Buildings | J93: CSA
A94: 9 | B94: 03 40 00 | C94: Precast Concrete — Tilt-Up Panels — breakdown ↓ | D94: 480000 | E94: =IFERROR(VLOOKUP($B94,'Unit Cost Database'!$A:$H,3,FALSE()),"LS") -> SF | F94: =IFERROR(VLOOKUP($B94,'Unit Cost Database'!$A:$H,8,FALSE()),0) -> 18 | G94: =$F$7 -> 0.1 | H94: =IF(OR(D94="",F94="",D94=0,F94=0),0,D94*F94*$H$8*(1+G94)*(1+$H$7)) -> 9836640 | I94: All Buildings | J94: CSA
B95: 3 40 01 | C95: • Tilt-Up — Panel Fabrication | D95: 0 | E95: =IFERROR(VLOOKUP($B95,'Unit Cost Database'!$A:$H,3,FALSE()),"LS") -> LS | F95: =IFERROR(VLOOKUP($B95,'Unit Cost Database'!$A:$H,8,FALSE()),0) -> 5184000 | G95: =$F$7 -> 0.1 | H95: =IF(OR(D95="",F95="",D95=0,F95=0),0,D95*F95*$H$8*(1+G95)*(1+$H$7)) -> 0 | I95: All Buildings | J95: CSA
B96: 3 40 02 | C96: • Tilt-Up — Erection & Bracing | D96: 0 | E96: =IFERROR(VLOOKUP($B96,'Unit Cost Database'!$A:$H,3,FALSE()),"LS") -> LS | F96: =IFERROR(VLOOKUP($B96,'Unit Cost Database'!$A:$H,8,FALSE()),0) -> 2160000 | G96: =$F$7 -> 0.1 | H96: =IF(OR(D96="",F96="",D96=0,F96=0),0,D96*F96*$H$8*(1+G96)*(1+$H$7)) -> 0 | I96: All Buildings | J96: CSA
B97: 3 40 03 | C97: • Tilt-Up — Connections & Joints | D97: 0 | E97: =IFERROR(VLOOKUP($B97,'Unit Cost Database'!$A:$H,3,FALSE()),"LS") -> LS | F97: =IFERROR(VLOOKUP($B97,'Unit Cost Database'!$A:$H,8,FALSE()),0) -> 864000 | G97: =$F$7 -> 0.1 | H97: =IF(OR(D97="",F97="",D97=0,F97=0),0,D97*F97*$H$8*(1+G97)*(1+$H$7)) -> 0 | I97: All Buildings | J97: CSA
B98: 3 40 04 | C98: • Tilt-Up — Finishing | D98: 0 | E98: =IFERROR(VLOOKUP($B98,'Unit Cost Database'!$A:$H,3,FALSE()),"LS") -> LS | F98: =IFERROR(VLOOKUP($B98,'Unit Cost Database'!$A:$H,8,FALSE()),0) -> 432000 | G98: =$F$7 -> 0.1 | H98: =IF(OR(D98="",F98="",D98=0,F98=0),0,D98*F98*$H$8*(1+G98)*(1+$H$7)) -> 0 | I98: All Buildings | J98: CSA
A99: 10 | B99: 03 41 00 | C99: Precast Structural Members | D99: =$C$6*0.05 -> 40000 | E99: =IFERROR(VLOOKUP($B99,'Unit Cost Database'!$A:$H,3,FALSE()),"LS") -> SF | F99: =IFERROR(VLOOKUP($B99,'Unit Cost Database'!$A:$H,8,FALSE()),0) -> 21 | G99: =$F$7 -> 0.1 | H99: =IF(OR(D99="",F99="",D99=0,F99=0),0,D99*F99*$H$8*(1+G99)*(1+$H$7)) -> 956340 | I99: All Buildings | J99: CSA
A100: 11 | B100: 03 05 00 | C100: Concrete Accessories — Embeds, Anchors | D100: =$C$6 -> 800000 | E100: =IFERROR(VLOOKUP($B100,'Unit Cost Database'!$A:$H,3,FALSE()),"LS") -> SF | F100: =IFERROR(VLOOKUP($B100,'Unit Cost Database'!$A:$H,8,FALSE()),0) -> 0.35 | G100: =$F$7 -> 0.1 | H100: =IF(OR(D100="",F100="",D100=0,F100=0),0,D100*F100*$H$8*(1+G100)*(1+$H$7)) -> 318780 | I100: All Buildings | J100: CSA
A101: 12 | B101: 03 15 00 | C101: Under-Slab Vapor Barrier & Joints | D101: 600000 | E101: =IFERROR(VLOOKUP($B101,'Unit Cost Database'!$A:$H,3,FALSE()),"LS") -> SF | F101: =IFERROR(VLOOKUP($B101,'Unit Cost Database'!$A:$H,8,FALSE()),0) -> 1.1 | G101: =$F$7 -> 0.1 | H101: =IF(OR(D101="",F101="",D101=0,F101=0),0,D101*F101*$H$8*(1+G101)*(1+$H$7)) -> 751410 | I101: All Buildings | J101: CSA
A102: 13 | B102: 03 30 70 | C102: Concrete Testing & Inspection | D102: 1 | E102: =IFERROR(VLOOKUP($B102,'Unit Cost Database'!$A:$H,3,FALSE()),"LS") -> LS | F102: =IFERROR(VLOOKUP($B102,'Unit Cost Database'!$A:$H,8,FALSE()),0) -> 180000 | G102: =$F$7 -> 0.1 | H102: =IF(OR(D102="",F102="",D102=0,F102=0),0,D102*F102*$H$8*(1+G102)*(1+$H$7)) -> 204930 | I102: All Buildings | J102: CSA
A103: 14 | B103: 03 30 80 | C103: Cast-in-Place — Mat Foundation / Raft — breakdown ↓ | D103: 9500 | E103: =IFERROR(VLOOKUP($B103,'Unit Cost Database'!$A:$H,3,FALSE()),"LS") -> CY | F103: =IFERROR(VLOOKUP($B103,'Unit Cost Database'!$A:$H,8,FALSE()),0) -> 320 | G103: =$F$7 -> 0.1 | H103: =IF(OR(D103="",F103="",D103=0,F103=0),0,D103*F103*$H$8*(1+G103)*(1+$H$7)) -> 3461040 | I103: All Buildings | J103: CSA
B104: 3 30 81 | C104: • Mat Foundation — Concrete | D104: 0 | E104: =IFERROR(VLOOKUP($B104,'Unit Cost Database'!$A:$H,3,FALSE()),"LS") -> LS | F104: =IFERROR(VLOOKUP($B104,'Unit Cost Database'!$A:$H,8,FALSE()),0) -> 1824000 | G104: =$F$7 -> 0.1 | H104: =IF(OR(D104="",F104="",D104=0,F104=0),0,D104*F104*$H$8*(1+G104)*(1+$H$7)) -> 0 | I104: All Buildings | J104: CSA
B105: 3 30 82 | C105: • Mat Foundation — Rebar | D105: 0 | E105: =IFERROR(VLOOKUP($B105,'Unit Cost Database'!$A:$H,3,FALSE()),"LS") -> LS | F105: =IFERROR(VLOOKUP($B105,'Unit Cost Database'!$A:$H,8,FALSE()),0) -> 760000 | G105: =$F$7 -> 0.1 | H105: =IF(OR(D105="",F105="",D105=0,F105=0),0,D105*F105*$H$8*(1+G105)*(1+$H$7)) -> 0 | I105: All Buildings | J105: CSA
B106: 3 30 83 | C106: • Mat Foundation — Forming & Finishing | D106: 0 | E106: =IFERROR(VLOOKUP($B106,'Unit Cost Database'!$A:$H,3,FALSE()),"LS") -> LS | F106: =IFERROR(VLOOKUP($B106,'Unit Cost Database'!$A:$H,8,FALSE()),0) -> 456000 | G106: =$F$7 -> 0.1 | H106: =IF(OR(D106="",F106="",D106=0,F106=0),0,D106*F106*$H$8*(1+G106)*(1+$H$7)) -> 0 | I106: All Buildings | J106: CSA
A107: 15 | B107: 03 30 95 | C107: Cast-in-Place — Pile Caps & Grade Beams | D107: 4200 | E107: =IFERROR(VLOOKUP($B107,'Unit Cost Database'!$A:$H,3,FALSE()),"LS") -> CY | F107: =IFERROR(VLOOKUP($B107,'Unit Cost Database'!$A:$H,8,FALSE()),0) -> 380 | G107: =$F$7 -> 0.1 | H107: =IF(OR(D107="",F107="",D107=0,F107=0),0,D107*F107*$H$8*(1+G107)*(1+$H$7)) -> 1817046 | I107: All Buildings | J107: CSA
...

Sheet Campus Rollup
A1: DATA CENTER CAMPUS — PROGRAM-LEVEL ROLLUP
A3: Program Name: | B3: Data Center Template, Northern Virginia | D3: Client: | E3: Confidential Hyperscaler | G3: Estimate Class: | H3: Class 3 (DD)
A4: Location: | B4: Loudoun County, VA | D4: Estimate Date: | E4: ='Construction Budget'!F3 -> 46143 | G4: Accuracy Range: | H4: =IFERROR(CHOOSE(MATCH(H3,{"Class 5 (Concept)","Class 4 (SD)","Class 3 (DD)","Class 2 (CD)","Class 1 (GMP/Tender)"},0),"−50% / +100%","−30% / +50%","−20% / +30%","−10% / +20%","−5% / +10%"),"") -> −20% / +30%
A6: BUILDING-BY-BUILDING SUMMARY
A7: # | B7: Building | C7: GBA (SF) | D7: IT Load (MW) | E7: CSA Cost | F7: MEP Cost | G7: Other (Cx/GC/Soft) | H7: Total | I7: $/SF | J7: $/MW
A8: 1 | B8: Building 1 (B1) | C8: 250000 | D8: 30 | E8: =SUMIFS('Construction Budget'!H:H,'Construction Budget'!I:I,"All Buildings",'Construction Budget'!J:J,"CSA")/3 -> 59235638 | F8: =SUMIFS('Construction Budget'!H:H,'Construction Budget'!I:I,"All Buildings",'Construction Budget'!J:J,"MEP")/3*'Scenario & Presets'!$B$67 -> 2.0305367e+08 | G8: =(SUMIFS('Construction Budget'!H:H,'Construction Budget'!I:I,"All Buildings",'Construction Budget'!J:J,"Cx")+SUMIFS('Construction Budget'!H:H,'Construction Budget'!I:I,"All Buildings",'Construction Budget'!J:J,"GC")+SUMIFS('Construction Budget'!H:H,'Construction Budget'!I:I,"All Buildings",'Construction Budget'!J:J,"Soft"))/3 -> 15789098 | H8: =E8+F8+G8 -> 2.780784e+08 | I8: =IF(C8=0,"—",H8/C8) -> 1112.3136 | J8: =IF(D8=0,"—",H8/D8) -> 9269280.1
A9: 2 | B9: Building 2 (B2) | C9: 250000 | D9: 30 | E9: =SUMIFS('Construction Budget'!H:H,'Construction Budget'!I:I,"All Buildings",'Construction Budget'!J:J,"CSA")/3 -> 59235638 | F9: =SUMIFS('Construction Budget'!H:H,'Construction Budget'!I:I,"All Buildings",'Construction Budget'!J:J,"MEP")/3*'Scenario & Presets'!$B$67 -> 2.0305367e+08 | G9: =(SUMIFS('Construction Budget'!H:H,'Construction Budget'!I:I,"All Buildings",'Construction Budget'!J:J,"Cx")+SUMIFS('Construction Budget'!H:H,'Construction Budget'!I:I,"All Buildings",'Construction Budget'!J:J,"GC")+SUMIFS('Construction Budget'!H:H,'Construction Budget'!I:I,"All Buildings",'Construction Budget'!J:J,"Soft"))/3 -> 15789098 | H9: =E9+F9+G9 -> 2.780784e+08 | I9: =IF(C9=0,"—",H9/C9) -> 1112.3136 | J9: =IF(D9=0,"—",H9/D9) -> 9269280.1
A10: 3 | B10: Building 3 (B3) | C10: 250000 | D10: 30 | E10: =SUMIFS('Construction Budget'!H:H,'Construction Budget'!I:I,"All Buildings",'Construction Budget'!J:J,"CSA")/3 -> 59235638 | F10: =SUMIFS('Construction Budget'!H:H,'Construction Budget'!I:I,"All Buildings",'Construction Budget'!J:J,"MEP")/3*'Scenario & Presets'!$B$67 -> 2.0305367e+08 | G10: =(SUMIFS('Construction Budget'!H:H,'Construction Budget'!I:I,"All Buildings",'Construction Budget'!J:J,"Cx")+SUMIFS('Construction Budget'!H:H,'Construction Budget'!I:I,"All Buildings",'Construction Budget'!J:J,"GC")+SUMIFS('Construction Budget'!H:H,'Construction Budget'!I:I,"All Buildings",'Construction Budget'!J:J,"Soft"))/3 -> 15789098 | H10: =E10+F10+G10 -> 2.780784e+08 | I10: =IF(C10=0,"—",H10/C10) -> 1112.3136 | J10: =IF(D10=0,"—",H10/D10) -> 9269280.1
A11: 4 | B11: Building 4 (B4) | C11: 0 | D11: 0 | E11: 0 | F11: 0 | G11: 0 | H11: =E11+F11+G11 -> 0 | I11: =IF(C11=0,"—",H11/C11) -> — | J11: =IF(D11=0,"—",H11/D11) -> —
A12: 5 | B12: Building 5 (B5) | C12: 0 | D12: 0 | E12: 0 | F12: 0 | G12: 0 | H12: =E12+F12+G12 -> 0 | I12: =IF(C12=0,"—",H12/C12) -> — | J12: =IF(D12=0,"—",H12/D12) -> —
A13: 6 | B13: Building 6 (B6) | C13: 0 | D13: 0 | E13: 0 | F13: 0 | G13: 0 | H13: =E13+F13+G13 -> 0 | I13: =IF(C13=0,"—",H13/C13) -> — | J13: =IF(D13=0,"—",H13/D13) -> —
A14: S | B14: Shared Infrastructure | C14: 50000 | D14: 0 | E14: =SUMIFS('Construction Budget'!H:H,'Construction Budget'!I:I,"Shared",'Construction Budget'!J:J,"CSA") -> 98025002 | F14: =SUMIFS('Construction Budget'!H:H,'Construction Budget'!I:I,"Shared",'Construction Budget'!J:J,"MEP")*'Scenario & Presets'!$B$67 -> 0 | G14: =SUMIFS('Construction Budget'!H:H,'Construction Budget'!I:I,"Shared",'Construction Budget'!J:J,"Cx")+SUMIFS('Construction Budget'!H:H,'Construction Budget'!I:I,"Shared",'Construction Budget'!J:J,"GC")+SUMIFS('Construction Budget'!H:H,'Construction Budget'!I:I,"Shared",'Construction Budget'!J:J,"Soft") -> 1.5608162e+08 | H14: =E14+F14+G14 -> 2.5410662e+08 | I14: — | J14: —
B16: CAMPUS TOTAL | C16: =SUM(C8:C14) -> 800000 | D16: =SUM(D8:D14) -> 90 | E16: =SUM(E8:E14) -> 2.7573192e+08 | F16: =SUM(F8:F14) -> 6.09161e+08 | G16: =SUM(G8:G14) -> 2.0344891e+08 | H16: =SUM(H8:H14) -> 1.0883418e+09 | I16: =IF(C16=0,"—",H16/C16) -> 1360.4273 | J16: =IF(D16=0,"—",H16/D16) -> 12092687
A18: PROGRAM-LEVEL METRICS
A20: CSA Share of Total: | B20: =IF(H16=0,0,E16/H16) -> 0.25335047 | D20: MEP Share of Total: | E20: =IF(H16=0,0,F16/H16) -> 0.55971477 | G20: Other Share: | H20: =IF(H16=0,0,G16/H16) -> 0.18693476
A21: Campus $/SF (excl. Shared): | B21: =IF(SUM(C8:C13)=0,"—",SUM(H8:H13)/SUM(C8:C13)) -> 1112.3136 | D21: Campus $/MW (incl. Shared): | E21: =IF(D16=0,"—",H16/D16) -> 12092687 | G21: Cost per Watt: | H21: =IF(D16=0,"—",H16/(D16*1000000)) -> 12.092687
A23: PROGRAM ECONOMICS — ALL-IN (bridge to TDC)
A24: Hard construction (this tab): | B24: =H16 -> 1.0883418e+09 | D24: All-in development cost: | E24: ='Total Development Cost'!C35 -> 1.5128738e+09 | G24: Hard cost % of all-in: | H24: =H16/'Total Development Cost'!C35 -> 0.71938706
A25: Construction $/MW: | B25: =H16/D16 -> 12092687 | D25: All-in $/MW: | E25: ='Total Development Cost'!C35/D16 -> 16809709 | G25: Capex uplift $/MW: | H25: =('Total Development Cost'!C35-H16)/D16 -> 4717021.7
A26: Construction $/SF (incl. shared): | B26: =H16/C16 -> 1360.4273 | D26: All-in $/SF: | E26: ='Total Development Cost'!C35/C16 -> 1891.0922 | G26: All-in cost per Watt: | H26: ='Total Development Cost'!C35/(D16*1000000) -> 16.809709
A27: Senior loan (60% LTC): | B27: ='Capital Stack & Returns'!B25 -> 9.0772427e+08 | D27: Sponsor equity: | E27: ='Capital Stack & Returns'!B27 -> 6.0514951e+08 | G27: Loan-to-cost: | H27: ='Capital Stack & Returns'!B29 -> 0.6
A29: NOTES
A30: • Tag each Construction Budget line in column I (Building) to one of B1–B6 or "Shared" so it rolls up here.
A31: • Column J (Scope) auto-classifies CSA / MEP / Cx / GC / Soft based on division. Override per line if needed.
A32: • Shared Infrastructure = site-wide utilities, security perimeter, central plant, common roads — not allocated to a specific building.
A33: • Campus $/SF excludes Shared Infra (which has no allocable SF). Campus $/MW includes Shared (allocated against total IT load).
A36: — chart source data —
A37: CSA (core & shell) | B37: =E16 -> 2.7573192e+08
A38: MEP (power & cooling) | B38: =F16 -> 6.09161e+08
A39: Other (Cx / GC / soft) | B39: =G16 -> 2.0344891e+08

Sheet CSA Summary
A1: CIVIL / STRUCTURAL / ARCHITECTURAL (CSA) ESTIMATE SUMMARY
A3: Scope: | B3: Civil + Structural + Architectural (excludes MEP, Cx, GC, Soft Costs)
A5: CSA DIVISION | B5: Base (current) | C5: Hyperscale (Hybrid) | D5: Air-Cooled | E5: AI / HPC (Liquid)
A6: Earthwork (Div 31) | B6: =SUMIFS('Construction Budget'!$H$744:$H$771,'Construction Budget'!$I$744:$I$771,"All Buildings")+SUMIFS('Construction Budget'!$H$744:$H$771,'Construction Budget'!$I$744:$I$771,"Shared") -> 25614732 | C6: =$B6*('Scenario Comparison'!C$15/'Scenario Comparison'!$B$15) -> 38723330 | D6: =$B6*('Scenario Comparison'!D$15/'Scenario Comparison'!$B$15) -> 38723330 | E6: =$B6*('Scenario Comparison'!E$15/'Scenario Comparison'!$B$15) -> 57459743
A7: Exterior Improvements (Div 32) | B7: =SUMIFS('Construction Budget'!$H$775:$H$791,'Construction Budget'!$I$775:$I$791,"All Buildings")+SUMIFS('Construction Budget'!$H$775:$H$791,'Construction Budget'!$I$775:$I$791,"Shared") -> 9371809.5 | C7: =$B7*('Scenario Comparison'!C$15/'Scenario Comparison'!$B$15) -> 14167928 | D7: =$B7*('Scenario Comparison'!D$15/'Scenario Comparison'!$B$15) -> 14167928 | E7: =$B7*('Scenario Comparison'!E$15/'Scenario Comparison'!$B$15) -> 21023127
A8: Utilities (Div 33) | B8: =SUMIFS('Construction Budget'!$H$795:$H$834,'Construction Budget'!$I$795:$I$834,"All Buildings")+SUMIFS('Construction Budget'!$H$795:$H$834,'Construction Budget'!$I$795:$I$834,"Shared") -> 63598602 | C8: =$B8*('Scenario Comparison'!C$15/'Scenario Comparison'!$B$15) -> 96145829 | D8: =$B8*('Scenario Comparison'!D$15/'Scenario Comparison'!$B$15) -> 96145829 | E8: =$B8*('Scenario Comparison'!E$15/'Scenario Comparison'!$B$15) -> 1.4266631e+08
A9: Concrete (Div 03) | B9: =SUMIFS('Construction Budget'!$H$78:$H$111,'Construction Budget'!$I$78:$I$111,"All Buildings")+SUMIFS('Construction Budget'!$H$78:$H$111,'Construction Budget'!$I$78:$I$111,"Shared") -> 33466040 | C9: =$B9*('Scenario Comparison'!C$15/'Scenario Comparison'!$B$15) -> 50592624 | D9: =$B9*('Scenario Comparison'!D$15/'Scenario Comparison'!$B$15) -> 50592624 | E9: =$B9*('Scenario Comparison'!E$15/'Scenario Comparison'!$B$15) -> 75072036
A10: Metals / Structural Steel (Div 05) | B10: =SUMIFS('Construction Budget'!$H$129:$H$163,'Construction Budget'!$I$129:$I$163,"All Buildings")+SUMIFS('Construction Budget'!$H$129:$H$163,'Construction Budget'!$I$129:$I$163,"Shared") -> 40836400 | C10: =$B10*('Scenario Comparison'!C$15/'Scenario Comparison'!$B$15) -> 61734840 | D10: =$B10*('Scenario Comparison'!D$15/'Scenario Comparison'!$B$15) -> 61734840 | E10: =$B10*('Scenario Comparison'!E$15/'Scenario Comparison'!$B$15) -> 91605450
A11: Thermal & Moisture (Div 07) | B11: =SUMIFS('Construction Budget'!$H$177:$H$211,'Construction Budget'!$I$177:$I$211,"All Buildings")+SUMIFS('Construction Budget'!$H$177:$H$211,'Construction Budget'!$I$177:$I$211,"Shared") -> 38165651 | C11: =$B11*('Scenario Comparison'!C$15/'Scenario Comparison'!$B$15) -> 57697308 | D11: =$B11*('Scenario Comparison'!D$15/'Scenario Comparison'!$B$15) -> 57697308 | E11: =$B11*('Scenario Comparison'!E$15/'Scenario Comparison'!$B$15) -> 85614345
A12: Openings (Div 08) | B12: =SUMIFS('Construction Budget'!$H$215:$H$238,'Construction Budget'!$I$215:$I$238,"All Buildings")+SUMIFS('Construction Budget'!$H$215:$H$238,'Construction Budget'!$I$215:$I$238,"Shared") -> 13742210 | C12: =$B12*('Scenario Comparison'!C$15/'Scenario Comparison'!$B$15) -> 20774925 | D12: =$B12*('Scenario Comparison'!D$15/'Scenario Comparison'!$B$15) -> 20774925 | E12: =$B12*('Scenario Comparison'!E$15/'Scenario Comparison'!$B$15) -> 30826942
A13: Finishes (Div 09) | B13: =SUMIFS('Construction Budget'!$H$242:$H$271,'Construction Budget'!$I$242:$I$271,"All Buildings")+SUMIFS('Construction Budget'!$H$242:$H$271,'Construction Budget'!$I$242:$I$271,"Shared") -> 33189552 | C13: =$B13*('Scenario Comparison'!C$15/'Scenario Comparison'!$B$15) -> 50174640 | D13: =$B13*('Scenario Comparison'!D$15/'Scenario Comparison'!$B$15) -> 50174640 | E13: =$B13*('Scenario Comparison'!E$15/'Scenario Comparison'!$B$15) -> 74451809
A14: Specialties (Div 10) | B14: =SUMIFS('Construction Budget'!$H$275:$H$291,'Construction Budget'!$I$275:$I$291,"All Buildings")+SUMIFS('Construction Budget'!$H$275:$H$291,'Construction Budget'!$I$275:$I$291,"Shared") -> 4010233.4 | C14: =$B14*('Scenario Comparison'!C$15/'Scenario Comparison'!$B$15) -> 6062510.9 | D14: =$B14*('Scenario Comparison'!D$15/'Scenario Comparison'!$B$15) -> 6062510.9 | E14: =$B14*('Scenario Comparison'!E$15/'Scenario Comparison'!$B$15) -> 8995877.2
A15: Masonry (Div 04) | B15: =SUMIFS('Construction Budget'!$H$115:$H$125,'Construction Budget'!$I$115:$I$125,"All Buildings")+SUMIFS('Construction Budget'!$H$115:$H$125,'Construction Budget'!$I$115:$I$125,"Shared") -> 5656068 | C15: =$B15*('Scenario Comparison'!C$15/'Scenario Comparison'!$B$15) -> 8550617.9 | D15: =$B15*('Scenario Comparison'!D$15/'Scenario Comparison'!$B$15) -> 8550617.9 | E15: =$B15*('Scenario Comparison'!E$15/'Scenario Comparison'!$B$15) -> 12687863
A16: Wood, Plastics & Composites (Div 06) | B16: =SUMIFS('Construction Budget'!$H$167:$H$173,'Construction Budget'!$I$167:$I$173,"All Buildings")+SUMIFS('Construction Budget'!$H$167:$H$173,'Construction Budget'!$I$167:$I$173,"Shared") -> 1233678.6 | C16: =$B16*('Scenario Comparison'!C$15/'Scenario Comparison'!$B$15) -> 1865026.1 | D16: =$B16*('Scenario Comparison'!D$15/'Scenario Comparison'!$B$15) -> 1865026.1 | E16: =$B16*('Scenario Comparison'!E$15/'Scenario Comparison'!$B$15) -> 2767425.2
A17: Equipment (Div 11) | B17: =SUMIFS('Construction Budget'!$H$295:$H$304,'Construction Budget'!$I$295:$I$304,"All Buildings")+SUMIFS('Construction Budget'!$H$295:$H$304,'Construction Budget'!$I$295:$I$304,"Shared") -> 1525590 | C17: =$B17*('Scenario Comparison'!C$15/'Scenario Comparison'!$B$15) -> 2306326.1 | D17: =$B17*('Scenario Comparison'!D$15/'Scenario Comparison'!$B$15) -> 2306326.1 | E17: =$B17*('Scenario Comparison'!E$15/'Scenario Comparison'!$B$15) -> 3422249.7
A18: Furnishings (Div 12) | B18: =SUMIFS('Construction Budget'!$H$308:$H$314,'Construction Budget'!$I$308:$I$314,"All Buildings")+SUMIFS('Construction Budget'!$H$308:$H$314,'Construction Budget'!$I$308:$I$314,"Shared") -> 1217056.5 | C18: =$B18*('Scenario Comparison'!C$15/'Scenario Comparison'!$B$15) -> 1839897.5 | D18: =$B18*('Scenario Comparison'!D$15/'Scenario Comparison'!$B$15) -> 1839897.5 | E18: =$B18*('Scenario Comparison'!E$15/'Scenario Comparison'!$B$15) -> 2730138
A19: Conveying Equipment (Div 14) | B19: =SUMIFS('Construction Budget'!$H$318:$H$323,'Construction Budget'!$I$318:$I$323,"All Buildings")+SUMIFS('Construction Budget'!$H$318:$H$323,'Construction Budget'!$I$318:$I$323,"Shared") -> 4104292.5 | C19: =$B19*('Scenario Comparison'!C$15/'Scenario Comparison'!$B$15) -> 6204705.6 | D19: =$B19*('Scenario Comparison'!D$15/'Scenario Comparison'!$B$15) -> 6204705.6 | E19: =$B19*('Scenario Comparison'!E$15/'Scenario Comparison'!$B$15) -> 9206873.4
A21: TOTAL CSA | B21: =SUM(B6:B19) -> 2.7573192e+08 | C21: =SUM(C6:C19) -> 4.1684051e+08 | D21: =SUM(D6:D19) -> 4.1684051e+08 | E21: =SUM(E6:E19) -> 6.1853019e+08
A22: Hyperscale / Air-Cooled / AI-HPC = Base division mix scaled to each scenario's CSA total (Scenario Comparison) — indicative, not separately estimated.
A23: CSA UNIT METRICS
A24: GBA (SF) | B24: ='Campus Rollup'!$C$16 -> 800000 | C24: ='Campus Rollup'!$C$16 -> 800000 | D24: ='Campus Rollup'!$C$16 -> 800000 | E24: ='Campus Rollup'!$C$16 -> 800000
A25: CSA $/SF | B25: =B21/B24 -> 344.66489 | C25: =C21/C24 -> 521.05064 | D25: =D21/D24 -> 521.05064 | E25: =E21/E24 -> 773.16274
A27: CSA IN CONTEXT
A28: Total CSA cost | B28: =B21 -> 2.7573192e+08
A29: Campus CSA $/SF (blended) | B29: =B25 -> 344.66489
A30: CSA % of total construction | B30: =B21/'Campus Rollup'!H16 -> 0.25335047
A31: CSA % of all-in TDC | B31: =B21/'Total Development Cost'!C35 -> 0.18225705
A34: — chart source data —
A35: =A6 -> Earthwork (Div 31) | B35: =B6 -> 25614732
A36: =A7 -> Exterior Improvements (Div 32) | B36: =B7 -> 9371809.5
A37: =A8 -> Utilities (Div 33) | B37: =B8 -> 63598602
A38: =A9 -> Concrete (Div 03) | B38: =B9 -> 33466040
A39: =A10 -> Metals / Structural Steel (Div 05) | B39: =B10 -> 40836400
A40: =A11 -> Thermal & Moisture (Div 07) | B40: =B11 -> 38165651
A41: =A12 -> Openings (Div 08) | B41: =B12 -> 13742210
A42: =A13 -> Finishes (Div 09) | B42: =B13 -> 33189552
A43: =A14 -> Specialties (Div 10) | B43: =B14 -> 4010233.4
A44: =A15 -> Masonry (Div 04) | B44: =B15 -> 5656068
A45: =A16 -> Wood, Plastics & Composites (Div 06) | B45: =B16 -> 1233678.6
A46: =A17 -> Equipment (Div 11) | B46: =B17 -> 1525590
... A48: =A19 -> Conveying Equipment (Div 14) | B48: =B19 -> 4104292.5

Sheet Unit Cost Database
A1: DATA CENTER — UNIT COST DATABASE / STANDARD REFERENCE PRICING | H1: Pricing Tier: | I1: ='Scenario & Presets'!B15 -> Low
A3: CSI Code | B3: Description | C3: Unit | D3: Low Range | E3: Mid Range | F3: High Range | G3: Notes | H3: Selected Price
A4: 31 10 00 | B4: Site Clearing & Demolition | C4: SF | D4: 1.5 | E4: 2.5 | F4: 4 | G4: Per SF of site area; varies with existing conditions | H4: =IF(OR($A4="",$A4="—"),"",CHOOSE(MATCH($I$1,{"Low","Mid","High"},0),D4,E4,F4)) -> 1.5
A5: 31 22 00 | B5: Grading & Excavation | C5: CY | D5: 8 | E5: 15 | F5: 25 | G5: Per cubic yard; rock excavation at high end | H5: =IF(OR($A5="",$A5="—"),"",CHOOSE(MATCH($I$1,{"Low","Mid","High"},0),D5,E5,F5)) -> 8
A6: 31 23 00 | B6: Fill, Backfill & Compaction | C6: CY | D6: 12 | E6: 22 | F6: 35 | G6: Includes import fill, placement, and proof-roll | H6: =IF(OR($A6="",$A6="—"),"",CHOOSE(MATCH($I$1,{"Low","Mid","High"},0),D6,E6,F6)) -> 12
A7: 31 62 00 | B7: Driven Piles | C7: LF | D7: 35 | E7: 55 | F7: 85 | G7: Per LF of pile; steel H-pile typical | H7: =IF(OR($A7="",$A7="—"),"",CHOOSE(MATCH($I$1,{"Low","Mid","High"},0),D7,E7,F7)) -> 35
A8: 32 12 00 | B8: Asphalt Paving | C8: SF | D8: 3.5 | E8: 5.5 | F8: 8 | G8: 4" HMA over 8" aggregate base | H8: =IF(OR($A8="",$A8="—"),"",CHOOSE(MATCH($I$1,{"Low","Mid","High"},0),D8,E8,F8)) -> 3.5
A9: 32 13 00 | B9: Concrete Paving | C9: SF | D9: 7 | E9: 11 | F9: 16 | G9: 6" reinforced concrete; truck aprons higher | H9: =IF(OR($A9="",$A9="—"),"",CHOOSE(MATCH($I$1,{"Low","Mid","High"},0),D9,E9,F9)) -> 7
A10: 32 31 00 | B10: Security Fencing — 8' Chain Link + Barbed Wire | C10: LF | D10: 45 | E10: 75 | F10: 120 | G10: Per LF including gates; K-rated bollards separate | H10: =IF(OR($A10="",$A10="—"),"",CHOOSE(MATCH($I$1,{"Low","Mid","High"},0),D10,E10,F10)) -> 45
A11: 33 10 00 | B11: Water Distribution — Main Connection | C11: LS | D11: 75000 | E11: 150000 | F11: 300000 | G11: Tap, meter, backflow, site distribution | H11: =IF(OR($A11="",$A11="—"),"",CHOOSE(MATCH($I$1,{"Low","Mid","High"},0),D11,E11,F11)) -> 75000
A12: 33 40 00 | B12: Storm Drainage System | C12: SF | D12: 2.5 | E12: 5 | F12: 9 | G12: Per SF of site; includes detention/retention | H12: =IF(OR($A12="",$A12="—"),"",CHOOSE(MATCH($I$1,{"Low","Mid","High"},0),D12,E12,F12)) -> 2.5
A13: 33 50 00 | B13: Fuel Oil Distribution — Generator Farm | C13: GAL | D13: 3 | E13: 5.5 | F13: 8.5 | G13: Per gallon of storage capacity; AST w/ piping | H13: =IF(OR($A13="",$A13="—"),"",CHOOSE(MATCH($I$1,{"Low","Mid","High"},0),D13,E13,F13)) -> 3
A14: 33 71 00 | B14: Electrical Utility — Primary Service Entrance | C14: MW | D14: 250000 | E14: 450000 | F14: 750000 | G14: Per MW; includes ductbank, switchgear pad, metering | H14: =IF(OR($A14="",$A14="—"),"",CHOOSE(MATCH($I$1,{"Low","Mid","High"},0),D14,E14,F14)) -> 250000
A15: 03 30 00 | B15: Cast-in-Place Concrete — Foundations | C15: CY | D15: 450 | E15: 650 | F15: 950 | G15: Per CY placed; includes form, rebar, finish | H15: =IF(OR($A15="",$A15="—"),"",CHOOSE(MATCH($I$1,{"Low","Mid","High"},0),D15,E15,F15)) -> 450
... A304: 25 95 00 | B304: Integration Testing, Tuning & Cx Support | C304: LS | D304: 800000 | E304: 1150000 | F304: 1600000 | G304: Integrated systems testing support to Cx | H304: =IF(OR($A304="",$A304="—"),"",CHOOSE(MATCH($I$1,{"Low","Mid","High"},0),D304,E304,F304)) -> 800000
A305: 31 23 20 | B305: Dewatering — Construction | C305: LS | D305: 350000 | E305: 550000 | F305: 850000 | G305: Added detail — earthwork supplemental | H305: =IF($A305="","",CHOOSE(MATCH($I$1,{"Low","Mid","High"},0),D305,E305,F305)) -> 350000
A306: 31 05 13 | B306: Aggregate Base Course — Under Slab/Paving | C306: CY | D306: 38 | E306: 52 | F306: 72 | G306: Added detail — earthwork supplemental | H306: =IF($A306="","",CHOOSE(MATCH($I$1,{"Low","Mid","High"},0),D306,E306,F306)) -> 38
A307: 31 32 00 | B307: Geotextile / Soil Stabilization Fabric | C307: SF | D307: 0.6 | E307: 0.95 | F307: 1.5 | G307: Added detail — earthwork supplemental | H307: =IF($A307="","",CHOOSE(MATCH($I$1,{"Low","Mid","High"},0),D307,E307,F307)) -> 0.6
A308: 32 32 50 | B308: Retaining Walls — Site | C308: SF | D308: 45 | E308: 68 | F308: 98 | G308: Added detail — exterior supplemental | H308: =IF($A308="","",CHOOSE(MATCH($I$1,{"Low","Mid","High"},0),D308,E308,F308)) -> 45
A309: 32 17 50 | B309: Guard Rails & Crash Barriers — Site | C309: LF | D309: 55 | E309: 85 | F309: 130 | G309: Added detail — exterior supplemental | H309: =IF($A309="","",CHOOSE(MATCH($I$1,{"Low","Mid","High"},0),D309,E309,F309)) -> 55
A310: 33 52 50 | B310: Natural Gas Service & Distribution | C310: LF | D310: 85 | E310: 130 | F310: 195 | G310: Added detail — utilities supplemental | H310: =IF($A310="","",CHOOSE(MATCH($I$1,{"Low","Mid","High"},0),D310,E310,F310)) -> 85
A311: 33 82 50 | B311: Communications Ductbank — Site | C311: LF | D311: 140 | E311: 200 | F311: 300 | G311: Added detail — utilities supplemental | H311: =IF($A311="","",CHOOSE(MATCH($I$1,{"Low","Mid","High"},0),D311,E311,F311)) -> 140
A312: 03 15 00 | B312: Under-Slab Vapor Barrier & Joints | C312: SF | D312: 1.1 | E312: 1.7 | F312: 2.6 | G312: Added detail — concrete supplemental | H312: =IF($A312="","",CHOOSE(MATCH($I$1,{"Low","Mid","High"},0),D312,E312,F312)) -> 1.1
A313: 03 30 70 | B313: Concrete Testing & Inspection | C313: LS | D313: 180000 | E313: 280000 | F313: 420000 | G313: Added detail — concrete supplemental | H313: =IF($A313="","",CHOOSE(MATCH($I$1,{"Low","Mid","High"},0),D313,E313,F313)) -> 180000
A314: 05 12 50 | B314: Anchor Bolts & Embed Plates — Structural | C314: LS | D314: 220000 | E314: 340000 | F314: 520000 | G314: Added detail — metals supplemental | H314: =IF($A314="","",CHOOSE(MATCH($I$1,{"Low","Mid","High"},0),D314,E314,F314)) -> 220000
A315: 07 27 00 | B315: Air & Vapor Barrier — Building Envelope | C315: SF | D315: 2.2 | E315: 3.4 | F315: 5 | G315: Added detail — thermal/moisture supplemental | H315: =IF($A315="","",CHOOSE(MATCH($I$1,{"Low","Mid","High"},0),D315,E315,F315)) -> 2.2
A316: 07 95 00 | B316: Expansion Joint Cover Assemblies | C316: LF | D316: 65 | E316: 95 | F316: 145 | G316: Added detail — thermal/moisture supplemental | H316: =IF($A316="","",CHOOSE(MATCH($I$1,{"Low","Mid","High"},0),D316,E316,F316)) -> 65
... A703: 33 40 03 | B703: Storm Drainage — Install | C703: LS | D703: 300000 | E703: 600000 | F703: 1080000 | G703: Decomposed from 33 40 00 | H703: =IF($A703="","",CHOOSE(MATCH($I$1,{"Low","Mid","High"},0),D703,E703,F703)) -> 300000
A704: CX 02 00 | B704: Level 1 Cx — Factory Witness Testing | C704: MW | D704: 35000 | E704: 40250 | F704: 47250 | G704: Added from Construction Budget CX/SC section; Low = current budget basis (NoVA). | H704: =IF(OR($A704="",$A704="—"),"",CHOOSE(MATCH($I$1,{"Low","Mid","High"},0),D704,E704,F704)) -> 35000
A705: CX 03 00 | B705: Level 2 Cx — Component Verification (Individual Equipment) | C705: MW | D705: 45000 | E705: 51750 | F705: 60750 | G705: Added from Construction Budget CX/SC section; Low = current budget basis (NoVA). | H705: =IF(OR($A705="",$A705="—"),"",CHOOSE(MATCH($I$1,{"Low","Mid","High"},0),D705,E705,F705)) -> 45000
A706: CX 04 00 | B706: Level 3 Cx — Subsystem Verification | C706: MW | D706: 55000 | E706: 63250 | F706: 74250 | G706: Added from Construction Budget CX/SC section; Low = current budget basis (NoVA). | H706: =IF(OR($A706="",$A706="—"),"",CHOOSE(MATCH($I$1,{"Low","Mid","High"},0),D706,E706,F706)) -> 55000
A707: CX 05 00 | B707: Level 4 Cx — System Verification (Integrated) | C707: MW | D707: 75000 | E707: 86250 | F707: 101250 | G707: Added from Construction Budget CX/SC section; Low = current budget basis (NoVA). | H707: =IF(OR($A707="",$A707="—"),"",CHOOSE(MATCH($I$1,{"Low","Mid","High"},0),D707,E707,F707)) -> 75000
A708: CX 07 00 | B708: Performance Verification Testing | C708: MW | D708: 65000 | E708: 74750 | F708: 87750 | G708: Added from Construction Budget CX/SC section; Low = current budget basis (NoVA). | H708: =IF(OR($A708="",$A708="—"),"",CHOOSE(MATCH($I$1,{"Low","Mid","High"},0),D708,E708,F708)) -> 65000
A709: CX 08 00 | B709: Seasonal Testing — Summer / Winter Peaks | C709: MW | D709: 45000 | E709: 51750 | F709: 60750 | G709: Added from Construction Budget CX/SC section; Low = current budget basis (NoVA). | H709: =IF(OR($A709="",$A709="—"),"",CHOOSE(MATCH($I$1,{"Low","Mid","High"},0),D709,E709,F709)) -> 45000
A710: CX 09 00 | B710: Failure Mode & Effects Testing (FMEA) | C710: MW | D710: 35000 | E710: 40250 | F710: 47250 | G710: Added from Construction Budget CX/SC section; Low = current budget basis (NoVA). | H710: =IF(OR($A710="",$A710="—"),"",CHOOSE(MATCH($I$1,{"Low","Mid","High"},0),D710,E710,F710)) -> 35000
A711: CX 10 00 | B711: Documentation — O&M Manuals, As-Builts | C711: MW | D711: 25000 | E711: 28750 | F711: 33750 | G711: Added from Construction Budget CX/SC section; Low = current budget basis (NoVA). | H711: =IF(OR($A711="",$A711="—"),"",CHOOSE(MATCH($I$1,{"Low","Mid","High"},0),D711,E711,F711)) -> 25000
A712: CX 11 00 | B712: Staff Training — Critical Systems Operation | C712: MW | D712: 18000 | E712: 20700 | F712: 24300 | G712: Added from Construction Budget CX/SC section; Low = current budget basis (NoVA). | H712: =IF(OR($A712="",$A712="—"),"",CHOOSE(MATCH($I$1,{"Low","Mid","High"},0),D712,E712,F712)) -> 18000
A713: CX 12 00 | B713: Uptime Institute Tier Certification Support | C713: LS | D713: 250000 | E713: 287500 | F713: 337500 | G713: Added from Construction Budget CX/SC section; Low = current budget basis (NoVA). | H713: =IF(OR($A713="",$A713="—"),"",CHOOSE(MATCH($I$1,{"Low","Mid","High"},0),D713,E713,F713)) -> 250000
A714: CX 13 00 | B714: Temporary Provisions — Load Banks for IST | C714: MW | D714: 35000 | E714: 40250 | F714: 47250 | G714: Added from Construction Budget CX/SC section; Low = current budget basis (NoVA). | H714: =IF(OR($A714="",$A714="—"),"",CHOOSE(MATCH($I$1,{"Low","Mid","High"},0),D714,E714,F714)) -> 35000
A715: CX 14 00 | B715: Deficiency Tracking & Remediation | C715: MW | D715: 25000 | E715: 28750 | F715: 33750 | G715: Added from Construction Budget CX/SC section; Low = current budget basis (NoVA). | H715: =IF(OR($A715="",$A715="—"),"",CHOOSE(MATCH($I$1,{"Low","Mid","High"},0),D715,E715,F715)) -> 25000
... A759: 23 81 00 | B759: Packaged DX Units — Electrical / Admin Rooms | C759: TON | D759: 1200 | E759: 1380 | F759: 1620 | G759: Added scope — typical hyperscale allowance; Low = budget basis. | H759: =IF(OR($A759="",$A759="—"),"",CHOOSE(MATCH($I$1,{"Low","Mid","High"},0),D759,E759,F759)) -> 1200

Sheet Allowances & Alternates
A1: DATA CENTER — ALLOWANCES & ALTERNATES
A3: ALLOWANCES
A4: # | B4: Description | C4: CSI Div | D4: Allowance Amt | E4: Actual Cost | F4: Variance | G4: Status | H4: Vendor | I4: Notes
A5: 1 | B5: Owner-Furnished Equipment Allowance | C5: 27 | D5: 2500000 | E5: 0 | F5: =D5-E5 -> 2500000 | G5: Pending
A6: 2 | B6: Fiber Optic Entrance — Carrier Buildout | C6: 27 | D6: 1200000 | E6: 0 | F6: =D6-E6 -> 1200000 | G6: Pending
A7: 3 | B7: Office / NOC Furniture | C7: 10 | D7: 850000 | E7: 0 | F7: =D7-E7 -> 850000 | G7: Pending
A8: 4 | B8: Landscaping Allowance | C8: 32 | D8: 350000 | E8: 0 | F8: =D8-E8 -> 350000 | G8: Pending
A9: 5 | B9: Security System Enhancements | C9: 28 | D9: 750000 | E9: 0 | F9: =D9-E9 -> 750000 | G9: Pending
A10: 6 | B10: Generator Fuel Fill — Initial | C10: 33 | D10: 425000 | E10: 0 | F10: =D10-E10 -> 425000 | G10: Pending
A11: 7 | B11: Contingency (suppressed — included in budget lines) | C11: 1 | D11: 0 | E11: 0 | F11: =D11-E11 -> 0 | G11: Pending
A12: 8 | B12: IT Cabinet Accessories | C12: 27 | D12: 500000 | E12: 0 | F12: =D12-E12 -> 500000 | G12: Pending
A13: 9 | B13: Commissioning & Integrated Systems Testing (L1–L5 IST) | C13: 1 | D13: 1800000 | E13: 0 | F13: =D13-E13 -> 1800000 | G13: Pending | I13: L5 integrated systems test across electrical/mechanical; pull/fail testing
A14: 10 | B14: DCIM & Building Management System Integration | C14: 25 | D14: 900000 | E14: 0 | F14: =D14-E14 -> 900000 | G14: Pending | I14: DCIM platform, BMS graphics/programming, sensor integration
A15: 11 | B15: Structured Cabling Backbone (MMR / MDA / Cross-Connect) | C15: 27 | D15: 1500000 | E15: 0 | F15: =D15-E15 -> 1500000 | G15: Pending | I15: OS2 fiber backbone, Cat6A, cross-connect fields in MMR/MDA
A16: 12 | B16: Clean-Agent Fire Suppression & VESDA Detection | C16: 21 | D16: 1100000 | E16: 0 | F16: =D16-E16 -> 1100000 | G16: Pending | I16: Inert/clean-agent in data halls; VESDA aspirating smoke detection
A17: 13 | B17: Grounding, Bonding & Lightning Protection | C17: 26 | D17: 650000 | E17: 0 | F17: =D17-E17 -> 650000 | G17: Pending | I17: Signal reference grid, telecom bonding backbone, LPS air terminals
A18: 14 | B18: Critical Spare Parts & Maintenance Inventory | C18: 23 | D18: 1250000 | E18: 0 | F18: =D18-E18 -> 1250000 | G18: Pending | I18: OEM spares for CRAH/CRAC, breakers, pumps, UPS modules
A19: 15 | B19: Utility Interconnection & Substation Fees | C19: 33 | D19: 2200000 | E19: 0 | F19: =D19-E19 -> 2200000 | G19: Pending | I19: Utility interconnection, primary switchgear/substation contributions
A20: 16 | B20: Signage, Wayfinding & ADA Compliance | C20: 10 | D20: 175000 | E20: 0 | F20: =D20-E20 -> 175000 | G20: Pending | I20: Code/arc-flash signage, room ID, ADA wayfinding
A21: 17 | B21: Temporary Construction Power & Conditioning | C21: 1 | D21: 600000 | E21: 0 | F21: =D21-E21 -> 600000 | G21: Pending | I21: Temp power, generators, distribution for construction phase
A22: 18 | B22: Hazmat Abatement / Unforeseen Site Conditions | C22: 2 | D22: 800000 | E22: 0 | F22: =D22-E22 -> 800000 | G22: Pending | I22: Abatement, dewatering, rock/soil remediation contingency
B23: TOTAL ALLOWANCES | D23: =SUM(D5:D22) -> 17550000 | E23: =SUM(E5:E22) -> 0 | F23: =SUM(F5:F22) -> 17550000
A25: ALTERNATES — TIER UPGRADES & OPTIONS
A26: Alt # | B26: Description | C26: CSI Div | D26: Baseline Cost | E26: Upgrade Cost | F26: Net Add ($) | G26: Accepted? | H26: Tier Impact | I26: Notes
A27: ALT-01 | B27: Tier III → Tier IV Electrical (2N UPS/Gen) | C27: 26 | D27: 217800000 | E27: 326700000 | F27: =E27-D27 -> 108900000 | G27: No | H27: Tier IV
A28: ALT-02 | B28: Tier III → Tier IV Mechanical (2N Cooling) | C28: 23 | D28: 2074286 | E28: 18500000 | F28: =E28-D28 -> 16425714 | G28: No | H28: Tier IV
A29: ALT-03 | B29: Liquid Cooling Infrastructure (in lieu of air) | C29: 23 | D29: 0 | E29: 8500000 | F29: =E29-D29 -> 8500000 | G29: No | H29: Tier III/IV
A30: ALT-04 | B30: On-Site Renewable — Solar Canopy | C30: 26 | D30: 0 | E30: 12000000 | F30: =E30-D30 -> 12000000 | G30: No | H30: None
A31: ALT-05 | B31: Battery Energy Storage System (BESS) | C31: 26 | D31: 9199228 | E31: 15800000 | F31: =E31-D31 -> 6600772 | G31: No | H31: Tier III/IV
A32: ALT-06 | B32: Lithium-Ion UPS Batteries (vs. VRLA) | C32: 26 | D32: 6222857 | E32: 4200000 | F32: =E32-D32 -> -2022857 | G32: No | H32: None
A33: ALT-07 | B33: Free Cooling — Airside Economizer | C33: 23 | D33: 16830000 | E33: 21500000 | F33: =E33-D33 -> 4670000 | G33: No | H33: None
A34: ALT-08 | B34: Enhanced Physical Security — Anti-Ram | C34: 28 | D34: 12588417 | E34: 14200000 | F34: =E34-D34 -> 1611583 | G34: No | H34: None
A35: ALT-09 | B35: Generator — Natural Gas (vs. Diesel) | C35: 26 | D35: 7882286 | E35: 12500000 | F35: =E35-D35 -> 4617714 | G35: No | H35: None
A36: ALT-10 | B36: High-Density Cooling (30+ kW/rack) | C36: 23 | D36: 990000000 | E36: 880000000 | F36: =E36-D36 -> -110000000 | G36: No | H36: None
A37: ALT-11 | B37: Modular / Prefab Data Hall Pod | C37: All | D37: 475200 | E37: 1850000 | F37: =E37-D37 -> 1374800 | G37: No | H37: Tier II/III
A38: ALT-12 | B38: Additional Meet-Me Room / Carrier Entrance | C38: 27 | D38: 0 | E38: 0 | F38: =E38-D38 -> 0 | G38: No | H38: None
B39: TOTAL ACCEPTED ALTERNATES | F39: =SUMIF(G27:G38,"Yes",F27:F38) -> 0
A42: SUMMARY
B44: Total Allowances: | F44: =D23 -> 17550000
B45: Total Accepted Alternates: | F45: =F39 -> 0
B46: Combined Net Impact (Allowances + Accepted Alts): | F46: =F44+F45 -> 17550000
B50: ACCEPTED ALTERNATES (for Proposal): | G50: =F39 -> 0

Sheet Location Factors
A1: DATA CENTER — LOCATION ADJUSTMENT FACTORS
A3: Selected Market: | B3: Northern Virginia
A4: Baseline Market: | B4: Northern Virginia (Index = 1.00)
A6: MASTER LOCATION FACTOR: | B6: =IFERROR(VLOOKUP(B3,A$31:C$204,3,FALSE()),1) -> 1
A7: Selected Region / Country: | B7: =IFERROR(VLOOKUP(B3,$A$31:$E$204,2,FALSE())&" · "&VLOOKUP(B3,$A$31:$E$204,5,FALSE()),"") -> North America · United States
A8: CATEGORY ADJUSTMENT FACTORS
A9: Category | B9: Base Factor | C9: Category Adj. | D9: Combined Factor | E9: Notes
A10: Site Work | B10: =$B$6 -> 1 | C10: 0 | D10: =B10*(1+C10) -> 1 | E10: Earthwork, paving, utilities, fencing
A11: Concrete | B11: =$B$6 -> 1 | C11: 0 | D11: =B11*(1+C11) -> 1 | E11: Foundations, slabs, precast
A12: Structural Steel | B12: =$B$6 -> 1 | C12: 0.02 | D12: =B12*(1+C12) -> 1.02 | E12: Steel erection, decking, misc metals
A13: Building Envelope | B13: =$B$6 -> 1 | C13: 0 | D13: =B13*(1+C13) -> 1 | E13: Roofing, wall panels, waterproofing
A14: Plumbing | B14: =$B$6 -> 1 | C14: 0 | D14: =B14*(1+C14) -> 1 | E14: Domestic water, make-up water, drains
A15: Fire Suppression | B15: =$B$6 -> 1 | C15: 0.03 | D15: =B15*(1+C15) -> 1.03 | E15: Clean agent, sprinkler, VESDA, alarm
A16: HVAC / Cooling | B16: =$B$6 -> 1 | C16: 0.05 | D16: =B16*(1+C16) -> 1.05 | E16: Chillers, CRAHs, towers, piping, controls
A17: Electrical / Critical Power | B17: =$B$6 -> 1 | C17: 0.06 | D17: =B17*(1+C17) -> 1.06 | E17: Switchgear, generators, UPS, PDUs
A18: IT Infrastructure | B18: =$B$6 -> 1 | C18: 0 | D18: =B18*(1+C18) -> 1 | E18: Cabling, racks, DCIM, leak detection
A19: Communications | B19: =$B$6 -> 1 | C19: 0 | D19: =B19*(1+C19) -> 1 | E19: Cabling, cabinets, DCIM, leak detection
A20: Security | B20: =$B$6 -> 1 | C20: 0.05 | D20: =B20*(1+C20) -> 1.05 | E20: Access control, CCTV, intrusion detection
A21: Commissioning | B21: =$B$6 -> 1 | C21: 0.08 | D21: =B21*(1+C21) -> 1.08 | E21: L1-L5 Cx, IST, seasonal, FMEA
... A26: Soft Costs | B26: =$B$6 -> 1 | C26: -0.02 | D26: =B26*(1+C26) -> 0.98 | E26: A/E fees, CxA, Uptime cert, BIM, legal
A29: MARKET INDEX TABLE
A30: Market | B30: Region | C30: Factor | D30: State | E30: Country
A31: Northern Virginia | B31: North America | C31: 1 | D31: VA | E31: United States
A32: Albuquerque, NM | B32: North America | C32: 0.86 | D32: NM | E32: United States
A33: Atlanta | B33: North America | C33: 0.86 | D33: GA | E33: United States
A34: Austin, TX | B34: North America | C34: 0.9 | D34: TX | E34: United States
A35: Baltimore, MD | B35: North America | C35: 0.98 | D35: MD | E35: United States
A36: Birmingham, AL | B36: North America | C36: 0.82 | D36: AL | E36: United States
A37: Boise, ID | B37: North America | C37: 0.88 | D37: ID | E37: United States
A38: Boston, MA | B38: North America | C38: 1.24 | D38: MA | E38: United States
A39: Buffalo, NY | B39: North America | C39: 1.03 | D39: NY | E39: United States
A40: Charlotte, NC | B40: North America | C40: 0.85 | D40: NC | E40: United States
A41: Chicago | B41: North America | C41: 1.05 | D41: IL | E41: United States
A42: Cincinnati, OH | B42: North America | C42: 0.95 | D42: OH | E42: United States
... A92: Virginia Beach / Norfolk, VA | B92: North America | C92: 0.88 | D92: VA | E92: United States
A93: Toronto | B93: North America | C93: 1.12 | E93: Canada
A94: Montreal | B94: North America | C94: 1.02 | E94: Canada
A95: London | B95: Europe | C95: 1.35 | E95: United Kingdom
A96: Frankfurt | B96: Europe | C96: 1.22 | E96: Germany
A97: Amsterdam | B97: Europe | C97: 1.18 | E97: Netherlands
A98: Dublin | B98: Europe | C98: 1.15 | E98: Ireland
A99: Paris | B99: Europe | C99: 1.3 | E99: France
A100: Stockholm | B100: Europe | C100: 1.25 | E100: Sweden
A101: Singapore | B101: Asia-Pacific | C101: 1.2 | E101: Singapore
A102: Tokyo | B102: Asia-Pacific | C102: 1.4 | E102: Japan
A103: Sydney | B103: Asia-Pacific | C103: 1.18 | E103: Australia
A104: Mumbai | B104: Asia-Pacific | C104: 0.55 | E104: India
A105: Carson City, NV | B105: North America | C105: 1.01 | D105: NV | E105: United States
A106: Eagle Pass, TX | B106: North America | C106: 0.79 | D106: TX | E106: United States
A107: Enid, OK | B107: North America | C107: 0.81 | D107: OK | E107: United States
A108: Walla Walla, WA | B108: North America | C108: 0.97 | D108: WA | E108: United States
A109: Lewiston, ID-WA | B109: North America | C109: 0.85 | D109: ID | E109: United States
A110: Minot, ND | B110: North America | C110: 0.99 | D110: ND | E110: United States
A111: Grand Island, NE | B111: North America | C111: 0.87 | D111: NE | E111: United States
A112: Casper, WY | B112: North America | C112: 0.96 | D112: WY | E112: United States
A113: Elmira, NY | B113: North America | C113: 0.99 | D113: NY | E113: United States
A114: Midland, MI | B114: North America | C114: 0.93 | D114: MI | E114: United States
A115: Kokomo, IN | B115: North America | C115: 0.89 | D115: IN | E115: United States
A116: Great Falls, MT | B116: North America | C116: 0.95 | D116: MT | E116: United States
... A204: Jefferson City, MO | B204: North America | C204: 0.92 | D204: MO | E204: United States
A206: STATE CONSTRUCTION COST FACTORS — MODELED REFERENCE (not linked; Northern Virginia = 1.00)
A207: State | B207: Factor
A208: AK | B208: 1.25
A209: AL | B209: 0.82
A210: AR | B210: 0.8
A211: AZ | B211: 0.87
A212: CA | B212: 1.08
A213: CO | B213: 0.99
A214: CT | B214: 1.07
A215: DE | B215: 1
A216: FL | B216: 0.86
A217: GA | B217: 0.85
A218: HI | B218: 1.27
A219: IA | B219: 0.92
... A257: WY | B257: 0.92

Sheet Value Engineering
A1: VALUE ENGINEERING LOG
A3: VE proposals — pricing, status, and decision rationale. Items marked Accepted flow into the budget; Pending items are reviewed at the next milestone.
A5: # | B5: ID | C5: Description | D5: Division | E5: Building | F5: Baseline Cost | G5: Proposed Cost | H5: Savings ($) | I5: Savings (%) | J5: Schedule Impact | K5: Quality / Risk | L5: Status | M5: Decision Date | N5: Owner
A6: 1 | B6: VE-001 | C6: Tilt-up panels in lieu of CMU exterior wall | D6: 7 | E6: All Buildings | F6: 1786466 | G6: 1450000 | H6: =IF(OR(F6=0,G6=0),0,F6-G6) -> 336466 | I6: =IF(F6=0,0,H6/F6) -> 0.18834168 | J6: Saves 2 weeks | K6: Low — proven tilt-up method for DC | L6: Accepted
A7: 2 | B7: VE-002 | C7: Reduce slab thickness in admin building | D7: 3 | E7: All Buildings | F7: 4500000 | G7: 3825000 | H7: =IF(OR(F7=0,G7=0),0,F7-G7) -> 675000 | I7: =IF(F7=0,0,H7/F7) -> 0.15 | J7: None | K7: Low — admin area only, not data halls | L7: Accepted
A8: 3 | B8: VE-003 | C8: Single-source steel package across campus | D8: 5 | E8: Shared | F8: 34650000 | G8: 32200000 | H8: =IF(OR(F8=0,G8=0),0,F8-G8) -> 2450000 | I8: =IF(F8=0,0,H8/F8) -> 0.070707071 | J8: Saves 3 weeks | K8: Med — single-source risk; bond required | L8: Accepted
A9: 4 | B9: VE-004 | C9: Defer landscaping to post-occupancy | D9: 32 | E9: Shared | F9: 528000 | G9: 0 | H9: =IF(OR(F9=0,G9=0),0,F9-G9) -> 0 | I9: =IF(F9=0,0,H9/F9) -> 0 | J9: None | K9: Low — deferred to post-CO, cosmetic only | L9: Accepted
A10: 5 | B10: VE-005 | C10: Standardize door hardware across all buildings | D10: 8 | E10: Shared | F10: 409398 | G10: 365000 | H10: =IF(OR(F10=0,G10=0),0,F10-G10) -> 44398 | I10: =IF(F10=0,0,H10/F10) -> 0.10844704 | J10: None | K10: Low — reduces procurement complexity | L10: Accepted
A11: 6 | B11: VE-006 | C11: Overhead busway in lieu of conduit + cable whips (data halls) | D11: 26 | E11: All Buildings | F11: 24000000 | G11: 19500000 | H11: =IF(OR(F11=0,G11=0),0,F11-G11) -> 4500000 | I11: =IF(F11=0,0,H11/F11) -> 0.1875 | J11: Saves time | K11: Low risk | L11: Accepted
A12: 7 | B12: VE-007 | C12: Air-cooled chillers; eliminate cooling towers + CW treatment | D12: 23 | E12: All Buildings | F12: 47500000 | G12: 41000000 | H12: =IF(OR(F12=0,G12=0),0,F12-G12) -> 6500000 | I12: =IF(F12=0,0,H12/F12) -> 0.13684211 | J12: +0 days | K12: Med risk | L12: Pending
A13: 8 | B13: VE-008 | C13: Prefabricated electrical skids (modular PDU / RPP) | D13: 26 | E13: All Buildings | F13: 18000000 | G13: 15200000 | H13: =IF(OR(F13=0,G13=0),0,F13-G13) -> 2800000 | I13: =IF(F13=0,0,H13/F13) -> 0.15555556 | J13: Saves time | K13: Low risk | L13: Accepted
A14: 9 | B14: VE-009 | C14: VRF for office / admin in lieu of chilled-water AHUs | D14: 23 | E14: Shared | F14: 3200000 | G14: 2400000 | H14: =IF(OR(F14=0,G14=0),0,F14-G14) -> 800000 | I14: =IF(F14=0,0,H14/F14) -> 0.25 | J14: +0 days | K14: Low risk | L14: Accepted
A15: 10 | B15: VE-010 | C15: Consolidate IT MDA / IDA rooms (reduce cabling runs) | D15: 27 | E15: All Buildings | F15: 12000000 | G15: 10300000 | H15: =IF(OR(F15=0,G15=0),0,F15-G15) -> 1700000 | I15: =IF(F15=0,0,H15/F15) -> 0.14166667 | J15: +0 days | K15: Low risk | L15: Accepted
A16: 11 | B16: VE-011 | C16: Eliminate raised access floor; overhead power & cooling distribution | D16: 3 | E16: All Buildings | F16: 18000000 | G16: 14500000 | H16: =IF(OR(F16=0,G16=0),0,F16-G16) -> 3500000 | I16: =IF(F16=0,0,H16/F16) -> 0.19444444 | J16: Saves 1 week | K16: Low — overhead distribution proven in DC | L16: Accepted
A17: 12 | B17: VE-012 | C17: Aluminum feeders & busway in lieu of copper | D17: 26 | E17: All Buildings | F17: 38000000 | G17: 31000000 | H17: =IF(OR(F17=0,G17=0),0,F17-G17) -> 7000000 | I17: =IF(F17=0,0,H17/F17) -> 0.18421053 | J17: None | K17: Med — Al terminations/derating per NEC | L17: Accepted
... A25: 20 | B25: VE-020 | C25: Reduce on-site generator fuel storage (24h → 12h) | D25: 23 | E25: Shared | F25: 8500000 | G25: 6000000 | H25: =IF(OR(F25=0,G25=0),0,F25-G25) -> 2500000 | I25: =IF(F25=0,0,H25/F25) -> 0.29411765 | J25: None | K25: High — resiliency: shorter on-site fuel autonomy (24h → 12h) | L25: Pending
C27: TOTALS | F27: =SUM(F6:F25) -> 411073864 | G27: =SUM(G6:G25) -> 341740000 | H27: =SUM(H6:H25) -> 68805864 | I27: =IF(F27=0,0,H27/F27) -> 0.16738078
A29: VE STATUS SUMMARY
A30: Accepted | B30: Count: | C30: =COUNTIF(L6:L25,"Accepted") -> 15 | D30: Savings: | E30: =SUMIF(L6:L25,"Accepted",H6:H25) -> 35305864
A31: Pending / Review | B31: Count: | C31: =COUNTIF(L6:L25,"Pending")+COUNTIF(L6:L25,"Under Review") -> 5 | D31: Savings: | E31: =SUMIF(L6:L25,"Pending",H6:H25)+SUMIF(L6:L25,"Under Review",H6:H25) -> 33500000
A32: Rejected | B32: Count: | C32: =COUNTIF(L6:L25,"Rejected") -> 0 | D32: Savings: | E32: =SUMIF(L6:L25,"Rejected",H6:H25) -> 0
A34: VE-ADJUSTED ESTIMATE (active VE scenario — see selector →)
A35: Base Estimate (live scenario): | E35: ='Campus Rollup'!H16 -> 1.0883418e+09
A36: Less: VE Savings (active scenario): | E36: =$L$43 -> 35305864
A37: VE-Adjusted Total: | E37: =$E$35-$L$43 -> 1.053036e+09
A38: VE-Adjusted Cost / MW: | E38: =IF('Campus Rollup'!D16=0,"—",$E$37/'Campus Rollup'!D16) -> 11700400
A40: VE SCENARIO MODEL — ADOPTION SCENARIOS | J40: ACTIVE VE SCENARIO
A41: Toggle which VE items each scenario accepts: 1 (✓) = accept, 0 (–) = reject. Aggressive takes every cost lever that PRESERVES resiliency; Accept All additionally adopts the four High-risk resiliency reductions (UPS autonomy, cooling & power redundancy, fuel storage). | J41: Selected scenario: | L41: Balanced
B42: ID | C42: Description | D42: Risk | E42: As-Designed | F42: Conservative | G42: Balanced | H42: Aggressive | I42: Accept All | J42: Items accepted: | L42: =IF(L41="Custom (Status)",$C$30,INDEX($E$64:$I$64,MATCH($L$41,$E$42:$I$42,0))) -> 15
B43: =B6 -> VE-001 | C43: =C6 -> Tilt-up panels in lieu of CMU exterior wall | D43: =IF(ISNUMBER(SEARCH("High",K6)),"High",IF(ISNUMBER(SEARCH("Med",K6)),"Med","Low")) -> Low | E43: 0 | F43: 1 | G43: 1 | H43: 1 | I43: 1 | J43: VE savings ($): | L43: =IF(L41="Custom (Status)",$E$30,INDEX($E$65:$I$65,MATCH($L$41,$E$42:$I$42,0))) -> 35305864
B44: =B7 -> VE-002 | C44: =C7 -> Reduce slab thickness in admin building | D44: =IF(ISNUMBER(SEARCH("High",K7)),"High",IF(ISNUMBER(SEARCH("Med",K7)),"Med","Low")) -> Low | E44: 0 | F44: 1 | G44: 1 | H44: 1 | I44: 1 | J44: VE-adjusted total: | L44: =$E$35-$L$43 -> 1.053036e+09
B45: =B8 -> VE-003 | C45: =C8 -> Single-source steel package across campus | D45: =IF(ISNUMBER(SEARCH("High",K8)),"High",IF(ISNUMBER(SEARCH("Med",K8)),"Med","Low")) -> Med | E45: 0 | F45: 0 | G45: 1 | H45: 1 | I45: 1 | J45: VE-adjusted $/MW: | L45: =$L$44/'Campus Rollup'!$D$16 -> 11700400
B46: =B9 -> VE-004 | C46: =C9 -> Defer landscaping to post-occupancy | D46: =IF(ISNUMBER(SEARCH("High",K9)),"High",IF(ISNUMBER(SEARCH("Med",K9)),"Med","Low")) -> Low | E46: 0 | F46: 1 | G46: 1 | H46: 1 | I46: 1 | J46: Reduction vs base: | L46: =$L$43/$E$35 -> 0.032440051
B47: =B10 -> VE-005 | C47: =C10 -> Standardize door hardware across all buildings | D47: =IF(ISNUMBER(SEARCH("High",K10)),"High",IF(ISNUMBER(SEARCH("Med",K10)),"Med","Low")) -> Low | E47: 0 | F47: 1 | G47: 1 | H47: 1 | I47: 1 | J47: Med-risk items incl.: | L47: =IF(L41="Custom (Status)",SUMPRODUCT(($D$43:$D$62="Med")*($L$6:$L$25="Accepted")),INDEX($E$69:$I$69,MATCH($L$41,$E$42:$I$42,0))) -> 4
B48: =B11 -> VE-006 | C48: =C11 -> Overhead busway in lieu of conduit + cable whips (data halls) | D48: =IF(ISNUMBER(SEARCH("High",K11)),"High",IF(ISNUMBER(SEARCH("Med",K11)),"Med","Low")) -> Low | E48: 0 | F48: 1 | G48: 1 | H48: 1 | I48: 1 | J48: Resiliency cuts incl.: | L48: =IF(L41="Custom (Status)",SUMPRODUCT(($D$43:$D$62="High")*($L$6:$L$25="Accepted")),INDEX($E$70:$I$70,MATCH($L$41,$E$42:$I$42,0))) -> 0
B49: =B12 -> VE-007 | C49: =C12 -> Air-cooled chillers; eliminate cooling towers + CW treatment | D49: =IF(ISNUMBER(SEARCH("High",K12)),"High",IF(ISNUMBER(SEARCH("Med",K12)),"Med","Low")) -> Med | E49: 0 | F49: 0 | G49: 0 | H49: 1 | I49: 1
B50: =B13 -> VE-008 | C50: =C13 -> Prefabricated electrical skids (modular PDU / RPP) | D50: =IF(ISNUMBER(SEARCH("High",K13)),"High",IF(ISNUMBER(SEARCH("Med",K13)),"Med","Low")) -> Low | E50: 0 | F50: 1 | G50: 1 | H50: 1 | I50: 1
B51: =B14 -> VE-009 | C51: =C14 -> VRF for office / admin in lieu of chilled-water AHUs | D51: =IF(ISNUMBER(SEARCH("High",K14)),"High",IF(ISNUMBER(SEARCH("Med",K14)),"Med","Low")) -> Low | E51: 0 | F51: 1 | G51: 1 | H51: 1 | I51: 1
B52: =B15 -> VE-010 | C52: =C15 -> Consolidate IT MDA / IDA rooms (reduce cabling runs) | D52: =IF(ISNUMBER(SEARCH("High",K15)),"High",IF(ISNUMBER(SEARCH("Med",K15)),"Med","Low")) -> Low | E52: 0 | F52: 1 | G52: 1 | H52: 1 | I52: 1
B53: =B16 -> VE-011 | C53: =C16 -> Eliminate raised access floor; overhead power & cooling distribution | D53: =IF(ISNUMBER(SEARCH("High",K16)),"High",IF(ISNUMBER(SEARCH("Med",K16)),"Med","Low")) -> Low | E53: 0 | F53: 1 | G53: 1 | H53: 1 | I53: 1
B54: =B17 -> VE-012 | C54: =C17 -> Aluminum feeders & busway in lieu of copper | D54: =IF(ISNUMBER(SEARCH("High",K17)),"High",IF(ISNUMBER(SEARCH("Med",K17)),"Med","Low")) -> Med | E54: 0 | F54: 0 | G54: 1 | H54: 1 | I54: 1
B55: =B18 -> VE-013 | C55: =C18 -> Medium-voltage reticulation to data halls (reduce LV copper/gear) | D55: =IF(ISNUMBER(SEARCH("High",K18)),"High",IF(ISNUMBER(SEARCH("Med",K18)),"Med","Low")) -> Med | E55: 0 | F55: 0 | G55: 1 | H55: 1 | I55: 1
B56: =B19 -> VE-014 | C56: =C19 -> Reduce UPS battery autonomy (10 → 5 min) | D56: =IF(ISNUMBER(SEARCH("High",K19)),"High",IF(ISNUMBER(SEARCH("Med",K19)),"Med","Low")) -> High | E56: 0 | F56: 0 | G56: 0 | H56: 0 | I56: 1
B57: =B20 -> VE-015 | C57: =C20 -> Reduce chilled-water plant redundancy (N+2 → N+1) | D57: =IF(ISNUMBER(SEARCH("High",K20)),"High",IF(ISNUMBER(SEARCH("Med",K20)),"Med","Low")) -> High | E57: 0 | F57: 0 | G57: 0 | H57: 0 | I57: 1
B58: =B21 -> VE-016 | C58: =C21 -> Raise supply-air / CHW setpoints (ASHRAE A1→A3); downsize cooling | D58: =IF(ISNUMBER(SEARCH("High",K21)),"High",IF(ISNUMBER(SEARCH("Med",K21)),"Med","Low")) -> Low | E58: 0 | F58: 1 | G58: 1 | H58: 1 | I58: 1
B59: =B22 -> VE-017 | C59: =C22 -> Right-size standby generation (N+1 vs 2N) | D59: =IF(ISNUMBER(SEARCH("High",K22)),"High",IF(ISNUMBER(SEARCH("Med",K22)),"Med","Low")) -> High | E59: 0 | F59: 0 | G59: 0 | H59: 0 | I59: 1
B60: =B23 -> VE-018 | C60: =C23 -> Single-vendor standardized switchgear package | D60: =IF(ISNUMBER(SEARCH("High",K23)),"High",IF(ISNUMBER(SEARCH("Med",K23)),"Med","Low")) -> Med | E60: 0 | F60: 0 | G60: 1 | H60: 1 | I60: 1
... B62: =B25 -> VE-020 | C62: =C25 -> Reduce on-site generator fuel storage (24h → 12h) | D62: =IF(ISNUMBER(SEARCH("High",K25)),"High",IF(ISNUMBER(SEARCH("Med",K25)),"Med","Low")) -> High | E62: 0 | F62: 0 | G62: 0 | H62: 0 | I62: 1
A63: SCENARIO ROLL-UP
A64: Items accepted (count) | E64: =SUM(E43:E62) -> 0 | F64: =SUM(F43:F62) -> 11 | G64: =SUM(G43:G62) -> 15 | H64: =SUM(H43:H62) -> 16 | I64: =SUM(I43:I62) -> 20
A65: Total VE savings ($) | E65: =SUMPRODUCT(E43:E62,$H$6:$H$25) -> 0 | F65: =SUMPRODUCT(F43:F62,$H$6:$H$25) -> 19655864 | G65: =SUMPRODUCT(G43:G62,$H$6:$H$25) -> 35305864 | H65: =SUMPRODUCT(H43:H62,$H$6:$H$25) -> 41805864 | I65: =SUMPRODUCT(I43:I62,$H$6:$H$25) -> 68805864
A66: VE-adjusted total ($) | E66: =$E$35-E65 -> 1.0883418e+09 | F66: =$E$35-F65 -> 1.068686e+09 | G66: =$E$35-G65 -> 1.053036e+09 | H66: =$E$35-H65 -> 1.046536e+09 | I66: =$E$35-I65 -> 1.019536e+09
A67: VE-adjusted $ / MW | E67: =E66/'Campus Rollup'!$D$16 -> 12092687 | F67: =F66/'Campus Rollup'!$D$16 -> 11874288 | G67: =G66/'Campus Rollup'!$D$16 -> 11700400 | H67: =H66/'Campus Rollup'!$D$16 -> 11628177 | I67: =I66/'Campus Rollup'!$D$16 -> 11328177
A68: Reduction vs base (%) | E68: =E65/$E$35 -> 0 | F68: =F65/$E$35 -> 0.018060377 | G68: =G65/$E$35 -> 0.032440051 | H68: =H65/$E$35 -> 0.038412439 | I68: =I65/$E$35 -> 0.063220821
A69: Med-risk items included | E69: {=SUMPRODUCT((($D$43:$D$62)="Med")*E43:E62)} -> 0 | F69: {=SUMPRODUCT((($D$43:$D$62)="Med")*F43:F62)} -> 0 | G69: {=SUMPRODUCT((($D$43:$D$62)="Med")*G43:G62)} -> 4 | H69: {=SUMPRODUCT((($D$43:$D$62)="Med")*H43:H62)} -> 5 | I69: =SUMPRODUCT((($D$43:$D$62)="Med")*I43:I62) -> 5
A70: Resiliency cuts included (High) | E70: =SUMPRODUCT((($D$43:$D$62)="High")*E43:E62) -> 0 | F70: =SUMPRODUCT((($D$43:$D$62)="High")*F43:F62) -> 0 | G70: =SUMPRODUCT((($D$43:$D$62)="High")*G43:G62) -> 0 | H70: =SUMPRODUCT((($D$43:$D$62)="High")*H43:H62) -> 0 | I70: =SUMPRODUCT((($D$43:$D$62)="High")*I43:I62) -> 4

Sheet Basis of Estimate
A1: BASIS OF ESTIMATE (BOE)
A3: Project: | B3: ='Construction Budget'!C3 -> Data Center Template, Northern Virginia | D3: Estimate Class: | E3: ='Campus Rollup'!H3 -> Class 3 (DD)
A4: Estimate Date: | B4: ='Construction Budget'!F3 -> 46143 | D4: Accuracy Range: | E4: ='Campus Rollup'!H4 -> −20% / +30%
A5: Prepared By: | B5: =IF($B$6="","Senior Cost Estimator","Senior Cost Estimator, "&$B$6) -> Senior Cost Estimator | D5: Reviewed By: | E5: =IF($B$6="","Estimating Lead","Estimating Lead, "&$B$6) -> Estimating Lead
A6: Cost Manager:
A7: 1. DOCUMENTS REVIEWED
A8: Drawing Set: | B8: Architectural / Structural / Civil drawings dated April 18, 2026 (100% DD set)
A9: Specifications: | B9: Project Manual, Division 01–33 specifications (Rev. 3, April 2026)
A10: Geotechnical Report: | B10: Terracon Consultants, Inc., dated January 15, 2026
A11: Site Survey: | B11: Bowman Consulting Group, dated December 8, 2025
A12: RFP / Program Brief: | B12: Owner's program requirements v2.1, dated November 20, 2025
A13: BIM Models: | B13: Architectural and Structural Revit models, LOD 350
A15: 2. KEY ASSUMPTIONS
A16: A.1 | B16: Pricing reflects market conditions as of the estimate date. Escalation to the construction midpoint is applied at 3.5%/yr in the Construction Budget (cell H7); further market shifts tracked separately.
A17: A.2 | B17: Construction sequencing assumes no major site access constraints or owner-imposed work hour restrictions.
A18: A.3 | B18: Subcontractor market is assumed to be reasonably competitive (≥3 qualified bidders per major package).
A19: A.4 | B19: Prevailing wage rates apply per project location; non-union labor where market permits.
A20: A.5 | B20: Soils assumed suitable for standard spread footings per geotech report; no extensive soil remediation included.
A21: A.6 | B21: Utilities (power, water, fiber) are available at the property line; service entrance work included.
A22: A.7 | B22: Permits and AHJ approvals proceed on a normal review cycle; no expedited fees included.
A23: A.8 | B23: Owner-furnished IT equipment (servers, network gear) is excluded; OFCI integration coordination included.
A24: A.9 | B24: Single mobilization per building; phased delivery sequencing per program schedule.
A25: A.10 | B25: Labor productivity reflects regional norms; no premium time included in base estimate.
A26: A.11 | B26: ="Design basis: "&TEXT('Campus Rollup'!D16,"0")&" MW total IT load across "&TEXT('Campus Rollup'!C16/1000,"#,##0")&"K SF gross; resiliency "&'Scenario & Presets'!B17&", redundancy "&'Scenario & Presets'!B18&", rack density "&'Scenario & Presets'!B19&"." -> Design basis: 90 MW total IT load across 800K SF gross; resiliency Tier III, redundancy N+1, rack density High (15–30 kW).
A27: A.12 | B27: ="Cooling design basis: "&'Scenario & Presets'!B16&"; Division 23 air / chilled-water / liquid scope scales from the active cooling preset on the Scenario & Presets tab." -> Cooling design basis: Liquid-Cooled (DLC); Division 23 air / chilled-water / liquid scope scales from the active cooling preset on the Scenario & Presets tab.
A28: A.13 | B28: ="Location basis: pricing indexed to "&'Location Factors'!B3&" at a location factor of "&TEXT('Location Factors'!B6,"0.00")&" relative to the Northern Virginia baseline; set on the Location Factors tab and applied in the Construction Budget." -> Location basis: pricing indexed to Northern Virginia at a location factor of 1.00 relative to the Northern Virginia baseline; set on the Location Factors tab and applied in the Construction Budget.
A30: 3. INCLUSIONS
A31: I.1 | B31: All civil work within property line: site clearing, mass excavation, structural fill, paving, fencing, security perimeter.
A32: I.2 | B32: Building envelope: foundations, structural steel, slabs, exterior wall systems, roofing, openings.
A33: I.3 | B33: MEP systems sized for stated IT load and Tier rating: utility service, generators, UPS, distribution, cooling, controls.
A34: I.4 | B34: Fire / life safety: clean agent suppression in data halls, pre-action sprinklers, VESDA detection, fire alarm, mass notification.
A35: I.5 | B35: Interior finishes: raised access flooring, gypsum partitions, painting, sealed concrete in support areas.
A36: I.6 | B36: Commissioning Levels 1–5 per ASHRAE / Uptime guideline.
A37: I.7 | B37: General conditions, contractor overhead and profit, and design contingency at the rate shown in Construction Budget cell C7.
A38: I.8 | B38: Permits, fees, builder's risk insurance, performance and payment bonds.
A39: I.9 | B39: Electronic security systems: access control, CCTV / video surveillance, intrusion detection, and visitor management across site perimeter, building, and data-hall white space.
A40: I.10 | B40: Structured cabling backbone (OS2 fiber + Cat6A trunks to MDA / IDA) and integrated controls — BMS, DCIM, and electrical power monitoring (EPMS).
A42: 3.1 GENERAL CONTRACTOR BASE SCOPE — TRADES (CSI DIVISIONS)
A43: CSI | B43: Trade / CSI Division — GC Base Scope | E43: Status | F43: Base Cost ($)
A44: 1 | B44: General Conditions & Project Requirements | E44: Included | F44: ='Construction Budget'!H58 -> 42983031
A45: Cx | B45: Commissioning & Testing (Levels 1–5) | E45: Included | F45: ='Construction Budget'!H75 -> 47367292
A46: 3 | B46: Concrete | E46: Included | F46: ='Construction Budget'!H112 -> 33466040
A47: 4 | B47: Masonry | E47: Included | F47: ='Construction Budget'!H126 -> 5656068
A48: 5 | B48: Metals / Structural Steel | E48: Included | F48: ='Construction Budget'!H164 -> 40836400
A49: 6 | B49: Wood, Plastics & Composites | E49: Included | F49: ='Construction Budget'!H174 -> 1233678.6
A50: 7 | B50: Thermal & Moisture Protection | E50: Included | F50: ='Construction Budget'!H212 -> 38165651
A51: 8 | B51: Openings (Doors, Frames & Glazing) | E51: Included | F51: ='Construction Budget'!H239 -> 13742210
A52: 9 | B52: Finishes | E52: Included | F52: ='Construction Budget'!H272 -> 33189552
A53: 10 | B53: Specialties | E53: Included | F53: ='Construction Budget'!H292 -> 4010233.4
A54: 11 | B54: Equipment | E54: Included | F54: ='Construction Budget'!H305 -> 1525590
A55: 12 | B55: Furnishings | E55: Included | F55: ='Construction Budget'!H315 -> 1217056.5
A56: 14 | B56: Conveying Equipment (Elevators) | E56: Included | F56: ='Construction Budget'!H324 -> 4104292.5
A57: 21 | B57: Fire Suppression | E57: Included | F57: ='Construction Budget'!H359 -> 22577594
A58: 22 | B58: Plumbing | E58: Included | F58: ='Construction Budget'!H387 -> 22312499
A59: 23 | B59: HVAC / Cooling Systems | E59: Included | F59: ='Construction Budget'!H495 -> 2.2648425e+08
A60: 25 | B60: Integrated Automation (BMS / DCIM / EPMS) | E60: Included | F60: ='Construction Budget'!H517 -> 13470732
A61: 26 | B61: Electrical / Critical Power | E61: Included | F61: ='Construction Budget'!H665 -> 2.4814778e+08
A62: 27 | B62: Communications / IT Infrastructure | E62: Included | F62: ='Construction Budget'!H714 -> 60417388
A63: 28 | B63: Electronic Safety & Security | E63: Included | F63: ='Construction Budget'!H742 -> 15750753
A64: 31 | B64: Earthwork | E64: Included | F64: ='Construction Budget'!H772 -> 25614732
A65: 32 | B65: Exterior Improvements | E65: Included | F65: ='Construction Budget'!H792 -> 9371809.5
A66: 33 | B66: Utilities | E66: Included | F66: ='Construction Budget'!H835 -> 63598602
B67: GC BASE CONSTRUCTION COST (Div 01–33, incl. Commissioning) | F67: =SUM(F44:F66) -> 9.7524324e+08
A68: All trades carried by the General Contractor are linked live to division subtotals on the Construction Budget. CSI divisions with no discrete scope on this greenfield project — Div 02 Existing Conditions and Div 13 Special Construction (containment carried within Specialties) — are captured within adjacent divisions. Soft costs, owner's contingency and OFCI IT equipment are excluded (see Exclusions).
A70: 4. EXCLUSIONS
A71: E.1 | B71: Land acquisition, due diligence, environmental remediation of pre-existing contamination.
A72: E.2 | B72: Off-site utility extensions beyond the property line (utility company scope).
A73: E.3 | B73: IT equipment: servers, switches, racks (when OFCI), structured cabling end-of-row terminations beyond Cat6A trunks.
A74: E.4 | B74: Owner's project management staff, owner's representative, legal fees.
A75: E.5 | B75: Move-in / commissioning of owner-furnished equipment.
A76: E.6 | B76: Operational costs, spare parts inventory, post-occupancy maintenance.
A77: E.7 | B77: Sales tax (assumed exempt or capitalized separately per owner accounting).
A78: E.8 | B78: Market escalation beyond the 3.5%/yr already applied to the construction midpoint (additional inflation or supply-chain shocks carried at owner level).
A79: E.9 | B79: Owner's contingency (carried at owner level, not in this estimate).
A80: E.10 | B80: Force majeure events; abnormal weather; pandemic-related labor or supply chain shocks.
A81: E.11 | B81: Construction financing and interest during construction (IDC); carried at owner level on the Total Development Cost tab.
A82: E.12 | B82: Utility capacity / demand charges, standby and interconnection fees, and utility-imposed substation contributions beyond the service entrance.
A84: 5. RISKS & SENSITIVITIES
A85: # | B85: Risk Description | C85: Likelihood | D85: Impact ($) | E85: Mitigation | F85: Owner
A86: R-01 | B86: Switchgear lead times exceed schedule float | C86: High | D86: Schedule slip + premium | E86: Early procurement; alternate manufacturer pre-qualification | F86: PM/Procurement
A87: R-02 | B87: Generator supply constraint due to global demand | C87: High | D87: $2M–$5M premium | E87: Lock pricing 12+ months ahead; reserve mfg slots | F87: Procurement
A88: R-03 | B88: Soil conditions worse than geotech indicates | C88: Med | D88: $500K–$2M | E88: Allowance carried; over-excavation contingency | F88: Civil/Estimating
A89: R-04 | B89: Concrete material price escalation | C89: Med | D89: ±5–10% on Div 03 | E89: Lock pricing at GMP; monitor PPI | F89: Estimating
A90: R-05 | B90: Labor availability in selected market | C90: Med | D90: Schedule + premium time | E90: Pre-qualify multiple GCs; out-of-area labor plan | F90: PM
A91: R-06 | B91: Permit / AHJ delays | C91: Low–Med | D91: Schedule slip | E91: Early entitlement engagement; expediter on retainer | F91: PM
A92: R-07 | B92: Design changes during DD/CD | C92: Med | D92: ±3–7% per change cycle | E92: Tight change-control process; gated milestone reviews | F92: Design Mgr
A93: R-08 | B93: Tariffs / trade policy on imported equipment | C93: Med | D93: ±2–5% on MEP | E93: Domestic-source alternate priced; sensitivity tracked | F93: Procurement
A94: R-09 | B94: Utility power interconnection capacity / energization timing | C94: High | D94: Schedule-critical; multi-month slip | E94: Early utility engagement; reserve capacity; on-site generation bridging plan | F94: Owner / PM
A95: R-10 | B95: Liquid-cooling (DLC) supply chain & technology maturity | C95: Med | D95: ±3–6% on Div 23; schedule | E95: Pre-qualify CDU / coolant vendors; retain air+liquid hybrid flexibility | F95: MEP / Procurement
A97: 6. SIGN-OFF
A98: Role | C98: Name | D98: Signature | E98: Date
A99: Project Director
A100: Client Acceptance
A102: SCENARIO CONTROLS & VALUE ENGINEERING
A103: Pricing Tier (Low/Mid/High) and Cooling Technology are driven from the 'Scenario & Presets' tab; defaults (Mid / Hybrid As-Designed) reproduce this estimate.
A104: Cooling presets scale Division 23 air / chilled-water / liquid scope; Tier, Redundancy and Rack Density are documented configuration with an expected $/MW band by archetype.
A105: Value-engineering options are logged on the 'Value Engineering' tab; items marked Accepted flow into the VE-Adjusted Total. VE and presets are illustrative pending MEP design confirmation.
A106: Cooling topology (O-1, resolved): committed to an air + liquid hybrid via 'Scenario & Presets' → Cooling = Liquid-Cooled (DLC). In-Row air cooling now scales by the air-side factor (40%) and direct-liquid infrastructure + CDUs are engaged, replacing the prior stacked full-air + full-liquid scope. Division 23 −$33M; project total $1,122.7M → $1,088.3M. Revert by setting Cooling = Chilled Water (Air-Cooled).
A107: MEP cost mix (O-2, resolved): Division 26 (Electrical, $248M) reviewed line-by-line — coherent critical-power scope (UPS, generators, PDU, busway, switchgear), no double-counts. The elevated MEP weight was driven by In-Row air cooling, not electrical; after the hybrid rationalization Electrical + HVAC ≈ 44% of cost, within the 45–55% norm.

Sheet Benchmark Library
A1: 0.0175
A3: Anchor each new estimate against this library. Filter by Tier, region, and vintage. Apply location and time-value adjustments before comparison.
A4: Filter by Tier: | B4: All | C4: Filtered Median $/MW: | D4: {=IFERROR(IF($B$4="All",J20,_xlfn.AGGREGATE(17,6,J6:J15/(E6:E15=$B$4),5)),"—")} -> 1430000 | E4: Filtered Count: | F4: =IF($B$4="All",10,COUNTIF(E6:E15,$B$4)) -> 10
A5: # | B5: Project | C5: Region | D5: Vintage | E5: Tier | F5: Buildings | G5: GBA (SF) | H5: IT Load (MW) | I5: CSA $/SF | J5: CSA $/MW | K5: Total $/SF | L5: Total $/MW | M5: Total $/W | N5: Notes
A6: 1 | B6: Hyperscale Campus — NoVA Phase 2 | C6: Northern Virginia | D6: 2023 | E6: Tier III | F6: 4 | G6: 1200000 | H6: 96 | I6: 220 | J6: 1450000 | K6: 880 | L6: 11500000 | M6: 11.5 | N6: Greenfield, water-cooled chillers
A7: 2 | B7: Edge Campus — Hillsboro | C7: Hillsboro, OR | D7: 2024 | E7: Tier III | F7: 2 | G7: 480000 | H7: 36 | I7: 240 | J7: 1620000 | K7: 920 | L7: 12200000 | M7: 12.2 | N7: Indirect evap cooling, lithium UPS
A8: 3 | B8: Build-to-Suit — Phoenix | C8: Phoenix, AZ | D8: 2022 | E8: Tier III+ | F8: 3 | G8: 850000 | H8: 72 | I8: 205 | J8: 1380000 | K8: 850 | L8: 11000000 | M8: 11 | N8: Adiabatic; high ambient design
A9: 4 | B9: Hyperscale — Quincy | C9: Quincy, WA | D9: 2023 | E9: Tier II | F9: 6 | G9: 1800000 | H9: 144 | I9: 195 | J9: 1310000 | K9: 780 | L9: 10200000 | M9: 10.2 | N9: Direct outside air economization
A10: 5 | B10: Colocation Expansion — Ashburn | C10: Ashburn, VA | D10: 2024 | E10: Tier IV | F10: 1 | G10: 280000 | H10: 24 | I10: 280 | J10: 1900000 | K10: 1080 | L10: 14500000 | M10: 14.5 | N10: Brownfield, 2N redundant
A11: 6 | B11: Hyperscale Campus — Dallas | C11: Dallas-Fort Worth, TX | D11: 2024 | E11: Tier III | F11: 5 | G11: 1450000 | H11: 120 | I11: 215 | J11: 1410000 | K11: 870 | L11: 11300000 | M11: 11.3 | N11: Liquid-cooling-ready
A12: 7 | B12: Build-to-Suit — Council Bluffs | C12: Council Bluffs, IA | D12: 2022 | E12: Tier III | F12: 2 | G12: 620000 | H12: 48 | I12: 185 | J12: 1240000 | K12: 760 | L12: 9800000 | M12: 9.8 | N12: Air-cooled chillers, low-cost market
A13: 8 | B13: Hyperscale — Santa Clara | C13: Santa Clara, CA | D13: 2023 | E13: Tier III | F13: 1 | G13: 220000 | H13: 18 | I13: 340 | J13: 2280000 | K13: 1310 | L13: 17800000 | M13: 17.8 | N13: Seismic + high cost market
A14: 9 | B14: Edge Campus — Atlanta | C14: Atlanta, GA | D14: 2023 | E14: Tier III | F14: 3 | G14: 720000 | H14: 60 | I14: 205 | J14: 1380000 | K14: 840 | L14: 10900000 | M14: 10.9 | N14: Standard scope
A15: 10 | B15: Hyperscale — Reno | C15: Reno-Sparks, NV | D15: 2024 | E15: Tier III+ | F15: 4 | G15: 1100000 | H15: 96 | I15: 225 | J15: 1510000 | K15: 900 | L15: 11700000 | M15: 11.7 | N15: DLC-ready, GPU buildout
A17: BENCHMARK STATISTICS (across all projects above)
A18: Statistic | I18: CSA $/SF | J18: CSA $/MW | K18: Total $/SF | L18: Total $/MW | M18: Total $/W
A19: Min | I19: =MIN(I6:I15) -> 185 | J19: =MIN(J6:J15) -> 1240000 | K19: =MIN(K6:K15) -> 760 | L19: =MIN(L6:L15) -> 9800000 | M19: =MIN(M6:M15) -> 9.8
A20: Median | I20: =MEDIAN(I6:I15) -> 217.5 | J20: =MEDIAN(J6:J15) -> 1430000 | K20: =MEDIAN(K6:K15) -> 875 | L20: =MEDIAN(L6:L15) -> 11400000 | M20: =MEDIAN(M6:M15) -> 11.4
A21: Mean | I21: =AVERAGE(I6:I15) -> 231 | J21: =AVERAGE(J6:J15) -> 1548000 | K21: =AVERAGE(K6:K15) -> 919 | L21: =AVERAGE(L6:L15) -> 12090000 | M21: =AVERAGE(M6:M15) -> 12.09
A22: Max | I22: =MAX(I6:I15) -> 340 | J22: =MAX(J6:J15) -> 2280000 | K22: =MAX(K6:K15) -> 1310 | L22: =MAX(L6:L15) -> 17800000 | M22: =MAX(M6:M15) -> 17.8
A24: CURRENT ESTIMATE vs BENCHMARK MEDIAN
A25: Current Estimate | I25: =IF('Campus Rollup'!C16=0,0,'CSA Summary'!I21/'Campus Rollup'!C16) -> 0 | J25: =IF('Campus Rollup'!D16=0,0,'CSA Summary'!I21/'Campus Rollup'!D16) -> 0 | K25: ='Campus Rollup'!I16 -> 1360.4273 | L25: ='Campus Rollup'!J16 -> 12092687 | M25: ='Campus Rollup'!H21 -> 12.092687
A26: Benchmark Median | I26: =I20 -> 217.5 | J26: =J20 -> 1430000 | K26: =K20 -> 875 | L26: =L20 -> 11400000 | M26: =M20 -> 11.4
A27: Δ vs Median | I27: =IFERROR(I25-I26,"—") -> -217.5 | J27: =IFERROR(J25-J26,"—") -> -1430000 | K27: =IFERROR(K25-K26,"—") -> 485.42728 | L27: =IFERROR(L25-L26,"—") -> 692686.97 | M27: =IFERROR(M25-M26,"—") -> 0.69268697
A28: Δ % | I28: =IFERROR(I25/I26-1,"—") -> -1 | J28: =IFERROR(J25/J26-1,"—") -> -1 | K28: =IFERROR(K25/K26-1,"—") -> 0.55477404 | L28: =IFERROR(L25/L26-1,"—") -> 0.060762015 | M28: =IFERROR(M25/M26-1,"—") -> 0.060762015
A31: STAKEHOLDER BENCHMARKS — RETURNS, CAPITAL EFFICIENCY & CREDIT
A32: Typical institutional ranges for Tier III hyperscale / wholesale data centers; current figures link live from the model (TDC, Pro Forma, Capital Stack). Illustrative — calibrate Low/Median/High to deal-specific quotes.
B33: Metric | F33: Market Low | G33: Median | H33: High | I33: Current Project | K33: Position vs Market
B34: ◆ DEVELOPER — COST & DELIVERY
B35: All-in development cost ($/MW) | F35: 13000000 | G35: 16000000 | H35: 22000000 | I35: ='Total Development Cost'!C38 -> 16809709 | K35: =IF($I35="","",IF($I35>$H35,"▲ Above market",IF($I35<$F35,"▼ Below market","● In market range"))) -> ● In market range
B36: Construction (hard) cost ($/MW) | F36: 9800000 | G36: 11400000 | H36: 17800000 | I36: ='Campus Rollup'!J16 -> 12092687 | K36: =IF($I36="","",IF($I36>$H36,"▲ Above market",IF($I36<$F36,"▼ Below market","● In market range"))) -> ● In market range
B37: Hard cost (% of all-in TDC) | F37: 0.65 | G37: 0.72 | H37: 0.8 | I37: ='Total Development Cost'!C41 -> 0.71938706 | K37: =IF($I37="","",IF($I37>$H37,"▲ Above market",IF($I37<$F37,"▼ Below market","● In market range"))) -> ● In market range
B38: Design PUE | F38: 1.2 | G38: 1.4 | H38: 1.6 | I38: ='Construction Budget'!C8 -> 1.4 | K38: =IF($I38="","",IF($I38>$H38,"▲ Above market",IF($I38<$F38,"▼ Below market","● In market range"))) -> ● In market range
B39: Schedule to energization (months) | F39: 18 | G39: 24 | H39: 36 | I39: ='Total Development Cost'!C28 -> 30 | K39: =IF($I39="","",IF($I39>$H39,"▲ Above market",IF($I39<$F39,"▼ Below market","● In market range"))) -> ● In market range
B40: ◆ CFO — CAPITAL EFFICIENCY
B41: Soft + financing + contingency (% of TDC) | F41: 0.2 | G41: 0.28 | H41: 0.35 | I41: =1-'Total Development Cost'!C41 -> 0.28061294 | K41: =IF($I41="","",IF($I41>$H41,"▲ Above market",IF($I41<$F41,"▼ Below market","● In market range"))) -> ● In market range
B42: Owner's contingency (%) | F42: 0.05 | G42: 0.08 | H42: 0.12 | I42: ='Total Development Cost'!D34 -> 0.05 | K42: =IF($I42="","",IF($I42>$H42,"▲ Above market",IF($I42<$F42,"▼ Below market","● In market range"))) -> ● In market range
B43: Interest during construction (% of TDC) | F43: 0.03 | G43: 0.045 | H43: 0.07 | I43: ='Total Development Cost'!D48 -> 0.055494829 | K43: =IF($I43="","",IF($I43>$H43,"▲ Above market",IF($I43<$F43,"▼ Below market","● In market range"))) -> ● In market range
B44: All-in cost ($/SF) | F44: 1500 | G44: 1870 | H44: 2400 | I44: ='Total Development Cost'!C39 -> 1891.0922 | K44: =IF($I44="","",IF($I44>$H44,"▲ Above market",IF($I44<$F44,"▼ Below market","● In market range"))) -> ● In market range
B45: ◆ INVESTOR — RETURNS
B46: Stabilized yield-on-cost | F46: 0.08 | G46: 0.1 | H46: 0.13 | I46: ='Investment Pro Forma'!B38 -> 0.10901442 | K46: =IF($I46="","",IF($I46>$H46,"▲ Above market",IF($I46<$F46,"▼ Below market","● In market range"))) -> ● In market range
B47: Going-in yield (Yr-1 NOI ÷ TDC) | F47: 0.045 | G47: 0.055 | H47: 0.07 | I47: ='Investment Pro Forma'!B37 -> 0.050653909 | K47: =IF($I47="","",IF($I47>$H47,"▲ Above market",IF($I47<$F47,"▼ Below market","● In market range"))) -> ● In market range
B48: Exit / terminal cap rate | F48: 0.055 | G48: 0.065 | H48: 0.075 | I48: ='Investment Pro Forma'!B11 -> 0.065 | K48: =IF($I48="","",IF($I48>$H48,"▲ Above market",IF($I48<$F48,"▼ Below market","● In market range"))) -> ● In market range
B49: Lease rate ($/kW IT / month) | F49: 120 | G49: 150 | H49: 190 | I49: ='Investment Pro Forma'!B9 -> 165 | K49: =IF($I49="","",IF($I49>$H49,"▲ Above market",IF($I49<$F49,"▼ Below market","● In market range"))) -> ● In market range
B50: Unlevered IRR (8-yr hold) | F50: 0.09 | G50: 0.12 | H50: 0.16 | I50: ='Investment Pro Forma'!B33 -> 0.1744147 | K50: =IF($I50="","",IF($I50>$H50,"▲ Above market",IF($I50<$F50,"▼ Below market","● In market range"))) -> ▲ Above market
B51: Levered equity IRR | F51: 0.14 | G51: 0.18 | H51: 0.25 | I51: ='Capital Stack & Returns'!B46 -> 0.26651127 | K51: =IF($I51="","",IF($I51>$H51,"▲ Above market",IF($I51<$F51,"▼ Below market","● In market range"))) -> ▲ Above market
B52: Levered equity multiple (8-yr) | F52: 1.8 | G52: 2.2 | H52: 3 | I52: ='Capital Stack & Returns'!B47 -> 5.1974061 | K52: =IF($I52="","",IF($I52>$H52,"▲ Above market",IF($I52<$F52,"▼ Below market","● In market range"))) -> ▲ Above market
B53: Development margin (% of cost) | F53: 0.15 | G53: 0.25 | H53: 0.4 | I53: ='Investment Pro Forma'!B42 -> 0.67714491 | K53: =IF($I53="","",IF($I53>$H53,"▲ Above market",IF($I53<$F53,"▼ Below market","● In market range"))) -> ▲ Above market
B54: ◆ LENDER — CREDIT & FINANCEABILITY
B55: Loan-to-cost (LTC) | F55: 0.5 | G55: 0.6 | H55: 0.7 | I55: ='Capital Stack & Returns'!B29 -> 0.6 | K55: =IF($I55="","",IF($I55>$H55,"▲ Above market",IF($I55<$F55,"▼ Below market","● In market range"))) -> ● In market range
B56: Stabilized DSCR | F56: 1.25 | G56: 1.4 | H56: 1.75 | I56: ='Capital Stack & Returns'!B30 -> 2.37264 | K56: =IF($I56="","",IF($I56>$H56,"▲ Above market",IF($I56<$F56,"▼ Below market","● In market range"))) -> ▲ Above market
B57: Debt yield (stabilized) | F57: 0.085 | G57: 0.1 | H57: 0.12 | I57: ='Capital Stack & Returns'!B31 -> 0.1816907 | K57: =IF($I57="","",IF($I57>$H57,"▲ Above market",IF($I57<$F57,"▼ Below market","● In market range"))) -> ▲ Above market
B58: All-in permanent loan rate | F58: 0.055 | G58: 0.065 | H58: 0.08 | I58: ='Capital Stack & Returns'!B14 -> 0.065 | K58: =IF($I58="","",IF($I58>$H58,"▲ Above market",IF($I58<$F58,"▼ Below market","● In market range"))) -> ● In market range
B59: Sponsor equity (% of cost) | F59: 0.3 | G59: 0.4 | H59: 0.5 | I59: =1-'Capital Stack & Returns'!B29 -> 0.4 | K59: =IF($I59="","",IF($I59>$H59,"▲ Above market",IF($I59<$F59,"▼ Below market","● In market range"))) -> ● In market range
A61: STAKEHOLDER POSITIONING SUMMARY
B62: Stakeholder | F62: In Range | G62: Above Mkt | H62: Below Mkt | I62: Metrics | K62: Read
B63: Developer — Cost & Delivery | F63: =COUNTIF(K35:K39,"*In market*") -> 5 | G63: =COUNTIF(K35:K39,"*Above*") -> 0 | H63: =COUNTIF(K35:K39,"*Below*") -> 0 | I63: =COUNTA(K35:K39) -> 5 | K63: ="Cost position: "&IF(COUNTIF(K35:K39,"*Above*")=0,"at or below market","review "&COUNTIF(K35:K39,"*Above*")&" above-market item(s)") -> Cost position: at or below market
B64: CFO — Capital Efficiency | F64: =COUNTIF(K41:K44,"*In market*") -> 4 | G64: =COUNTIF(K41:K44,"*Above*") -> 0 | H64: =COUNTIF(K41:K44,"*Below*") -> 0 | I64: =COUNTA(K41:K44) -> 4 | K64: ="Capital efficiency: "&IF(COUNTIF(K41:K44,"*Above*")=0,"within norms","review "&COUNTIF(K41:K44,"*Above*")&" above-market item(s)") -> Capital efficiency: within norms
B65: Investor — Returns | F65: =COUNTIF(K46:K53,"*In market*") -> 4 | G65: =COUNTIF(K46:K53,"*Above*") -> 4 | H65: =COUNTIF(K46:K53,"*Below*") -> 0 | I65: =COUNTA(K46:K53) -> 8 | K65: ="Returns: "&IF(COUNTIF(K46:K53,"*Above*")>=4,"exceed market benchmarks",IF(COUNTIF(K46:K53,"*Below*")>=4,"below market — review","broadly in line with market")) -> Returns: exceed market benchmarks
B66: Lender — Credit & Financeability | F66: =COUNTIF(K55:K59,"*In market*") -> 3 | G66: =COUNTIF(K55:K59,"*Above*") -> 2 | H66: =COUNTIF(K55:K59,"*Below*") -> 0 | I66: =COUNTA(K55:K59) -> 5 | K66: ="Credit: "&IF(COUNTIF(K55:K59,"*Above*")>=2,"coverage stronger than market","in line with market") -> Credit: coverage stronger than market

Sheet Power & Space Capacity
A1: POWER & SPACE CAPACITY MODEL
A2: Ties cost to engineering: IT load → electrical / cooling / space sizing, the binding constraint, and stranded capacity. Yellow cells are inputs.
A4: 1 · DESIGN INPUTS & REFERENCES
A5: IT load (design) | B5: ='Campus Rollup'!$D$16 -> 90 | C5: MW — from Campus Rollup
A6: Gross building area (GBA) | B6: ='Campus Rollup'!$C$16 -> 800000 | C6: SF — from Campus Rollup
A7: PUE (design) | B7: 1.3 | C7: facility kW per IT kW
A8: Average utilisation | B8: 0.8 | C8: of IT capacity, annualised
A9: Rack power density | B9: 20 | C9: kW per rack
A10: Area per rack (incl. aisles) | B10: 30 | C10: SF per rack
A11: Redundancy (from preset) | B11: ='Scenario & Presets'!$B$18 -> N+1 | C11: N / N+1 / 2N / 2N+1
A12: Redundancy de-rate factor | B12: =INDEX($B$45:$B$48,MATCH('Scenario & Presets'!$B$18,$A$45:$A$48,0)) -> 1.2 | C12: usable = provisioned ÷ factor
A13: Facility load | B13: =B5*B7 -> 117 | C13: MW = IT × PUE
A15: 2 · CAPACITY BALANCE (provisioned → supportable IT)
A16: Subsystem | B16: Provisioned | C16: Unit | D16: Supportable IT (MW) | E16: Stranded (MW)
A17: UPS / critical power | B17: 108 | C17: MW | D17: =B17/$B$12 -> 90 | E17: =D17-$B$23 -> 0.25641026
A18: Standby generation | B18: 140 | C18: MW | D18: =B18/$B$12/$B$7 -> 89.74359 | E18: =D18-$B$23 -> 0
A19: Cooling plant | B19: 31000 | C19: tons | D19: =B19*3.517/1000/$B$12 -> 90.855833 | E19: =D19-$B$23 -> 1.1122436
A20: Utility / transformers | B20: 130 | C20: MW | D20: =B20/$B$7 -> 100 | E20: =D20-$B$23 -> 10.25641
A22: Design IT load (target): | B22: ='Campus Rollup'!$D$16 -> 90
A23: Usable IT (binding subsystem): | B23: =MIN(D17:D20) -> 89.74359
A24: Binding constraint: | B24: =INDEX(A17:A20,MATCH(MIN(D17:D20),D17:D20,0)) -> Standby generation
A25: Capacity adequacy: | B25: =IF(B23>=B22,"● Meets design IT load","▲ Short by "&TEXT(B22-B23,"0.0")&" MW — relieve binding subsystem") -> ▲ Short by 0.3 MW — relieve binding subsystem
A27: 3 · SPACE PROGRAM
A28: Rack count (capacity) | B28: =B5*1000/B9 -> 4500 | C28: racks = IT kW ÷ density
A29: White-space area | B29: =B28*B10 -> 135000 | C29: SF = racks × area/rack
A30: White space per MW | B30: =B29/B5 -> 1500 | C30: SF / MW
A31: White space as % of GBA | B31: =B29/B6 -> 0.16875 | C31: of gross building area
A32: Support / MEP / admin balance | B32: =B6-B29 -> 665000 | C32: SF (GBA − white space)
A34: 4 · UNIT COST METRICS (from the live estimate)
A35: Cost per MW (IT) | B35: ='Campus Rollup'!$H$16/B5 -> 12092687 | C35: per IT MW
A36: Cost per MW (facility) | B36: ='Campus Rollup'!$H$16/B13 -> 9302066.9 | C36: per facility MW
A37: Cost per rack | B37: ='Campus Rollup'!$H$16/B28 -> 241853.74 | C37: per rack position
A38: Cost per cooling ton | B38: ='Campus Rollup'!$H$16/B19 -> 35107.801 | C38: per installed ton
A39: Cost per SF | B39: ='Campus Rollup'!$H$16/B6 -> 1360.4273 | C39: per gross SF
A40: Cost per IT watt | B40: ='Campus Rollup'!$H$16/(B5*1000000) -> 12.092687 | C40: per IT watt
A43: (lookup — do not edit)
A44: Redundancy | B44: Factor
A45: N | B45: 1
A46: N+1 | B46: 1.2
A47: 2N | B47: 2
A48: 2N+1 | B48: 2.1
A50: 5 · STAKEHOLDER VIEW — CAPACITY TRANSLATED FOR CAPITAL PARTNERS
A51: Translates the engineering capacity above into the metric each capital partner underwrites. Links live to the estimate, TDC, and Pro Forma lease rate.
A52: ◆ DEVELOPER — DELIVERABLE CAPACITY
A53: Usable IT capacity (binding) | B53: =B23 -> 89.74359 | C53: ="limited by "&LOWER(B24) -> limited by standby generation
A54: Capacity adequacy vs design | B54: =B23/B22 -> 0.997151 | C54: usable ÷ design IT target
A55: Stranded provisioned capacity | B55: =MAX(D17:D20)-B23 -> 10.25641 | C55: MW provisioned beyond binding (relievable)
A56: ◆ CFO — CAPITAL EFFICIENCY
A57: All-in cost per usable MW | B57: ='Total Development Cost'!C35/B23 -> 16857736 | C57: TDC ÷ usable IT MW
A58: Construction cost per usable MW | B58: ='Campus Rollup'!H16/B23 -> 12127238 | C58: hard construction ÷ usable IT MW
A59: Capacity efficiency | B59: =B23/B22 -> 0.997151 | C59: usable ÷ design (capital utilisation)
A60: ◆ INVESTOR — REVENUE CAPACITY
A61: Leasable IT capacity | B61: =B23 -> 89.74359 | C61: revenue-generating IT (usable)
A62: Gross revenue capacity @ lease rate | B62: =B23*1000*'Investment Pro Forma'!B9*12 -> 1.7769231e+08 | C62: ="$/yr at full lease ("&TEXT('Investment Pro Forma'!B9,"$0")&"/kW/mo)" -> $/yr at full lease ($165/kW/mo)
A63: Revenue at risk — binding shortfall | B63: =(B22-B23)*1000*'Investment Pro Forma'!B9*12 -> 507692.31 | C63: $/yr forgone vs design IT
A64: ◆ LENDER — CAPACITY SECURITY
A65: Redundancy level | B65: =B11 -> N+1 | C65: N / N+1 / 2N resiliency tier
A66: Capacity adequacy | B66: =IF(B23>=B22,"● Meets design","▲ Short "&TEXT(B22-B23,"0.0")&" MW") -> ▲ Short 0.3 MW | C66: provisioned vs design IT load
A67: Design utilisation (load factor) | B67: =B8 -> 0.8 | C67: of IT capacity, annualised

Sheet Bid Cover Sheet
B2: SEALED BID
B3: DO NOT OPEN UNTIL PUBLIC BID OPENING
B5: ='Construction Budget'!C3 -> Data Center Template, Northern Virginia
B6: ="Hyperscale Data Center | "&'Construction Budget'!C4 -> Hyperscale Data Center | Loudoun County, VA
B8: SOLICITATION
B9: Solicitation / RFP No.: | C9: =IF('GC Bid Form'!D10="","",'GC Bid Form'!D10)
B10: Bid Due Date & Time: | C10: =IF('GC Bid Form'!D11="","",'GC Bid Form'!D11)
B11: Delivery Method: | C11: =IF('GC Bid Form'!D9="","",'GC Bid Form'!D9) -> CM-at-Risk / Guaranteed Maximum Price (GMP)
B13: SUBMIT TO
B14: Owner / Procurement: | C14: Owner Program Management Office (edit)
B15: Attention: | C15: Attn: Procurement & Contracts
B16: Address: | C16: [ Insert delivery address, room / desk ]
B18: FROM (BIDDER)
B19: Company: | C19: =IF('GC Bid Form'!D16="","",'GC Bid Form'!D16)
B20: Contact / Phone: | C20: =IF('GC Bid Form'!D17="","",'GC Bid Form'!D17)
B22: SEALING & LABELING INSTRUCTIONS
B23: 1. Enclose the completed, signed Bid Form and all required attachments in a sealed, opaque envelope or package.
B24: 2. Affix this cover sheet to the outside of the sealed package.
B25: 3. Mark the package “SEALED BID — DO NOT OPEN” and deliver to the Submit-To address before the Bid Due Date & Time.
B26: 4. Late submissions will not be accepted. Faxed or emailed bids are not accepted unless expressly permitted in the solicitation.
B28: Do not write the bid amount anywhere on this cover. The Owner is not responsible for premature opening of bids not properly sealed and labeled.
B30: REQUIRED DOCUMENTS — CONFIRM ENCLOSED
B31: ☐ Completed & signed Bid Form (every division priced or excluded)
B32: ☐ Bid bond / bid security (amount per solicitation)
B33: ☐ Certificate of Insurance meeting Owner requirements
B34: ☐ Contractor's license & statement of qualifications
B35: ☐ Proposed project schedule (to Substantial Completion)
... B39: ☐ Safety record (EMR) & three comparable project references

Sheet GC Bid Form
B1: GENERAL CONTRACTOR BID FORM
B2: ='Construction Budget'!C3&" — Hyperscale Data Center" -> Data Center Template, Northern Virginia — Hyperscale Data Center
B3: CONFIDENTIAL — Submit a sealed, signed bid by the Bid Due Date stated below. All amounts in US$.
B5: 1 · PROJECT & SOLICITATION
B6: Project: | D6: ='Construction Budget'!C3 -> Data Center Template, Northern Virginia
B7: Location: | D7: ='Construction Budget'!C4 -> Loudoun County, VA
B8: Owner / Client: | D8: ='Construction Budget'!C5 -> Confidential Hyperscaler
B9: Delivery Method: | D9: CM-at-Risk / Guaranteed Maximum Price (GMP)
B10: RFP / Solicitation No.:
B11: Bid Due Date:
B12: Target NTP (ref): | D12: ='Construction Budget'!F3 -> 46143
B13: Target Completion (ref): | D13: ='Construction Budget'!F4 -> Q1 2029
B15: 2 · BIDDER INFORMATION
B16: Company Name:
B17: Primary Contact / Title:
B18: Address:
B19: Phone / Email:
B20: Contractor License No.:
B21: Bonding Capacity / Surety:
B22: Date Submitted:
B24: 3 · BASE BID BY TRADE / DIVISION (CSI)
B25: Enter a lump-sum base bid for each division below. Leave blank only if excluding a division — note all exclusions in §7.
B26: # | C26: Trade / Division (CSI) | D26: Base Bid (US$) | E26: Notes / Clarifications
B27: 1 | C27: ='Bid Leveling'!B13 -> General Conditions & Requirements
B28: 2 | C28: ='Bid Leveling'!B14 -> Commissioning & Testing
B29: 3 | C29: ='Bid Leveling'!B15 -> Div 03 — Concrete
B30: 4 | C30: ='Bid Leveling'!B16 -> Div 04 — Masonry
B31: 5 | C31: ='Bid Leveling'!B17 -> Div 05 — Metals / Structural Steel
B32: 6 | C32: ='Bid Leveling'!B18 -> Div 06 — Wood, Plastics & Composites
B33: 7 | C33: ='Bid Leveling'!B19 -> Div 07 — Thermal & Moisture Protection
B34: 8 | C34: ='Bid Leveling'!B20 -> Div 08 — Openings
B35: 9 | C35: ='Bid Leveling'!B21 -> Div 09 — Finishes
B36: 10 | C36: ='Bid Leveling'!B22 -> Div 10 — Specialties
B37: 11 | C37: ='Bid Leveling'!B23 -> Div 11 — Equipment
B38: 12 | C38: ='Bid Leveling'!B24 -> Div 12 — Furnishings
... B50: 24 | C50: ='Bid Leveling'!B36 -> Soft Costs / Pre-Construction
C51: TOTAL BASE BID (sum of all divisions) | D51: =SUM(D27:D50) -> 0
B53: 4 · ALTERNATES (ADD / DEDUCT)
B54: # | C54: Alternate Description | D54: Add / (Deduct) $ | E54: Notes
B55: 1 | C55: Upgrade to N+2 redundancy on critical cooling
B56: 2 | C56: Add 10 MW incremental UPS capacity
B57: 3 | C57: Premium to accelerate Substantial Completion by 2 months
B58: 4 | C58: Substitute air-cooled chillers for water-cooled plant
B59: 5 | C59: Bidder-proposed alternate (describe):
B61: 5 · UNIT PRICES (FOR CHANGES IN SCOPE)
B62: # | C62: Item | D62: Unit | E62: Unit Price (US$)
B63: 1 | C63: Structural concrete — placed & finished | D63: CY
B64: 2 | C64: Reinforcing steel — installed | D64: TON
B65: 3 | C65: Mass excavation | D65: CY
B66: 4 | C66: Select structural fill — imported & compacted | D66: CY
B67: 5 | C67: Branch conduit & wire (typical run) | D67: LF
B69: 6 · SCHEDULE COMMITMENT
B70: Proposed mobilization (days from NTP):
B71: Proposed Substantial Completion date:
B72: Total duration (calendar months):
B73: Can you meet the Owner's Target Completion? (Y/N):
B74: Schedule comments:
B76: 7 · QUALIFICATIONS, ASSUMPTIONS & EXCLUSIONS
B77: List all qualifications, assumptions, and scope exclusions below. Any division left blank in §3 must be noted here as excluded. Attach additional sheets as needed.
B83: 8 · ACKNOWLEDGEMENTS
B84: Addenda received (list numbers):
B85: Bid bond / security attached (Y/N):
B86: Bid valid for (calendar days):
... B96: Company Seal:

Sheet Bid Leveling
A1: BID LEVELING — GENERAL CONTRACTOR ANALYSIS
A2: Trade-by-trade comparison of general contractor bids vs. the engineer's estimate. Baseline = Construction Budget. Enter GC bids in the blue input cells.
A4: EXECUTIVE SUMMARY
A6: RECOMMENDED GC | C6: AWARD VALUE | E6: SAVINGS vs EE | G6: ENGINEER'S ESTIMATE | I6: GC BIDS RECEIVED
A7: =IF(MAX($D$37:$G$37)=0,"— enter bids",INDEX($D$12:$G$12,MATCH(_xlfn.MINIFS($D$37:$G$37,$D$37:$G$37,">0"),$D$37:$G$37,0))) -> — enter bids | C7: =IF(MAX($D$37:$G$37)=0,0,_xlfn.MINIFS($D$37:$G$37,$D$37:$G$37,">0")) -> 0 | E7: =IF($C$7=0,0,$C$37-$C$7) -> 0 | G7: =$C$37 -> 1.0883418e+09 | I7: =COUNTIF($D$37:$G$37,">0") -> 0
A10: TRADE-BY-TRADE GC BID COMPARISON
A12: # | B12: Trade / Division (CSI) | C12: Engineer's Estimate | D12: National Build Group | E12: Western Constructors | F12: Metro Mission Critical | G12: Pinnacle CM (DC specialist) | H12: Low Bid | I12: Δ Low vs EE | J12: Notes
A13: 1 | B13: General Conditions & Requirements | C13: ='Construction Budget'!H58 -> 42983031 | D13: =IF('GC Bid Form'!$D$16<>D$12,"",IFERROR(INDEX('GC Bid Form'!$D$27:$D$50,MATCH($B13,'GC Bid Form'!$C$27:$C$50,0)),"")) | E13: =IF('GC Bid Form'!$D$16<>E$12,"",IFERROR(INDEX('GC Bid Form'!$D$27:$D$50,MATCH($B13,'GC Bid Form'!$C$27:$C$50,0)),"")) | F13: =IF('GC Bid Form'!$D$16<>F$12,"",IFERROR(INDEX('GC Bid Form'!$D$27:$D$50,MATCH($B13,'GC Bid Form'!$C$27:$C$50,0)),"")) | G13: =IF('GC Bid Form'!$D$16<>G$12,"",IFERROR(INDEX('GC Bid Form'!$D$27:$D$50,MATCH($B13,'GC Bid Form'!$C$27:$C$50,0)),"")) | H13: =IF(COUNT(D13:G13)=0,"",MIN(D13:G13)) | I13: =IF(OR($H13="",$C13=0),"",($H13-$C13)/$C13)
A14: 2 | B14: Commissioning & Testing | C14: ='Construction Budget'!H75 -> 47367292 | D14: =IF('GC Bid Form'!$D$16<>D$12,"",IFERROR(INDEX('GC Bid Form'!$D$27:$D$50,MATCH($B14,'GC Bid Form'!$C$27:$C$50,0)),"")) | E14: =IF('GC Bid Form'!$D$16<>E$12,"",IFERROR(INDEX('GC Bid Form'!$D$27:$D$50,MATCH($B14,'GC Bid Form'!$C$27:$C$50,0)),"")) | F14: =IF('GC Bid Form'!$D$16<>F$12,"",IFERROR(INDEX('GC Bid Form'!$D$27:$D$50,MATCH($B14,'GC Bid Form'!$C$27:$C$50,0)),"")) | G14: =IF('GC Bid Form'!$D$16<>G$12,"",IFERROR(INDEX('GC Bid Form'!$D$27:$D$50,MATCH($B14,'GC Bid Form'!$C$27:$C$50,0)),"")) | H14: =IF(COUNT(D14:G14)=0,"",MIN(D14:G14)) | I14: =IF(OR($H14="",$C14=0),"",($H14-$C14)/$C14)
A15: 3 | B15: Div 03 — Concrete | C15: ='Construction Budget'!H112 -> 33466040 | D15: =IF('GC Bid Form'!$D$16<>D$12,"",IFERROR(INDEX('GC Bid Form'!$D$27:$D$50,MATCH($B15,'GC Bid Form'!$C$27:$C$50,0)),"")) | E15: =IF('GC Bid Form'!$D$16<>E$12,"",IFERROR(INDEX('GC Bid Form'!$D$27:$D$50,MATCH($B15,'GC Bid Form'!$C$27:$C$50,0)),"")) | F15: =IF('GC Bid Form'!$D$16<>F$12,"",IFERROR(INDEX('GC Bid Form'!$D$27:$D$50,MATCH($B15,'GC Bid Form'!$C$27:$C$50,0)),"")) | G15: =IF('GC Bid Form'!$D$16<>G$12,"",IFERROR(INDEX('GC Bid Form'!$D$27:$D$50,MATCH($B15,'GC Bid Form'!$C$27:$C$50,0)),"")) | H15: =IF(COUNT(D15:G15)=0,"",MIN(D15:G15)) | I15: =IF(OR($H15="",$C15=0),"",($H15-$C15)/$C15)
A16: 4 | B16: Div 04 — Masonry | C16: ='Construction Budget'!H126 -> 5656068 | D16: =IF('GC Bid Form'!$D$16<>D$12,"",IFERROR(INDEX('GC Bid Form'!$D$27:$D$50,MATCH($B16,'GC Bid Form'!$C$27:$C$50,0)),"")) | E16: =IF('GC Bid Form'!$D$16<>E$12,"",IFERROR(INDEX('GC Bid Form'!$D$27:$D$50,MATCH($B16,'GC Bid Form'!$C$27:$C$50,0)),"")) | F16: =IF('GC Bid Form'!$D$16<>F$12,"",IFERROR(INDEX('GC Bid Form'!$D$27:$D$50,MATCH($B16,'GC Bid Form'!$C$27:$C$50,0)),"")) | G16: =IF('GC Bid Form'!$D$16<>G$12,"",IFERROR(INDEX('GC Bid Form'!$D$27:$D$50,MATCH($B16,'GC Bid Form'!$C$27:$C$50,0)),"")) | H16: =IF(COUNT(D16:G16)=0,"",MIN(D16:G16)) | I16: =IF(OR($H16="",$C16=0),"",($H16-$C16)/$C16)
A17: 5 | B17: Div 05 — Metals / Structural Steel | C17: ='Construction Budget'!H164 -> 40836400 | D17: =IF('GC Bid Form'!$D$16<>D$12,"",IFERROR(INDEX('GC Bid Form'!$D$27:$D$50,MATCH($B17,'GC Bid Form'!$C$27:$C$50,0)),"")) | E17: =IF('GC Bid Form'!$D$16<>E$12,"",IFERROR(INDEX('GC Bid Form'!$D$27:$D$50,MATCH($B17,'GC Bid Form'!$C$27:$C$50,0)),"")) | F17: =IF('GC Bid Form'!$D$16<>F$12,"",IFERROR(INDEX('GC Bid Form'!$D$27:$D$50,MATCH($B17,'GC Bid Form'!$C$27:$C$50,0)),"")) | G17: =IF('GC Bid Form'!$D$16<>G$12,"",IFERROR(INDEX('GC Bid Form'!$D$27:$D$50,MATCH($B17,'GC Bid Form'!$C$27:$C$50,0)),"")) | H17: =IF(COUNT(D17:G17)=0,"",MIN(D17:G17)) | I17: =IF(OR($H17="",$C17=0),"",($H17-$C17)/$C17)
A18: 6 | B18: Div 06 — Wood, Plastics & Composites | C18: ='Construction Budget'!H174 -> 1233678.6 | D18: =IF('GC Bid Form'!$D$16<>D$12,"",IFERROR(INDEX('GC Bid Form'!$D$27:$D$50,MATCH($B18,'GC Bid Form'!$C$27:$C$50,0)),"")) | E18: =IF('GC Bid Form'!$D$16<>E$12,"",IFERROR(INDEX('GC Bid Form'!$D$27:$D$50,MATCH($B18,'GC Bid Form'!$C$27:$C$50,0)),"")) | F18: =IF('GC Bid Form'!$D$16<>F$12,"",IFERROR(INDEX('GC Bid Form'!$D$27:$D$50,MATCH($B18,'GC Bid Form'!$C$27:$C$50,0)),"")) | G18: =IF('GC Bid Form'!$D$16<>G$12,"",IFERROR(INDEX('GC Bid Form'!$D$27:$D$50,MATCH($B18,'GC Bid Form'!$C$27:$C$50,0)),"")) | H18: =IF(COUNT(D18:G18)=0,"",MIN(D18:G18)) | I18: =IF(OR($H18="",$C18=0),"",($H18-$C18)/$C18)
A19: 7 | B19: Div 07 — Thermal & Moisture Protection | C19: ='Construction Budget'!H212 -> 38165651 | D19: =IF('GC Bid Form'!$D$16<>D$12,"",IFERROR(INDEX('GC Bid Form'!$D$27:$D$50,MATCH($B19,'GC Bid Form'!$C$27:$C$50,0)),"")) | E19: =IF('GC Bid Form'!$D$16<>E$12,"",IFERROR(INDEX('GC Bid Form'!$D$27:$D$50,MATCH($B19,'GC Bid Form'!$C$27:$C$50,0)),"")) | F19: =IF('GC Bid Form'!$D$16<>F$12,"",IFERROR(INDEX('GC Bid Form'!$D$27:$D$50,MATCH($B19,'GC Bid Form'!$C$27:$C$50,0)),"")) | G19: =IF('GC Bid Form'!$D$16<>G$12,"",IFERROR(INDEX('GC Bid Form'!$D$27:$D$50,MATCH($B19,'GC Bid Form'!$C$27:$C$50,0)),"")) | H19: =IF(COUNT(D19:G19)=0,"",MIN(D19:G19)) | I19: =IF(OR($H19="",$C19=0),"",($H19-$C19)/$C19)
A20: 8 | B20: Div 08 — Openings | C20: ='Construction Budget'!H239 -> 13742210 | D20: =IF('GC Bid Form'!$D$16<>D$12,"",IFERROR(INDEX('GC Bid Form'!$D$27:$D$50,MATCH($B20,'GC Bid Form'!$C$27:$C$50,0)),"")) | E20: =IF('GC Bid Form'!$D$16<>E$12,"",IFERROR(INDEX('GC Bid Form'!$D$27:$D$50,MATCH($B20,'GC Bid Form'!$C$27:$C$50,0)),"")) | F20: =IF('GC Bid Form'!$D$16<>F$12,"",IFERROR(INDEX('GC Bid Form'!$D$27:$D$50,MATCH($B20,'GC Bid Form'!$C$27:$C$50,0)),"")) | G20: =IF('GC Bid Form'!$D$16<>G$12,"",IFERROR(INDEX('GC Bid Form'!$D$27:$D$50,MATCH($B20,'GC Bid Form'!$C$27:$C$50,0)),"")) | H20: =IF(COUNT(D20:G20)=0,"",MIN(D20:G20)) | I20: =IF(OR($H20="",$C20=0),"",($H20-$C20)/$C20)
A21: 9 | B21: Div 09 — Finishes | C21: ='Construction Budget'!H272 -> 33189552 | D21: =IF('GC Bid Form'!$D$16<>D$12,"",IFERROR(INDEX('GC Bid Form'!$D$27:$D$50,MATCH($B21,'GC Bid Form'!$C$27:$C$50,0)),"")) | E21: =IF('GC Bid Form'!$D$16<>E$12,"",IFERROR(INDEX('GC Bid Form'!$D$27:$D$50,MATCH($B21,'GC Bid Form'!$C$27:$C$50,0)),"")) | F21: =IF('GC Bid Form'!$D$16<>F$12,"",IFERROR(INDEX('GC Bid Form'!$D$27:$D$50,MATCH($B21,'GC Bid Form'!$C$27:$C$50,0)),"")) | G21: =IF('GC Bid Form'!$D$16<>G$12,"",IFERROR(INDEX('GC Bid Form'!$D$27:$D$50,MATCH($B21,'GC Bid Form'!$C$27:$C$50,0)),"")) | H21: =IF(COUNT(D21:G21)=0,"",MIN(D21:G21)) | I21: =IF(OR($H21="",$C21=0),"",($H21-$C21)/$C21)
A22: 10 | B22: Div 10 — Specialties | C22: ='Construction Budget'!H292 -> 4010233.4 | D22: =IF('GC Bid Form'!$D$16<>D$12,"",IFERROR(INDEX('GC Bid Form'!$D$27:$D$50,MATCH($B22,'GC Bid Form'!$C$27:$C$50,0)),"")) | E22: =IF('GC Bid Form'!$D$16<>E$12,"",IFERROR(INDEX('GC Bid Form'!$D$27:$D$50,MATCH($B22,'GC Bid Form'!$C$27:$C$50,0)),"")) | F22: =IF('GC Bid Form'!$D$16<>F$12,"",IFERROR(INDEX('GC Bid Form'!$D$27:$D$50,MATCH($B22,'GC Bid Form'!$C$27:$C$50,0)),"")) | G22: =IF('GC Bid Form'!$D$16<>G$12,"",IFERROR(INDEX('GC Bid Form'!$D$27:$D$50,MATCH($B22,'GC Bid Form'!$C$27:$C$50,0)),"")) | H22: =IF(COUNT(D22:G22)=0,"",MIN(D22:G22)) | I22: =IF(OR($H22="",$C22=0),"",($H22-$C22)/$C22)
A23: 11 | B23: Div 11 — Equipment | C23: ='Construction Budget'!H305 -> 1525590 | D23: =IF('GC Bid Form'!$D$16<>D$12,"",IFERROR(INDEX('GC Bid Form'!$D$27:$D$50,MATCH($B23,'GC Bid Form'!$C$27:$C$50,0)),"")) | E23: =IF('GC Bid Form'!$D$16<>E$12,"",IFERROR(INDEX('GC Bid Form'!$D$27:$D$50,MATCH($B23,'GC Bid Form'!$C$27:$C$50,0)),"")) | F23: =IF('GC Bid Form'!$D$16<>F$12,"",IFERROR(INDEX('GC Bid Form'!$D$27:$D$50,MATCH($B23,'GC Bid Form'!$C$27:$C$50,0)),"")) | G23: =IF('GC Bid Form'!$D$16<>G$12,"",IFERROR(INDEX('GC Bid Form'!$D$27:$D$50,MATCH($B23,'GC Bid Form'!$C$27:$C$50,0)),"")) | H23: =IF(COUNT(D23:G23)=0,"",MIN(D23:G23)) | I23: =IF(OR($H23="",$C23=0),"",($H23-$C23)/$C23)
A24: 12 | B24: Div 12 — Furnishings | C24: ='Construction Budget'!H315 -> 1217056.5 | D24: =IF('GC Bid Form'!$D$16<>D$12,"",IFERROR(INDEX('GC Bid Form'!$D$27:$D$50,MATCH($B24,'GC Bid Form'!$C$27:$C$50,0)),"")) | E24: =IF('GC Bid Form'!$D$16<>E$12,"",IFERROR(INDEX('GC Bid Form'!$D$27:$D$50,MATCH($B24,'GC Bid Form'!$C$27:$C$50,0)),"")) | F24: =IF('GC Bid Form'!$D$16<>F$12,"",IFERROR(INDEX('GC Bid Form'!$D$27:$D$50,MATCH($B24,'GC Bid Form'!$C$27:$C$50,0)),"")) | G24: =IF('GC Bid Form'!$D$16<>G$12,"",IFERROR(INDEX('GC Bid Form'!$D$27:$D$50,MATCH($B24,'GC Bid Form'!$C$27:$C$50,0)),"")) | H24: =IF(COUNT(D24:G24)=0,"",MIN(D24:G24)) | I24: =IF(OR($H24="",$C24=0),"",($H24-$C24)/$C24)
A25: 13 | B25: Div 14 — Conveying Equipment | C25: ='Construction Budget'!H324 -> 4104292.5 | D25: =IF('GC Bid Form'!$D$16<>D$12,"",IFERROR(INDEX('GC Bid Form'!$D$27:$D$50,MATCH($B25,'GC Bid Form'!$C$27:$C$50,0)),"")) | E25: =IF('GC Bid Form'!$D$16<>E$12,"",IFERROR(INDEX('GC Bid Form'!$D$27:$D$50,MATCH($B25,'GC Bid Form'!$C$27:$C$50,0)),"")) | F25: =IF('GC Bid Form'!$D$16<>F$12,"",IFERROR(INDEX('GC Bid Form'!$D$27:$D$50,MATCH($B25,'GC Bid Form'!$C$27:$C$50,0)),"")) | G25: =IF('GC Bid Form'!$D$16<>G$12,"",IFERROR(INDEX('GC Bid Form'!$D$27:$D$50,MATCH($B25,'GC Bid Form'!$C$27:$C$50,0)),"")) | H25: =IF(COUNT(D25:G25)=0,"",MIN(D25:G25)) | I25: =IF(OR($H25="",$C25=0),"",($H25-$C25)/$C25)
A26: 14 | B26: Div 21 — Fire Suppression | C26: ='Construction Budget'!H359 -> 22577594 | D26: =IF('GC Bid Form'!$D$16<>D$12,"",IFERROR(INDEX('GC Bid Form'!$D$27:$D$50,MATCH($B26,'GC Bid Form'!$C$27:$C$50,0)),"")) | E26: =IF('GC Bid Form'!$D$16<>E$12,"",IFERROR(INDEX('GC Bid Form'!$D$27:$D$50,MATCH($B26,'GC Bid Form'!$C$27:$C$50,0)),"")) | F26: =IF('GC Bid Form'!$D$16<>F$12,"",IFERROR(INDEX('GC Bid Form'!$D$27:$D$50,MATCH($B26,'GC Bid Form'!$C$27:$C$50,0)),"")) | G26: =IF('GC Bid Form'!$D$16<>G$12,"",IFERROR(INDEX('GC Bid Form'!$D$27:$D$50,MATCH($B26,'GC Bid Form'!$C$27:$C$50,0)),"")) | H26: =IF(COUNT(D26:G26)=0,"",MIN(D26:G26)) | I26: =IF(OR($H26="",$C26=0),"",($H26-$C26)/$C26)
A27: 15 | B27: Div 22 — Plumbing | C27: ='Construction Budget'!H387 -> 22312499 | D27: =IF('GC Bid Form'!$D$16<>D$12,"",IFERROR(INDEX('GC Bid Form'!$D$27:$D$50,MATCH($B27,'GC Bid Form'!$C$27:$C$50,0)),"")) | E27: =IF('GC Bid Form'!$D$16<>E$12,"",IFERROR(INDEX('GC Bid Form'!$D$27:$D$50,MATCH($B27,'GC Bid Form'!$C$27:$C$50,0)),"")) | F27: =IF('GC Bid Form'!$D$16<>F$12,"",IFERROR(INDEX('GC Bid Form'!$D$27:$D$50,MATCH($B27,'GC Bid Form'!$C$27:$C$50,0)),"")) | G27: =IF('GC Bid Form'!$D$16<>G$12,"",IFERROR(INDEX('GC Bid Form'!$D$27:$D$50,MATCH($B27,'GC Bid Form'!$C$27:$C$50,0)),"")) | H27: =IF(COUNT(D27:G27)=0,"",MIN(D27:G27)) | I27: =IF(OR($H27="",$C27=0),"",($H27-$C27)/$C27)
A28: 16 | B28: Div 23 — HVAC / Cooling Systems | C28: ='Construction Budget'!H495 -> 2.2648425e+08 | D28: =IF('GC Bid Form'!$D$16<>D$12,"",IFERROR(INDEX('GC Bid Form'!$D$27:$D$50,MATCH($B28,'GC Bid Form'!$C$27:$C$50,0)),"")) | E28: =IF('GC Bid Form'!$D$16<>E$12,"",IFERROR(INDEX('GC Bid Form'!$D$27:$D$50,MATCH($B28,'GC Bid Form'!$C$27:$C$50,0)),"")) | F28: =IF('GC Bid Form'!$D$16<>F$12,"",IFERROR(INDEX('GC Bid Form'!$D$27:$D$50,MATCH($B28,'GC Bid Form'!$C$27:$C$50,0)),"")) | G28: =IF('GC Bid Form'!$D$16<>G$12,"",IFERROR(INDEX('GC Bid Form'!$D$27:$D$50,MATCH($B28,'GC Bid Form'!$C$27:$C$50,0)),"")) | H28: =IF(COUNT(D28:G28)=0,"",MIN(D28:G28)) | I28: =IF(OR($H28="",$C28=0),"",($H28-$C28)/$C28)
A29: 17 | B29: Div 25 — Integrated Automation | C29: ='Construction Budget'!H517 -> 13470732 | D29: =IF('GC Bid Form'!$D$16<>D$12,"",IFERROR(INDEX('GC Bid Form'!$D$27:$D$50,MATCH($B29,'GC Bid Form'!$C$27:$C$50,0)),"")) | E29: =IF('GC Bid Form'!$D$16<>E$12,"",IFERROR(INDEX('GC Bid Form'!$D$27:$D$50,MATCH($B29,'GC Bid Form'!$C$27:$C$50,0)),"")) | F29: =IF('GC Bid Form'!$D$16<>F$12,"",IFERROR(INDEX('GC Bid Form'!$D$27:$D$50,MATCH($B29,'GC Bid Form'!$C$27:$C$50,0)),"")) | G29: =IF('GC Bid Form'!$D$16<>G$12,"",IFERROR(INDEX('GC Bid Form'!$D$27:$D$50,MATCH($B29,'GC Bid Form'!$C$27:$C$50,0)),"")) | H29: =IF(COUNT(D29:G29)=0,"",MIN(D29:G29)) | I29: =IF(OR($H29="",$C29=0),"",($H29-$C29)/$C29)
A30: 18 | B30: Div 26 — Electrical / Critical Power | C30: ='Construction Budget'!H665 -> 2.4814778e+08 | D30: =IF('GC Bid Form'!$D$16<>D$12,"",IFERROR(INDEX('GC Bid Form'!$D$27:$D$50,MATCH($B30,'GC Bid Form'!$C$27:$C$50,0)),"")) | E30: =IF('GC Bid Form'!$D$16<>E$12,"",IFERROR(INDEX('GC Bid Form'!$D$27:$D$50,MATCH($B30,'GC Bid Form'!$C$27:$C$50,0)),"")) | F30: =IF('GC Bid Form'!$D$16<>F$12,"",IFERROR(INDEX('GC Bid Form'!$D$27:$D$50,MATCH($B30,'GC Bid Form'!$C$27:$C$50,0)),"")) | G30: =IF('GC Bid Form'!$D$16<>G$12,"",IFERROR(INDEX('GC Bid Form'!$D$27:$D$50,MATCH($B30,'GC Bid Form'!$C$27:$C$50,0)),"")) | H30: =IF(COUNT(D30:G30)=0,"",MIN(D30:G30)) | I30: =IF(OR($H30="",$C30=0),"",($H30-$C30)/$C30)
A31: 19 | B31: Div 27 — Communications / IT Infrastructure | C31: ='Construction Budget'!H714 -> 60417388 | D31: =IF('GC Bid Form'!$D$16<>D$12,"",IFERROR(INDEX('GC Bid Form'!$D$27:$D$50,MATCH($B31,'GC Bid Form'!$C$27:$C$50,0)),"")) | E31: =IF('GC Bid Form'!$D$16<>E$12,"",IFERROR(INDEX('GC Bid Form'!$D$27:$D$50,MATCH($B31,'GC Bid Form'!$C$27:$C$50,0)),"")) | F31: =IF('GC Bid Form'!$D$16<>F$12,"",IFERROR(INDEX('GC Bid Form'!$D$27:$D$50,MATCH($B31,'GC Bid Form'!$C$27:$C$50,0)),"")) | G31: =IF('GC Bid Form'!$D$16<>G$12,"",IFERROR(INDEX('GC Bid Form'!$D$27:$D$50,MATCH($B31,'GC Bid Form'!$C$27:$C$50,0)),"")) | H31: =IF(COUNT(D31:G31)=0,"",MIN(D31:G31)) | I31: =IF(OR($H31="",$C31=0),"",($H31-$C31)/$C31)
A32: 20 | B32: Div 28 — Electronic Safety & Security | C32: ='Construction Budget'!H742 -> 15750753 | D32: =IF('GC Bid Form'!$D$16<>D$12,"",IFERROR(INDEX('GC Bid Form'!$D$27:$D$50,MATCH($B32,'GC Bid Form'!$C$27:$C$50,0)),"")) | E32: =IF('GC Bid Form'!$D$16<>E$12,"",IFERROR(INDEX('GC Bid Form'!$D$27:$D$50,MATCH($B32,'GC Bid Form'!$C$27:$C$50,0)),"")) | F32: =IF('GC Bid Form'!$D$16<>F$12,"",IFERROR(INDEX('GC Bid Form'!$D$27:$D$50,MATCH($B32,'GC Bid Form'!$C$27:$C$50,0)),"")) | G32: =IF('GC Bid Form'!$D$16<>G$12,"",IFERROR(INDEX('GC Bid Form'!$D$27:$D$50,MATCH($B32,'GC Bid Form'!$C$27:$C$50,0)),"")) | H32: =IF(COUNT(D32:G32)=0,"",MIN(D32:G32)) | I32: =IF(OR($H32="",$C32=0),"",($H32-$C32)/$C32)
A33: 21 | B33: Div 31 — Earthwork | C33: ='Construction Budget'!H772 -> 25614732 | D33: =IF('GC Bid Form'!$D$16<>D$12,"",IFERROR(INDEX('GC Bid Form'!$D$27:$D$50,MATCH($B33,'GC Bid Form'!$C$27:$C$50,0)),"")) | E33: =IF('GC Bid Form'!$D$16<>E$12,"",IFERROR(INDEX('GC Bid Form'!$D$27:$D$50,MATCH($B33,'GC Bid Form'!$C$27:$C$50,0)),"")) | F33: =IF('GC Bid Form'!$D$16<>F$12,"",IFERROR(INDEX('GC Bid Form'!$D$27:$D$50,MATCH($B33,'GC Bid Form'!$C$27:$C$50,0)),"")) | G33: =IF('GC Bid Form'!$D$16<>G$12,"",IFERROR(INDEX('GC Bid Form'!$D$27:$D$50,MATCH($B33,'GC Bid Form'!$C$27:$C$50,0)),"")) | H33: =IF(COUNT(D33:G33)=0,"",MIN(D33:G33)) | I33: =IF(OR($H33="",$C33=0),"",($H33-$C33)/$C33)
A34: 22 | B34: Div 32 — Exterior Improvements | C34: ='Construction Budget'!H792 -> 9371809.5 | D34: =IF('GC Bid Form'!$D$16<>D$12,"",IFERROR(INDEX('GC Bid Form'!$D$27:$D$50,MATCH($B34,'GC Bid Form'!$C$27:$C$50,0)),"")) | E34: =IF('GC Bid Form'!$D$16<>E$12,"",IFERROR(INDEX('GC Bid Form'!$D$27:$D$50,MATCH($B34,'GC Bid Form'!$C$27:$C$50,0)),"")) | F34: =IF('GC Bid Form'!$D$16<>F$12,"",IFERROR(INDEX('GC Bid Form'!$D$27:$D$50,MATCH($B34,'GC Bid Form'!$C$27:$C$50,0)),"")) | G34: =IF('GC Bid Form'!$D$16<>G$12,"",IFERROR(INDEX('GC Bid Form'!$D$27:$D$50,MATCH($B34,'GC Bid Form'!$C$27:$C$50,0)),"")) | H34: =IF(COUNT(D34:G34)=0,"",MIN(D34:G34)) | I34: =IF(OR($H34="",$C34=0),"",($H34-$C34)/$C34)
A35: 23 | B35: Div 33 — Utilities | C35: ='Construction Budget'!H835 -> 63598602 | D35: =IF('GC Bid Form'!$D$16<>D$12,"",IFERROR(INDEX('GC Bid Form'!$D$27:$D$50,MATCH($B35,'GC Bid Form'!$C$27:$C$50,0)),"")) | E35: =IF('GC Bid Form'!$D$16<>E$12,"",IFERROR(INDEX('GC Bid Form'!$D$27:$D$50,MATCH($B35,'GC Bid Form'!$C$27:$C$50,0)),"")) | F35: =IF('GC Bid Form'!$D$16<>F$12,"",IFERROR(INDEX('GC Bid Form'!$D$27:$D$50,MATCH($B35,'GC Bid Form'!$C$27:$C$50,0)),"")) | G35: =IF('GC Bid Form'!$D$16<>G$12,"",IFERROR(INDEX('GC Bid Form'!$D$27:$D$50,MATCH($B35,'GC Bid Form'!$C$27:$C$50,0)),"")) | H35: =IF(COUNT(D35:G35)=0,"",MIN(D35:G35)) | I35: =IF(OR($H35="",$C35=0),"",($H35-$C35)/$C35)
A36: 24 | B36: Soft Costs / Pre-Construction | C36: ='Construction Budget'!H37 -> 113098590 | D36: =IF('GC Bid Form'!$D$16<>D$12,"",IFERROR(INDEX('GC Bid Form'!$D$27:$D$50,MATCH($B36,'GC Bid Form'!$C$27:$C$50,0)),"")) | E36: =IF('GC Bid Form'!$D$16<>E$12,"",IFERROR(INDEX('GC Bid Form'!$D$27:$D$50,MATCH($B36,'GC Bid Form'!$C$27:$C$50,0)),"")) | F36: =IF('GC Bid Form'!$D$16<>F$12,"",IFERROR(INDEX('GC Bid Form'!$D$27:$D$50,MATCH($B36,'GC Bid Form'!$C$27:$C$50,0)),"")) | G36: =IF('GC Bid Form'!$D$16<>G$12,"",IFERROR(INDEX('GC Bid Form'!$D$27:$D$50,MATCH($B36,'GC Bid Form'!$C$27:$C$50,0)),"")) | H36: =IF(COUNT(D36:G36)=0,"",MIN(D36:G36)) | I36: =IF(OR($H36="",$C36=0),"",($H36-$C36)/$C36)
B37: TOTAL — ALL TRADES | C37: =SUM(C13:C36) -> 1.0883418e+09 | D37: =SUM(D13:D36) -> 0 | E37: =SUM(E13:E36) -> 0 | F37: =SUM(F13:F36) -> 0 | G37: =SUM(G13:G36) -> 0 | H37: =IF(COUNT(D37:G37)=0,"",SUM(H13:H36)) -> 0 | I37: =IF(OR($H37="",$H37=0,$C37=0),"",($H37-$C37)/$C37)
A39: GC BID SUMMARY & RECOMMENDATION | B39: ="▲ Columns D–G link live to the GC Bid Form. Currently mapped to: "&IF('GC Bid Form'!D16="","(no bidder selected)",'GC Bid Form'!D16) -> ▲ Columns D–G link live to the GC Bid Form. Currently mapped to: (no bidder selected)
B40: Workflow: select the bidder on the GC Bid Form, enter their division prices, then Copy → Paste-Values that column here to retain it before processing the next bidder. | C40: Total Bid | D40: Δ vs EE ($) | E40: Δ vs EE (%) | F40: Rank | G40: Status / Qualification
B41: =D12 -> National Build Group | C41: =D37 -> 0 | D41: =IF($C41=0,"",$C41-$C$37) | E41: =IF($C41=0,"",$C41/$C$37-1) | F41: {=IF($C41=0,"—",SUMPRODUCT(($C$41:$C$44>0)*($C$41:$C$44<$C41))+1)} -> —
B42: =E12 -> Western Constructors | C42: =E37 -> 0 | D42: =IF($C42=0,"",$C42-$C$37) | E42: =IF($C42=0,"",$C42/$C$37-1) | F42: {=IF($C42=0,"—",SUMPRODUCT(($C$41:$C$44>0)*($C$41:$C$44<$C42))+1)} -> —
B43: =F12 -> Metro Mission Critical | C43: =F37 -> 0 | D43: =IF($C43=0,"",$C43-$C$37) | E43: =IF($C43=0,"",$C43/$C$37-1) | F43: {=IF($C43=0,"—",SUMPRODUCT(($C$41:$C$44>0)*($C$41:$C$44<$C43))+1)} -> —
B44: =G12 -> Pinnacle CM (DC specialist) | C44: =G37 -> 0 | D44: =IF($C44=0,"",$C44-$C$37) | E44: =IF($C44=0,"",$C44/$C$37-1) | F44: {=IF($C44=0,"—",SUMPRODUCT(($C$41:$C$44>0)*($C$41:$C$44<$C44))+1)} -> —
B46: RECOMMENDATION | C46: =IF(MAX($C$41:$C$44)=0,"Enter GC bids in the blue cells to generate a recommendation.","Award to "&$A$7&" at "&TEXT($C$7,"$#,##0")&" ("&TEXT(($C$7-$C$37)/$C$37,"+0.0%;-0.0%")&" vs engineer's estimate of "&TEXT($C$37,"$#,##0")&").") -> Enter GC bids in the blue cells to generate a recommendation.

Sheet Bid Evaluation
A1: BID EVALUATION — WEIGHTED SCORING
A2: CMAR / GMP selection. Yellow = inputs (weights, GMP, qualitative scores 1–10). Price score is auto-normalised (lowest bid = 10). Complements the price-only Bid Leveling tab.
A4: Package: | B4: General Contractor / CMAR — Data Center Template, NoVA
A6: 1 · EVALUATION CRITERIA & WEIGHTS
C7: Criterion → | D7: Price | E7: Schedule | F7: Technical | G7: Experience | H7: Safety (EMR) | I7: Financial
B8: Weights (must total 100%): | D8: 0.4 | E8: 0.15 | F8: 0.15 | G8: 0.15 | H8: 0.1 | I8: 0.05 | J8: =SUM(D8:I8) -> 1 | K8: =IF(ROUND(J8,4)=1,"✓","✗") -> ✓
A10: 2 · BIDDER SCORING (qualitative scores 1–10) | M10: WEIGHTED CONTRIBUTION BY CRITERION
A11: # | B11: Bidder (CM) | C11: GMP Bid | D11: Price Score | E11: Sched. | F11: Tech. | G11: Exp. | H11: Safety | I11: Fin. | J11: Weighted Score | K11: Rank | M11: Bidder | N11: Price | O11: Schedule | P11: Technical | Q11: Experience | R11: Safety | S11: Financial
A12: 1 | B12: ='Bid Leveling'!D12 -> National Build Group | C12: 1640000000 | D12: =ROUND(MIN($C$12:$C$15)/C12*10,2) -> 9.66 | E12: 8 | F12: 9 | G12: 9 | H12: 8 | I12: 9 | J12: =SUMPRODUCT($D$8:$I$8,D12:I12) -> 9.014 | K12: =RANK(J12,$J$12:$J$15) -> 2 | M12: =LEFT(B12,8) -> National | N12: =$D$8*D12 -> 3.864 | O12: =$E$8*E12 -> 1.2 | P12: =$F$8*F12 -> 1.35 | Q12: =$G$8*G12 -> 1.35 | R12: =$H$8*H12 -> 0.8 | S12: =$I$8*I12 -> 0.45
A13: 2 | B13: ='Bid Leveling'!E12 -> Western Constructors | C13: 1585000000 | D13: =ROUND(MIN($C$12:$C$15)/C13*10,2) -> 10 | E13: 7 | F13: 7 | G13: 8 | H13: 9 | I13: 7 | J13: =SUMPRODUCT($D$8:$I$8,D13:I13) -> 8.55 | K13: =RANK(J13,$J$12:$J$15) -> 4 | M13: =LEFT(B13,8) -> Western | N13: =$D$8*D13 -> 4 | O13: =$E$8*E13 -> 1.05 | P13: =$F$8*F13 -> 1.05 | Q13: =$G$8*G13 -> 1.2 | R13: =$H$8*H13 -> 0.9 | S13: =$I$8*I13 -> 0.35
A14: 3 | B14: ='Bid Leveling'!F12 -> Metro Mission Critical | C14: 1612000000 | D14: =ROUND(MIN($C$12:$C$15)/C14*10,2) -> 9.83 | E14: 9 | F14: 8 | G14: 7 | H14: 7 | I14: 8 | J14: =SUMPRODUCT($D$8:$I$8,D14:I14) -> 8.632 | K14: =RANK(J14,$J$12:$J$15) -> 3 | M14: =LEFT(B14,8) -> Metro Mi | N14: =$D$8*D14 -> 3.932 | O14: =$E$8*E14 -> 1.35 | P14: =$F$8*F14 -> 1.2 | Q14: =$G$8*G14 -> 1.05 | R14: =$H$8*H14 -> 0.7 | S14: =$I$8*I14 -> 0.4
A15: 4 | B15: ='Bid Leveling'!G12 -> Pinnacle CM (DC specialist) | C15: 1675000000 | D15: =ROUND(MIN($C$12:$C$15)/C15*10,2) -> 9.46 | E15: 8 | F15: 9 | G15: 10 | H15: 9 | I15: 10 | J15: =SUMPRODUCT($D$8:$I$8,D15:I15) -> 9.234 | K15: =RANK(J15,$J$12:$J$15) -> 1 | M15: =LEFT(B15,8) -> Pinnacle | N15: =$D$8*D15 -> 3.784 | O15: =$E$8*E15 -> 1.2 | P15: =$F$8*F15 -> 1.35 | Q15: =$G$8*G15 -> 1.5 | R15: =$H$8*H15 -> 0.9 | S15: =$I$8*I15 -> 0.5
A17: 3 · RECOMMENDATION
A18: Recommended award: | C18: =INDEX(B12:B15,MATCH(MAX(J12:J15),J12:J15,0)) -> Pinnacle CM (DC specialist)
A19: Winning weighted score: | C19: =MAX(J12:J15) -> 9.234
A20: Their GMP vs low bid: | C20: =TEXT(INDEX(C12:C15,MATCH(MAX(J12:J15),J12:J15,0))-MIN(C12:C15),"$#,##0,,")&"M above lowest bid (quality-justified premium)" -> $90M above lowest bid (quality-justified premium)
A22: 4 · GMP VARIANCE ANALYSIS
A23: # | B23: General Contractor | C23: GMP Bid | D23: Leveled Constr. (Bid Leveling) | E23: Implied GC Fee / Soft | F23: vs Low GMP ($) | G23: vs Low GMP (%) | H23: vs Avg GMP (%) | I23: vs Trades EE (%) | J23: Price Rank
A24: =A12 -> 1 | B24: =B12 -> National Build Group | C24: =C12 -> 1640000000 | D24: ='Bid Leveling'!D37 -> 0 | E24: =IF(D24=0,"—",C24-D24) -> — | F24: =C24-MIN($C$12:$C$15) -> 55000000 | G24: =C24/MIN($C$12:$C$15)-1 -> 0.034700315 | H24: =C24/AVERAGE($C$12:$C$15)-1 -> 0.0073710074 | I24: =C24/$C$62-1 -> 0.68163176 | J24: =RANK(C24,$C$24:$C$27,1) -> 3
A25: =A13 -> 2 | B25: =B13 -> Western Constructors | C25: =C13 -> 1585000000 | D25: ='Bid Leveling'!E37 -> 0 | E25: =IF(D25=0,"—",C25-D25) -> — | F25: =C25-MIN($C$12:$C$15) -> 0 | G25: =C25/MIN($C$12:$C$15)-1 -> 0 | H25: =C25/AVERAGE($C$12:$C$15)-1 -> -0.026412776 | I25: =C25/$C$62-1 -> 0.62523557 | J25: =RANK(C25,$C$24:$C$27,1) -> 1
A26: =A14 -> 3 | B26: =B14 -> Metro Mission Critical | C26: =C14 -> 1612000000 | D26: ='Bid Leveling'!F37 -> 0 | E26: =IF(D26=0,"—",C26-D26) -> — | F26: =C26-MIN($C$12:$C$15) -> 27000000 | G26: =C26/MIN($C$12:$C$15)-1 -> 0.0170347 | H26: =C26/AVERAGE($C$12:$C$15)-1 -> -0.0098280098 | I26: =C26/$C$62-1 -> 0.65292097 | J26: =RANK(C26,$C$24:$C$27,1) -> 2
A27: =A15 -> 4 | B27: =B15 -> Pinnacle CM (DC specialist) | C27: =C15 -> 1675000000 | D27: ='Bid Leveling'!G37 -> 0 | E27: =IF(D27=0,"—",C27-D27) -> — | F27: =C27-MIN($C$12:$C$15) -> 90000000 | G27: =C27/MIN($C$12:$C$15)-1 -> 0.056782334 | H27: =C27/AVERAGE($C$12:$C$15)-1 -> 0.028869779 | I27: =C27/$C$62-1 -> 0.71752024 | J27: =RANK(C27,$C$24:$C$27,1) -> 4
B29: Low GMP | C29: =MIN(C12:C15) -> 1585000000
B30: Average GMP | C30: =AVERAGE(C12:C15) -> 1628000000
B31: High GMP | C31: =MAX(C12:C15) -> 1675000000
B32: Spread (High − Low) | C32: =C31-C29 -> 90000000 | D32: =C32/C29 -> 0.056782334
B33: Engineer's Estimate (Trades, excl. Soft Costs) | C33: =$C$62 -> 9.7524324e+08
A35: Leveled Constr. and Implied GC Fee populate from Bid Leveling once GC trade bids are entered. 'vs Trades EE' compares each GMP to the construction-trades estimate (excl. owner soft costs, $975M).
A37: 5 · TRADE-BY-TRADE BID DETAIL — GC-BID TRADES (EXCL. SOFT COSTS)
B38: Trade / Division | C38: Eng. Estimate | D38: ='Bid Leveling'!D12 -> National Build Group | E38: ='Bid Leveling'!E12 -> Western Constructors | F38: ='Bid Leveling'!F12 -> Metro Mission Critical | G38: ='Bid Leveling'!G12 -> Pinnacle CM (DC specialist) | H38: Low Bid | I38: Δ vs EE
B39: ='Bid Leveling'!B13 -> General Conditions & Requirements | C39: ='Bid Leveling'!C13 -> 42983031 | D39: ='Bid Leveling'!D13 | E39: ='Bid Leveling'!E13 | F39: ='Bid Leveling'!F13 | G39: ='Bid Leveling'!G13 | H39: ='Bid Leveling'!H13 | I39: ='Bid Leveling'!I13
B40: ='Bid Leveling'!B14 -> Commissioning & Testing | C40: ='Bid Leveling'!C14 -> 47367292 | D40: ='Bid Leveling'!D14 | E40: ='Bid Leveling'!E14 | F40: ='Bid Leveling'!F14 | G40: ='Bid Leveling'!G14 | H40: ='Bid Leveling'!H14 | I40: ='Bid Leveling'!I14
B41: ='Bid Leveling'!B15 -> Div 03 — Concrete | C41: ='Bid Leveling'!C15 -> 33466040 | D41: ='Bid Leveling'!D15 | E41: ='Bid Leveling'!E15 | F41: ='Bid Leveling'!F15 | G41: ='Bid Leveling'!G15 | H41: ='Bid Leveling'!H15 | I41: ='Bid Leveling'!I15
B42: ='Bid Leveling'!B16 -> Div 04 — Masonry | C42: ='Bid Leveling'!C16 -> 5656068 | D42: ='Bid Leveling'!D16 | E42: ='Bid Leveling'!E16 | F42: ='Bid Leveling'!F16 | G42: ='Bid Leveling'!G16 | H42: ='Bid Leveling'!H16 | I42: ='Bid Leveling'!I16
B43: ='Bid Leveling'!B17 -> Div 05 — Metals / Structural Steel | C43: ='Bid Leveling'!C17 -> 40836400 | D43: ='Bid Leveling'!D17 | E43: ='Bid Leveling'!E17 | F43: ='Bid Leveling'!F17 | G43: ='Bid Leveling'!G17 | H43: ='Bid Leveling'!H17 | I43: ='Bid Leveling'!I17
B44: ='Bid Leveling'!B18 -> Div 06 — Wood, Plastics & Composites | C44: ='Bid Leveling'!C18 -> 1233678.6 | D44: ='Bid Leveling'!D18 | E44: ='Bid Leveling'!E18 | F44: ='Bid Leveling'!F18 | G44: ='Bid Leveling'!G18 | H44: ='Bid Leveling'!H18 | I44: ='Bid Leveling'!I18
B45: ='Bid Leveling'!B19 -> Div 07 — Thermal & Moisture Protection | C45: ='Bid Leveling'!C19 -> 38165651 | D45: ='Bid Leveling'!D19 | E45: ='Bid Leveling'!E19 | F45: ='Bid Leveling'!F19 | G45: ='Bid Leveling'!G19 | H45: ='Bid Leveling'!H19 | I45: ='Bid Leveling'!I19
B46: ='Bid Leveling'!B20 -> Div 08 — Openings | C46: ='Bid Leveling'!C20 -> 13742210 | D46: ='Bid Leveling'!D20 | E46: ='Bid Leveling'!E20 | F46: ='Bid Leveling'!F20 | G46: ='Bid Leveling'!G20 | H46: ='Bid Leveling'!H20 | I46: ='Bid Leveling'!I20
B47: ='Bid Leveling'!B21 -> Div 09 — Finishes | C47: ='Bid Leveling'!C21 -> 33189552 | D47: ='Bid Leveling'!D21 | E47: ='Bid Leveling'!E21 | F47: ='Bid Leveling'!F21 | G47: ='Bid Leveling'!G21 | H47: ='Bid Leveling'!H21 | I47: ='Bid Leveling'!I21
B48: ='Bid Leveling'!B22 -> Div 10 — Specialties | C48: ='Bid Leveling'!C22 -> 4010233.4 | D48: ='Bid Leveling'!D22 | E48: ='Bid Leveling'!E22 | F48: ='Bid Leveling'!F22 | G48: ='Bid Leveling'!G22 | H48: ='Bid Leveling'!H22 | I48: ='Bid Leveling'!I22
B49: ='Bid Leveling'!B23 -> Div 11 — Equipment | C49: ='Bid Leveling'!C23 -> 1525590 | D49: ='Bid Leveling'!D23 | E49: ='Bid Leveling'!E23 | F49: ='Bid Leveling'!F23 | G49: ='Bid Leveling'!G23 | H49: ='Bid Leveling'!H23 | I49: ='Bid Leveling'!I23
B50: ='Bid Leveling'!B24 -> Div 12 — Furnishings | C50: ='Bid Leveling'!C24 -> 1217056.5 | D50: ='Bid Leveling'!D24 | E50: ='Bid Leveling'!E24 | F50: ='Bid Leveling'!F24 | G50: ='Bid Leveling'!G24 | H50: ='Bid Leveling'!H24 | I50: ='Bid Leveling'!I24
... B61: ='Bid Leveling'!B35 -> Div 33 — Utilities | C61: ='Bid Leveling'!C35 -> 63598602 | D61: ='Bid Leveling'!D35 | E61: ='Bid Leveling'!E35 | F61: ='Bid Leveling'!F35 | G61: ='Bid Leveling'!G35 | H61: ='Bid Leveling'!H35 | I61: ='Bid Leveling'!I35
B62: TOTAL — GC-BID TRADES (EXCL. SOFT COSTS) | C62: =SUM(C39:C61) -> 9.7524324e+08 | D62: =SUM(D39:D61) -> 0 | E62: =SUM(E39:E61) -> 0 | F62: =SUM(F39:F61) -> 0 | G62: =SUM(G39:G61) -> 0 | H62: =SUM(H39:H61) -> 0 | I62: =IF(OR(H62=0,C62=0),"",(H62-C62)/C62)
A64: 6 · GENERAL CONTRACTOR QUALIFICATIONS & DUE DILIGENCE
B65: Firm qualifications captured per bidding GC — complete during due diligence. Any "Fail" on a mandatory gate (bottom row) disqualifies regardless of weighted score.
B66: Qualification / Attribute | C66: Min Requirement | D66: =B12 -> National Build Group | E66: =B13 -> Western Constructors | F66: =B14 -> Metro Mission Critical | G66: =B15 -> Pinnacle CM (DC specialist)
B67: Firm HQ / local office presence
B68: Years in business
B69: Annual revenue ($M)
B70: Bonding capacity — aggregate ($M)
B71: Surety & bond rating
B72: Current backlog ($M)
B73: Data-center projects completed (#)
B74: DC capacity delivered (MW)
B75: Self-perform capability (% of work)
B76: Safety EMR (3-yr avg)
B77: Key project executive / PM assigned
B78: Mandatory gate — insurance, licensing & bonding

Sheet Procurement & Long-Lead
A1: PROCUREMENT & LONG-LEAD TRACKER
A2: Order-By = Required-On-Site − (lead + buffer). Long leads on transformers, gear and generators mean several packages must be ordered before mobilization.
A4: 1 · STATUS PARAMETERS
A5: Data Date: | B5: 46204
A6: Project Start (ref): | B6: ='Construction Budget'!F3 -> 46143
A7: Annual escalation (ref): | B7: ='Construction Budget'!H7 -> 0.035
A9: 2 · LONG-LEAD EQUIPMENT REGISTER
A10: Equipment Package | B10: Div | C10: Supply Responsibility | D10: Budget | E10: Lead (wks) | F10: Buffer (wks) | G10: Required On-Site | H10: Order-By Date | I10: Days to Order-By | J10: Escal. Exposure | K10: Status | L10: Procurement Flag | M10: Typical OEM / Vendor Pool | N10: Installed By | O10: Deposit % | P10: Deposit Due | Q10: Supply-Chain Risk
A11: Structural Steel | B11: 5 | C11: GC-Supplied | D11: 35000000 | E11: 22 | F11: 4 | G11: 46357 | H11: =G11-(E11+F11)*7 -> 46175 | I11: =H11-$B$5 -> -29 | J11: =D11*$B$7*E11/52 -> 518269.23 | K11: PO Released | L11: =IF(OR(K11="PO Released",K11="In Fabrication",K11="Shipped",K11="Delivered"),"✓ Ordered",IF($B$5>H11,"● LATE — order now",IF(H11-$B$5<=30,"▲ Order ≤30 days","On track"))) -> ✓ Ordered | M11: Mill + AISC fabricator (bid) | N11: GC self-perform / steel erector | O11: 0.15 | P11: =D11*O11 -> 5250000 | Q11: Med — mill rolling + fab capacity
A12: Raised Access Floor & Aisle Containment | B12: 9 | C12: GC-Supplied | D12: 21000000 | E12: 18 | F12: 4 | G12: 46692 | H12: =G12-(E12+F12)*7 -> 46538 | I12: =H12-$B$5 -> 334 | J12: =D12*$B$7*E12/52 -> 254423.08 | K12: Not Started | L12: =IF(OR(K12="PO Released",K12="In Fabrication",K12="Shipped",K12="Delivered"),"✓ Ordered",IF($B$5>H12,"● LATE — order now",IF(H12-$B$5<=30,"▲ Order ≤30 days","On track"))) -> On track | M12: Tate / ASM / Polargy / Subzero | N12: GC self-perform — floor & containment | O12: 0.2 | P12: =D12*O12 -> 4200000 | Q12: Low — stock product
A13: Clean-Agent / Pre-Action Fire Suppression | B13: 21 | C13: Owner (OFCI) | D13: 15000000 | E13: 24 | F13: 4 | G13: 46720 | H13: =G13-(E13+F13)*7 -> 46524 | I13: =H13-$B$5 -> 320 | J13: =D13*$B$7*E13/52 -> 242307.69 | K13: Not Started | L13: =IF(OR(K13="PO Released",K13="In Fabrication",K13="Shipped",K13="Delivered"),"✓ Ordered",IF($B$5>H13,"● LATE — order now",IF(H13-$B$5<=30,"▲ Order ≤30 days","On track"))) -> On track | M13: Fike / Kidde / Victaulic / Viking | N13: Fire-protection sub — pipe, cylinders, detection | O13: 0.15 | P13: =D13*O13 -> 2250000 | Q13: Low — domestic supply
A14: CRAH / In-Row Cooling Units | B14: 23 | C14: Owner (OFCI) | D14: 60000000 | E14: 28 | F14: 4 | G14: 46753 | H14: =G14-(E14+F14)*7 -> 46529 | I14: =H14-$B$5 -> 325 | J14: =D14*$B$7*E14/52 -> 1130769.2 | K14: Not Started | L14: =IF(OR(K14="PO Released",K14="In Fabrication",K14="Shipped",K14="Delivered"),"✓ Ordered",IF($B$5>H14,"● LATE — order now",IF(H14-$B$5<=30,"▲ Order ≤30 days","On track"))) -> On track | M14: Vertiv / Stulz / Schneider / Trane | N14: Mechanical sub — floor set & pipe | O14: 0.2 | P14: =D14*O14 -> 12000000 | Q14: Med — coil + EC fan supply
A15: Centrifugal Chillers | B15: 23 | C15: Owner (OFCI) | D15: 50000000 | E15: 45 | F15: 6 | G15: 46661 | H15: =G15-(E15+F15)*7 -> 46304 | I15: =H15-$B$5 -> 100 | J15: =D15*$B$7*E15/52 -> 1514423.1 | K15: Not Started | L15: =IF(OR(K15="PO Released",K15="In Fabrication",K15="Shipped",K15="Delivered"),"✓ Ordered",IF($B$5>H15,"● LATE — order now",IF(H15-$B$5<=30,"▲ Order ≤30 days","On track"))) -> On track | M15: Trane / Carrier / JCI / Daikin | N15: Mechanical sub — rig & pipe; OEM startup | O15: 0.3 | P15: =D15*O15 -> 15000000 | Q15: High — compressor + 45-wk lead
A16: Direct Liquid Cooling / CDUs | B16: 23 | C16: Owner (OFCI) | D16: 46000000 | E16: 34 | F16: 6 | G16: 46784 | H16: =G16-(E16+F16)*7 -> 46504 | I16: =H16-$B$5 -> 300 | J16: =D16*$B$7*E16/52 -> 1052692.3 | K16: Not Started | L16: =IF(OR(K16="PO Released",K16="In Fabrication",K16="Shipped",K16="Delivered"),"✓ Ordered",IF($B$5>H16,"● LATE — order now",IF(H16-$B$5<=30,"▲ Order ≤30 days","On track"))) -> On track | M16: Vertiv / CoolIT / Motivair / Boyd | N16: Mechanical/IT sub — manifold & CDU | O16: 0.3 | P16: =D16*O16 -> 13800000 | Q16: High — emerging supply, few OEMs
A17: Thermal Energy Storage | B17: 23 | C17: Owner (OFCI) | D17: 43000000 | E17: 30 | F17: 6 | G17: 46753 | H17: =G17-(E17+F17)*7 -> 46501 | I17: =H17-$B$5 -> 297 | J17: =D17*$B$7*E17/52 -> 868269.23 | K17: Not Started | L17: =IF(OR(K17="PO Released",K17="In Fabrication",K17="Shipped",K17="Delivered"),"✓ Ordered",IF($B$5>H17,"● LATE — order now",IF(H17-$B$5<=30,"▲ Order ≤30 days","On track"))) -> On track | M17: DN Tanks / CB&I / Trane TES | N17: Civil/Mech sub — tank & glycol fill | O17: 0.25 | P17: =D17*O17 -> 10750000 | Q17: Med — site-built tank schedule
A18: Air-Cooled Chillers (N+1 backup) | B18: 23 | C18: Owner (OFCI) | D18: 36000000 | E18: 40 | F18: 6 | G18: 46692 | H18: =G18-(E18+F18)*7 -> 46370 | I18: =H18-$B$5 -> 166 | J18: =D18*$B$7*E18/52 -> 969230.77 | K18: Not Started | L18: =IF(OR(K18="PO Released",K18="In Fabrication",K18="Shipped",K18="Delivered"),"✓ Ordered",IF($B$5>H18,"● LATE — order now",IF(H18-$B$5<=30,"▲ Order ≤30 days","On track"))) -> On track | M18: Trane / Carrier / Daikin / JCI | N18: Mechanical sub — yard rig & pipe | O18: 0.3 | P18: =D18*O18 -> 10800000 | Q18: High — compressor + 40-wk lead
A19: Air-Side Economizers / Evaporative Units | B19: 23 | C19: Owner (OFCI) | D19: 24000000 | E19: 32 | F19: 6 | G19: 46720 | H19: =G19-(E19+F19)*7 -> 46454 | I19: =H19-$B$5 -> 250 | J19: =D19*$B$7*E19/52 -> 516923.08 | K19: Not Started | L19: =IF(OR(K19="PO Released",K19="In Fabrication",K19="Shipped",K19="Delivered"),"✓ Ordered",IF($B$5>H19,"● LATE — order now",IF(H19-$B$5<=30,"▲ Order ≤30 days","On track"))) -> On track | M19: Munters / Nortek / Stulz | N19: Mechanical sub — roof rig & duct | O19: 0.25 | P19: =D19*O19 -> 6000000 | Q19: Med — engineered units
A20: Air Handling Units (AHUs) | B20: 23 | C20: Owner (OFCI) | D20: 20000000 | E20: 30 | F20: 4 | G20: 46692 | H20: =G20-(E20+F20)*7 -> 46454 | I20: =H20-$B$5 -> 250 | J20: =D20*$B$7*E20/52 -> 403846.15 | K20: Not Started | L20: =IF(OR(K20="PO Released",K20="In Fabrication",K20="Shipped",K20="Delivered"),"✓ Ordered",IF($B$5>H20,"● LATE — order now",IF(H20-$B$5<=30,"▲ Order ≤30 days","On track"))) -> On track | M20: Daikin / Trane / Nailor / Temtrol | N20: Mechanical sub — rig, duct & pipe | O20: 0.2 | P20: =D20*O20 -> 4000000 | Q20: Med — coil & fan lead
A21: Chilled-Water & Condenser Pumps / Skids | B21: 23 | C21: Owner (OFCI) | D21: 16000000 | E21: 28 | F21: 4 | G21: 46661 | H21: =G21-(E21+F21)*7 -> 46437 | I21: =H21-$B$5 -> 233 | J21: =D21*$B$7*E21/52 -> 301538.46 | K21: Not Started | L21: =IF(OR(K21="PO Released",K21="In Fabrication",K21="Shipped",K21="Delivered"),"✓ Ordered",IF($B$5>H21,"● LATE — order now",IF(H21-$B$5<=30,"▲ Order ≤30 days","On track"))) -> On track | M21: Bell & Gossett / Armstrong / Grundfos | N21: Mechanical sub — skid set & align | O21: 0.2 | P21: =D21*O21 -> 3200000 | Q21: Med — motor & VFD supply
A22: Cooling Towers | B22: 23 | C22: Owner (OFCI) | D22: 14000000 | E22: 26 | F22: 4 | G22: 46692 | H22: =G22-(E22+F22)*7 -> 46482 | I22: =H22-$B$5 -> 278 | J22: =D22*$B$7*E22/52 -> 245000 | K22: Not Started | L22: =IF(OR(K22="PO Released",K22="In Fabrication",K22="Shipped",K22="Delivered"),"✓ Ordered",IF($B$5>H22,"● LATE — order now",IF(H22-$B$5<=30,"▲ Order ≤30 days","On track"))) -> On track | M22: BAC / Evapco / SPX | N22: Mechanical sub — roof/yard rig & pipe | O22: 0.2 | P22: =D22*O22 -> 2800000 | Q22: Med — fabrication slot
... A39: Security System (Access Control & CCTV) | B39: 28 | C39: Owner (OFCI) | D39: 11000000 | E39: 22 | F39: 4 | G39: 46784 | H39: =G39-(E39+F39)*7 -> 46602 | I39: =H39-$B$5 -> 398 | J39: =D39*$B$7*E39/52 -> 162884.62 | K39: Not Started | L39: =IF(OR(K39="PO Released",K39="In Fabrication",K39="Shipped",K39="Delivered"),"✓ Ordered",IF($B$5>H39,"● LATE — order now",IF(H39-$B$5<=30,"▲ Order ≤30 days","On track"))) -> On track | M39: Genetec / Lenel / Avigilon / Axis | N39: Low-voltage/security sub — devices & head-end | O39: 0.15 | P39: =D39*O39 -> 1650000 | Q39: Low — broad supplier base
A40: TOTAL — tracked long-lead value | D40: =SUM(D11:D39) -> 1087000000 | J40: =SUM(J11:J39) -> 30288462 | P40: =SUM(P11:P39) -> 264400000
A42: 3 · PROCUREMENT SUMMARY
A43: Tracked long-lead value | B43: =D40 -> 1087000000
A44: Packages past Order-By (LATE) | B44: =COUNTIF(L11:L39,"● LATE*") -> 5
A45: Packages to order within 30 days | B45: =COUNTIF(L11:L39,"▲ Order*") -> 1
A46: Total escalation exposure | B46: =J40 -> 30288462
A47: Earliest Order-By date | B47: =MIN(H11:H39) -> 46029
A48: Owner-Supplied (OFCI) value | B48: =SUMIF($C$11:$C$39,"Owner*",$D$11:$D$39) -> 1031000000
A49: Owner-Supplied packages | B49: =COUNTIF($C$11:$C$39,"Owner*") -> 27
A50: Owner-Supplied escalation exposure | B50: =SUMIF($C$11:$C$39,"Owner*",$J$11:$J$39) -> 29515769
A51: GC-Supplied value | B51: =SUMIF($C$11:$C$39,"GC*",$D$11:$D$39) -> 56000000
A52: Deposit cash due at PO (all) | B52: =P40 -> 264400000
A53: — OFCI deposit cash due | B53: =SUMIF($C$11:$C$39,"Owner*",$P$11:$P$39) -> 254950000
A54: — GC-Supplied deposit cash due | B54: =SUMIF($C$11:$C$39,"GC*",$P$11:$P$39) -> 9450000
A55: High supply-chain-risk packages | B55: =COUNTIF($Q$11:$Q$39,"High*") -> 8

Sheet Construction Schedule
A1: CONSTRUCTION SCHEDULE — CRADLE TO GRAVE (Site Selection → Site Opening)
A2: MS-Project-style master schedule with CPM logic & procurement-driven delivery→install constraints. Durations (blue) are inputs; installs start at the LATER of their sequence predecessor or equipment delivery. Construction NTP is tied to Construction Budget!F3.
A3: Site Selection Start: | B3: ='Construction Budget'!F3-(D8+D9+D10+D11+D17+D19+D22+D23) -> 45658 | E3: Phase | G3: Critical task
A4: Data Date: | B4: 46204 | E4: Task (float) | G4: Milestone | I4: Equip delivery
A5: Construction Start (NTP): | B5: ='Construction Budget'!F3 -> 46143 | C5: Sched. NTP / Mobilize: | D5: =E62 -> 46143 | E5: Tie? | F5: =IF(D5=B5,"✓ Tied","⚠ off "&TEXT(D5-B5,"0")&"d") -> ✓ Tied | G5: Target Completion: | H5: ='Construction Budget'!F4 -> Q1 2029 | I5: Scheduled Go-Live: | J5: =F166 -> 47173 | K5: Go-Live vs Target: | L5: =IF(J5<=DATE(2029,3,31),"✓ On/Before "&H5,"⚠ "&TEXT(J5,"mmm-yy")&" (after "&H5&")") -> ✓ On/Before Q1 2029
A6: WBS | B6: Task / Activity | C6: Trade / Crew | D6: Dur (days) | E6: Start | F6: Finish | G6: Baseline Finish | H6: Var (d) | I6: Pred | J6: Float (d) | K6: Critical? | L6: % Comp | M6: Status | N6: Owner | O6: =DATE(YEAR($B$3),MONTH($B$3),1) -> 45658 | P6: =EDATE(O6,1) -> 45689 | Q6: =EDATE(P6,1) -> 45717 | R6: =EDATE(Q6,1) -> 45748 | S6: =EDATE(R6,1) -> 45778 | T6: =EDATE(S6,1) -> 45809 | U6: =EDATE(T6,1) -> 45839 | V6: =EDATE(U6,1) -> 45870 | W6: =EDATE(V6,1) -> 45901 | ... BV6: =EDATE(BU6,1) -> 47453
A7: 1 | B7: Site Selection & Feasibility | D7: =F7-E7 -> 155 | E7: =MIN(E8:E15) -> 45658 | F7: =MAX(F8:F15) -> 45813 | G7: 45813 | H7: =IF($G7="","",$F7-$G7) -> 0 | L7: =IFERROR(SUMPRODUCT($D8:$D15,$L8:$L15)/SUM($D8:$D15),0) -> 1 | M7: =IF(L7>=1,"Complete",IF(L7>0,"In Progress","Not Started")) -> Complete | N7: Developer
A8: 1.1 | B8: Market & power availability study | C8: Site selection | D8: 45 | E8: =$B$3 -> 45658 | F8: =E8+D8 -> 45703 | G8: 45703 | H8: =IF($G8="","",$F8-$G8) -> 0 | I8: — | J8: =MIN(E9)-F8 -> 0 | K8: =IF($D8="","",IF($J8<=0,"● CRITICAL","")) -> ● CRITICAL | L8: =IF($B$4>=F8,1,IF($B$4<=E8,0,($B$4-E8)/(F8-E8))) -> 1 | M8: =IF(L8>=1,"Complete",IF(L8>0,"In Progress","Not Started")) -> Complete | N8: Developer
A9: 1.2 | B9: Site identification & shortlisting | C9: Site selection | D9: 30 | E9: =F8 -> 45703 | F9: =E9+D9 -> 45733 | G9: 45733 | H9: =IF($G9="","",$F9-$G9) -> 0 | I9: 1.1 | J9: =MIN(E10)-F9 -> 0 | K9: =IF($D9="","",IF($J9<=0,"● CRITICAL","")) -> ● CRITICAL | L9: =IF($B$4>=F9,1,IF($B$4<=E9,0,($B$4-E9)/(F9-E9))) -> 1 | M9: =IF(L9>=1,"Complete",IF(L9>0,"In Progress","Not Started")) -> Complete | N9: Developer
A10: 1.3 | B10: Geotechnical & environmental due diligence | C10: Consultants | D10: 60 | E10: =F9 -> 45733 | F10: =E10+D10 -> 45793 | G10: 45793 | H10: =IF($G10="","",$F10-$G10) -> 0 | I10: 1.2 | J10: =MIN(E11)-F10 -> 0 | K10: =IF($D10="","",IF($J10<=0,"● CRITICAL","")) -> ● CRITICAL | L10: =IF($B$4>=F10,1,IF($B$4<=E10,0,($B$4-E10)/(F10-E10))) -> 1 | M10: =IF(L10>=1,"Complete",IF(L10>0,"In Progress","Not Started")) -> Complete | N10: Owner
A11: 1.4 | B11: Fatal-flaw & constructability review | C11: CM / A-E | D11: 20 | E11: =F10 -> 45793 | F11: =E11+D11 -> 45813 | G11: 45813 | H11: =IF($G11="","",$F11-$G11) -> 0 | I11: 1.3 | J11: =MIN(E15)-F11 -> 0 | K11: =IF($D11="","",IF($J11<=0,"● CRITICAL","")) -> ● CRITICAL | L11: =IF($B$4>=F11,1,IF($B$4<=E11,0,($B$4-E11)/(F11-E11))) -> 1 | M11: =IF(L11>=1,"Complete",IF(L11>0,"In Progress","Not Started")) -> Complete | N11: Owner / CM
A12: 1.6 | B12: Preliminary ALTA survey & title review | C12: Survey | D12: 30 | E12: =F9 -> 45733 | F12: =E12+D12 -> 45763 | G12: 45763 | H12: =IF($G12="","",$F12-$G12) -> 0 | I12: 1.2 | J12: =$F$166-F12 -> 1410 | K12: =IF($D12="","",IF($J12<=0,"● CRITICAL","")) | L12: =IF($B$4>=F12,1,IF($B$4<=E12,0,($B$4-E12)/(F12-E12))) -> 1 | M12: =IF(L12>=1,"Complete",IF(L12>0,"In Progress","Not Started")) -> Complete | N12: Owner / Legal
A13: 1.7 | B13: Economic incentives & tax abatement negotiation | C13: Developer | D13: 60 | E13: =F8 -> 45703 | F13: =E13+D13 -> 45763 | G13: 45763 | H13: =IF($G13="","",$F13-$G13) -> 0 | I13: 1.1 | J13: =$F$166-F13 -> 1410 | K13: =IF($D13="","",IF($J13<=0,"● CRITICAL","")) | L13: =IF($B$4>=F13,1,IF($B$4<=E13,0,($B$4-E13)/(F13-E13))) -> 1 | M13: =IF(L13>=1,"Complete",IF(L13>0,"In Progress","Not Started")) -> Complete | N13: Developer
A14: 1.8 | B14: Preliminary power interconnection study | C14: Utility eng. | D14: 75 | E14: =F8 -> 45703 | F14: =E14+D14 -> 45778 | G14: 45778 | H14: =IF($G14="","",$F14-$G14) -> 0 | I14: 1.1 | J14: =$F$166-F14 -> 1395 | K14: =IF($D14="","",IF($J14<=0,"● CRITICAL","")) | L14: =IF($B$4>=F14,1,IF($B$4<=E14,0,($B$4-E14)/(F14-E14))) -> 1 | M14: =IF(L14>=1,"Complete",IF(L14>0,"In Progress","Not Started")) -> Complete | N14: Owner / Utility
A15: 1.5 | B15: ◆ Site selection decision | C15: — | D15: 0 | E15: =F11 -> 45813 | F15: =E15+D15 -> 45813 | G15: 45813 | H15: =IF($G15="","",$F15-$G15) -> 0 | I15: 1.4 | J15: =MIN(E17)-F15 -> 0 | K15: =IF($D15="","",IF($J15<=0,"● CRITICAL","")) -> ● CRITICAL | L15: =IF($B$4>=F15,1,IF($B$4<=E15,0,($B$4-E15)/(F15-E15))) -> 1 | M15: =IF(L15>=1,"Complete",IF(L15>0,"In Progress","Not Started")) -> Complete | N15: Owner
A16: 2 | B16: Acquisition & Entitlements | D16: =F16-E16 -> 330 | E16: =MIN(E17:E27) -> 45813 | F16: =MAX(F17:F27) -> 46143 | G16: 46143 | H16: =IF($G16="","",$F16-$G16) -> 0 | L16: =IFERROR(SUMPRODUCT($D17:$D27,$L17:$L27)/SUM($D17:$D27),0) -> 1 | M16: =IF(L16>=1,"Complete",IF(L16>0,"In Progress","Not Started")) -> Complete | N16: Owner
A17: 2.1 | B17: Purchase & Sale negotiation | C17: Legal | D17: 45 | E17: =F15 -> 45813 | F17: =E17+D17 -> 45858 | G17: 45858 | H17: =IF($G17="","",$F17-$G17) -> 0 | I17: 1.5 | J17: =MIN(E18)-F17 -> 0 | K17: =IF($D17="","",IF($J17<=0,"● CRITICAL","")) -> ● CRITICAL | L17: =IF($B$4>=F17,1,IF($B$4<=E17,0,($B$4-E17)/(F17-E17))) -> 1 | M17: =IF(L17>=1,"Complete",IF(L17>0,"In Progress","Not Started")) -> Complete | N17: Owner / Legal
A18: 2.2 | B18: ◆ Land acquisition / closing | C18: — | D18: 0 | E18: =F17 -> 45858 | F18: =E18+D18 -> 45858 | G18: 45858 | H18: =IF($G18="","",$F18-$G18) -> 0 | I18: 2.1 | J18: =MIN(E19,E20,E21,E29)-F18 -> 0 | K18: =IF($D18="","",IF($J18<=0,"● CRITICAL","")) -> ● CRITICAL | L18: =IF($B$4>=F18,1,IF($B$4<=E18,0,($B$4-E18)/(F18-E18))) -> 1 | M18: =IF(L18>=1,"Complete",IF(L18>0,"In Progress","Not Started")) -> Complete | N18: Owner
A19: 2.3 | B19: Zoning & land-use approvals | C19: Land-use | D19: 120 | E19: =F18 -> 45858 | F19: =E19+D19 -> 45978 | G19: 45978 | H19: =IF($G19="","",$F19-$G19) -> 0 | I19: 2.2 | J19: =MIN(E22)-F19 -> 0 | K19: =IF($D19="","",IF($J19<=0,"● CRITICAL","")) -> ● CRITICAL | L19: =IF($B$4>=F19,1,IF($B$4<=E19,0,($B$4-E19)/(F19-E19))) -> 1 | M19: =IF(L19>=1,"Complete",IF(L19>0,"In Progress","Not Started")) -> Complete | N19: Owner
A20: 2.4 | B20: Environmental permits (wetlands, air, NPDES) | C20: Env. consultant | D20: 110 | E20: =F18 -> 45858 | F20: =E20+D20 -> 45968 | G20: 45968 | H20: =IF($G20="","",$F20-$G20) -> 0 | I20: 2.2 | J20: =$F$166-F20 -> 1205 | K20: =IF($D20="","",IF($J20<=0,"● CRITICAL","")) | L20: =IF($B$4>=F20,1,IF($B$4<=E20,0,($B$4-E20)/(F20-E20))) -> 1 | M20: =IF(L20>=1,"Complete",IF(L20>0,"In Progress","Not Started")) -> Complete | N20: Owner
A21: 2.5 | B21: Utility & power capacity agreements | C21: Utility | D21: 150 | E21: =F18 -> 45858 | F21: =E21+D21 -> 46008 | G21: 46008 | H21: =IF($G21="","",$F21-$G21) -> 0 | I21: 2.2 | J21: =$F$166-F21 -> 1165 | K21: =IF($D21="","",IF($J21<=0,"● CRITICAL","")) | L21: =IF($B$4>=F21,1,IF($B$4<=E21,0,($B$4-E21)/(F21-E21))) -> 1 | M21: =IF(L21>=1,"Complete",IF(L21>0,"In Progress","Not Started")) -> Complete | N21: Owner / Utility
A22: 2.6 | B22: Site plan & civil permitting | C22: Civil eng. | D22: 75 | E22: =F19 -> 45978 | F22: =E22+D22 -> 46053 | G22: 46053 | H22: =IF($G22="","",$F22-$G22) -> 0 | I22: 2.3 | J22: =MIN(E23)-F22 -> 0 | K22: =IF($D22="","",IF($J22<=0,"● CRITICAL","")) -> ● CRITICAL | L22: =IF($B$4>=F22,1,IF($B$4<=E22,0,($B$4-E22)/(F22-E22))) -> 1 | M22: =IF(L22>=1,"Complete",IF(L22>0,"In Progress","Not Started")) -> Complete | N22: Owner / Civil
A23: 2.7 | B23: Building permit application & review | C23: A-E / AHJ | D23: 90 | E23: =F22 -> 46053 | F23: =E23+D23 -> 46143 | G23: 46143 | H23: =IF($G23="","",$F23-$G23) -> 0 | I23: 2.6 | J23: =MIN(E27)-F23 -> 0 | K23: =IF($D23="","",IF($J23<=0,"● CRITICAL","")) -> ● CRITICAL | L23: =IF($B$4>=F23,1,IF($B$4<=E23,0,($B$4-E23)/(F23-E23))) -> 1 | M23: =IF(L23>=1,"Complete",IF(L23>0,"In Progress","Not Started")) -> Complete | N23: Architect
A24: 2.9 | B24: Traffic impact study & VDOT approvals | C24: Civil eng. | D24: 90 | E24: =F19 -> 45978 | F24: =E24+D24 -> 46068 | G24: 46068 | H24: =IF($G24="","",$F24-$G24) -> 0 | I24: 2.3 | J24: =$F$166-F24 -> 1105 | K24: =IF($D24="","",IF($J24<=0,"● CRITICAL","")) | L24: =IF($B$4>=F24,1,IF($B$4<=E24,0,($B$4-E24)/(F24-E24))) -> 1 | M24: =IF(L24>=1,"Complete",IF(L24>0,"In Progress","Not Started")) -> Complete | N24: Owner / Civil
